Workbook

Sheet DRI Cost
E2: EZDK DRI Cost / Ton | G2: ERM DRI Cost / Ton
E4: Base | G4: Base
C6: Exchange Rate | D6: EGP/USD | E6: =+DRI!E6 -> 16.2 | G6: =+DRI!E6 -> 16.2
C8: DRI
C10: Total DRi Production Capacity | D10: Tons | E10: 3000000 | G10: 1900000
C11: Capacity Utilization | D11: % | E11: 1 | G11: 1
C13: DRI Selling Price | D13: LE | E13: 6465.4133 | G13: 6465.4133
C15: MRMR | D15: Ratio | E15: =+DRI!E11 -> 1.5 | G15: =+DRI!F11 -> 1.43
C16: Production | D16: Tons | E16: ='EZDK Rebar'!E26+'EZDK Flat'!E26 -> 232533.39 | G16: ='EFS Rebar'!E26+'ESR Rebar'!E28 -> 86694.469
C17: Rquired IOP | D17: Tons | E17: =E16*E15 -> 348800.08 | G17: =G16*G15 -> 123973.09
C19: Consumption
C20: Electricity | D20: Kwh/ton | E20: 41.587557 | G20: 27.124498
C21: Natural Gas | D21: Nm3/ton | E21: =+DRI!E12 -> 292.58 | G21: =+DRI!F12 -> 333
C22: N.Gas | D22: MMBTU/ton | E22: =E21/28 -> 10.449286 | G22: =G21/28 -> 11.892857
C23: Oxygen | D23: Nm3/ton | E23: 14.353732 | G23: 14.353732
C24: Nitrogen | D24: Nm3/ton | E24: 23.733239 | G24: 15.479443
C25: Water | D25: Nm3/ton | E25: 1.1750577 | G25: 1.1750577
C26: Chemicals | D26: ton/ton | E26: 1 | G26: 0.65222629
C27: Spare Parts & Maint | D27: ton/ton | E27: 0 | G27: 0
C28: External Services | D28: ton/ton | E28: 1 | G28: 0.61145318
C29: Other | D29: ton/ton | E29: 1 | G29: 1
C31: Unit Price
C32: Oxide Pellets
C33: IOP Landed Cost | D33: USD/ton | E33: =+DRI!E8 -> 130 | G33: =+DRI!F8 -> 136.62
C34: IOP Landed Cost | D34: EGP/ton | E34: =(E33*E6) -> 2106 | G34: =(G33*G6) -> 2213.244
C35: Electricity | D35: EGP/KWH | E35: 0.90462765 | G35: 0.90462765
C36: Natural Gas | D36: EGP/Nm3 | E36: =+E37*E6/28 -> 3.1821429 | G36: =+G37*G6/28 -> 3.1821429
C37: Natural Gas | D37: USD/MMBTU | E37: =+DRI!E9 -> 5.5 | G37: =+DRI!F9 -> 5.5
C38: Oxygen | D38: EGP/Nm3 | E38: 0.00017117713 | G38: 0.00017117713
C39: Nitrogen | D39: EGP/Nm3 | E39: 0.6568664 | G39: 0.6568664
C40: Water | D40: EGP/Nm3 | E40: 3.9785731 | G40: 3.8890995
C41: Chemicals | D41: LE/ton | E41: 24.778635 | G41: 24.778635
C42: Spare Parts & Maint | D42: LE/ton | E42: 0 | G42: 0
C43: External Services | D43: LE/ton | E43: 42.724299 | G43: 39
C44: Other | D44: LE/ton | E44: 35.802217 | G44: 0
C46: DRI Fixed Exp
C47: Labor Exp | D47: LE | E47: 54011352 | G47: 54011352
C48: DRI Dep | E48: 2.3974642e+08 | G48: 2.3974642e+08
C49: Other Exp (Exluding Dep) | D49: LE | E49: =347999806.05-239746417.14-E47 -> 54242037 | G49: =347999806.05-239746417.14-G47 -> 54242037
C51: Cost Per Ton
C52: IOP | D52: LE/ton | E52: =E34*E15 -> 3159 | G52: =G34*G17/G16 -> 3164.9389
C53: Electricity | D53: LE/KWH | E53: =E20*E35 -> 37.621254 | G53: =G20*G35 -> 24.537571 | H53: =+G53/(SUM($G$53:$G$61)-$G$54) -> 0.30948246 | I53: =H53*$J$62 -> 0.22511533 | J53: =+G53-I53 -> 24.312456 | K53: 24.537571
C54: Natural Gas | D54: LE/NM3 | E54: =E21*E36 -> 931.03136 | G54: =G21*G36 -> 1059.6536
C55: Oxygen | D55: LE/NM3 | E55: =E23*E38 -> 0.0024570306 | G55: =G23*G38 -> 0.0024570306 | H55: =+G55/(SUM($G$53:$G$61)-$G$54) -> 3.0989533e-05 | I55: =H55*$J$62 -> 2.2541565e-05 | J55: =+G55-I55 -> 0.002434489 | K55: 0.00160254
C56: Nitrogen | D56: LE/NM3 | E56: =E24*E39 -> 15.589567 | G56: =G24*G39 -> 10.167926 | H56: =+G56/(SUM($G$53:$G$61)-$G$54) -> 0.12824393 | I56: =H56*$J$62 -> 0.093283722 | J56: =+G56-I56 -> 10.074642 | K56: 10.167926
C57: Water | D57: LE/M3 | E57: =E25*E40 -> 4.6750529 | G57: =G25*G40 -> 4.5699164 | H57: =+G57/(SUM($G$53:$G$61)-$G$54) -> 0.057638507 | I57: =H57*$J$62 -> 0.041925839 | J57: =+G57-I57 -> 4.5279906 | K57: 2.9806196
C58: Chemicals | D58: LE/ton | E58: =E26*E41 -> 24.778635 | G58: =G26*G41 -> 16.161277 | H58: =+G58/(SUM($G$53:$G$61)-$G$54) -> 0.20383565 | I58: =H58*$J$62 -> 0.1482686 | J58: =+G58-I58 -> 16.013009 | K58: 16.161277
C59: Spare Parts & Maint | D59: LE/ton | E59: =E27*E42 -> 0 | G59: =G27*G42 -> 0 | H59: =+G59/(SUM($G$53:$G$61)-$G$54) -> 0 | I59: =H59*$J$62 -> 0 | J59: =+G59-I59 -> 0 | K59: 0
C60: External Services | D60: LE/ton | E60: =E28*E43 -> 42.724299 | G60: =G28*G43 -> 23.846674 | H60: =+G60/(SUM($G$53:$G$61)-$G$54) -> 0.30076845 | I60: =H60*$J$62 -> 0.21877683 | J60: =+G60-I60 -> 23.627897 | K60: 25.436825
C61: Other | D61: LE/ton | E61: =E29*E44 -> 35.802217 | G61: =G29*G44 -> 0 | H61: =+G61/(SUM($G$53:$G$61)-$G$54) -> 0 | I61: =H61*$J$62 -> 0 | J61: =+G61-I61 -> 0 | K61: 0
E62: =+SUM(E53:E61)/E6 -> 67.421286 | G62: =SUM(G53:G61)/G6 -> 70.304901 | H62: 70.26 | I62: =G62-H62 -> 0.044900794 | J62: =+I62*G6 -> 0.72739286
C63: DRI Conversion Cost / Ton RM | E63: =(E15-1)*E34 -> 1053 | G63: =(G15-1)*G34 -> 951.69492
C64: DRI Conversion Cost / Ton Others | E64: =SUM(E53:E61) -> 1092.2248 | G64: =SUM(G53:G61) -> 1138.9394
C65: DRI Conversion Exp | E65: =E10*(E63+E64) -> 6.4356745e+09 | G65: =G10*(G63+G64) -> 3.9722052e+09
C68: DRI Variable Cost/Ton | D68: LE/ton | E68: =SUM(E52:E61) -> 4251.2248 | G68: =SUM(G52:G61) -> 4303.8783
C69: DRI Variable EXP | D69: LE | E69: =E68*E16 -> 9.8855172e+08 | G69: =G68*G16 -> 3.7312244e+08
C71: Labor Exp | D71: LE | E71: =E47 -> 54011352 | G71: =G47 -> 54011352
C72: Dep Exp | D72: LE | E72: =E48 -> 2.3974642e+08 | G72: =G48 -> 2.3974642e+08
C73: Other Fixed Exp | D73: LE | E73: =E49 -> 54242037 | G73: =G49 -> 54242037
C74: Labor | D74: LE/ton | E74: =E71/E$16 -> 232.27353 | G74: =G71/G$16 -> 623.00805
C75: Dep | D75: LE/ton | E75: =E72/E$16 -> 1031.0193 | G75: =G72/G$16 -> 2765.4177
C76: Other Fixed | D76: LE/ton | E76: =E73/E$16 -> 233.26558 | G76: =G73/G$16 -> 625.66895
C78: DRI Fixed Cost/Ton | D78: LE/ton | E78: =SUM(E74:E76) -> 1496.5584 | G78: =SUM(G74:G76) -> 4014.0947
C79: DRI Fixed EXP | D79: LE | E79: =E78*E16 -> 3.4799981e+08 | G79: =G78*G16 -> 3.4799981e+08
C81: DRI Manuf. Cost/Ton | D81: LE/ton | E81: =E78+E68 -> 5747.7833 | G81: =G78+G68 -> 8317.973
C82: DRI COGS | D82: LE | E82: =E81*E16 -> 1.3365515e+09 | G82: =G81*G16 -> 7.2112225e+08
C84: COGS/Sales | D84: % | E84: =E82/'[1]Production Q. & Sales (2)'!D95 -> 0.17139533 | G84: =G82/'[1]Production Q. & Sales (2)'!D95 -> 0.092474539
C85: Cost/Ton | D85: LE/ton | E85: =E81 -> 5747.7833 | G85: =G81 -> 8317.973
C86: Selling Price/Ton | D86: LE/ton | E86: ='[1]Production Q. & Sales (2)'!D95/'[1]Production Q. & Sales (2)'!D90 -> 6465.4133 | G86: ='[1]Production Q. & Sales (2)'!D95/'[1]Production Q. & Sales (2)'!D90 -> 6465.4133
C87: Gross Margin/Ton | D87: LE/ton | E87: =E86-E85 -> 717.63001 | G87: =G86-G85 -> -1852.5597

Sheet EZDK Rebar
E2: ='[1]EFS MS Flat'!N2 -> Base
C3: Steel Making - Stage #1
C5: FX Rate | E5: =+Billet!D7 -> 16.2
C6: Inflation
C8: Rebar Production Cap | E8: 2200000
C9: Rebar Production Cap Utlization | D9: % | E9: =E10/E8 -> 0.045454545
C10: MS Rebars Produced / Sold | E10: ='Market Share'!E6*1000 -> 100000
C12: Rebar Export Sales % | D12: % | E12: 0
C13: Rebar Local Sales % | D13: % | E13: 1
C15: Rebar Export Selling Price | D15: USD | E15: 0
C16: Rebar Local Selling Price | D16: USD | E16: 0
C17: Rebar Local Selling Price | D17: LE | E17: ='Market Share'!E29 -> 9300
C19: Produced Molten Steel | D19: Tons | E19: =E106 -> 159025 | G19: =E19*(E73+E74) -> 11221626
C20: Yeild Rate | D20: % | E20: =+Billet!E17% -> 0.8493
C21: Solid Charge | D21: Tons | E21: =E19/E20 -> 187242.43 | G21: =G19/E104 -> 71.005405 | H21: =G19/E156 -> 112.21626 | I21: =G19/G105 -> 75.537665
C23: Consumption
C24: Imported Scrap | D24: =+Billet!E15% -> 0.15977 | E24: =D24*$E$21 -> 29915.723
C25: Local Scrap | D25: =+Billet!E14% -> 0.04 | E25: =D25*$E$21 -> 7489.6973
C26: DRI | D26: =+Billet!E13% -> 0.8 | E26: =D26*$E$21 -> 149793.95
C27: Home scrap | D27: 0 | E27: =D27*$E$21 -> 0
C28: PIG IRON | D28: 0 | E28: =D28*$E$21 -> 0
C30: Byproduct (scrap) | D30: -0.031038676 | E30: =+D30*E21 -> -5811.7572
C32: Auxiliary Materials | D32: KG/ton | E32: 422.60159
C33: Refractories | D33: KG/ton | E33: 10.508598
C34: Electrodes | D34: KG/ton | E34: 2.5805617
C35: Other Fillers | D35: KG/ton | E35: 1.2842586
C37: Electricity (EAF & LF) | D37: KWH/Ton | E37: =+Billet!E20 -> 713.63
C38: Electricity (Aux - Airliq - Lime ) | D38: KWH/Ton | E38: 239.71539
C39: Natural Gas | D39: Nm3/ton | E39: 14.593054
C40: Water | D40: M3/ton | E40: 1.548884
C41: Oxygen | D41: Nm3/ton | E41: 34.797488
C42: Nitrogen | D42: Nm3/ton | E42: 4.0864981
C43: Aragon | D43: Nm3/ton | E43: 0.30455884
C45: Handling Machine over max. Qty. | D45: KG/ton | E45: 0.98684612
C46: Cutting LTS | D46: KG/ton | E46: 0
C48: Unit Purchase Price
C49: Imported Scrap | D49: $/ton | E49: =+Billet!E10 -> 300
C50: Local Scrap | D50: $/ton | E50: =+Billet!E9 -> 300
C51: DRI | D51: $/ton | E51: =+Billet!E8 -> 262.42129
C52: Home scrap | D52: $/ton | E52: 0
C53: PIG IRON | D53: $/ton | E53: 0
C55: Byproduct | D55: $/ton | E55: 352.50468
C57: Auxiliary Materials | D57: $/KG | E57: 59.397018
C58: Refractories | D58: $/KG | E58: 919.71986
C59: Electrodes | D59: $/KG | E59: 5841.4013
C60: Other Fillers | D60: $/KG | E60: 233.46352
C62: Electricity | D62: $/KWH | E62: =+Billet!E11 -> 0.07
C63: Natural Gas | D63: $/NM3 | E63: 0.25072464
C64: Water | D64: $/M3 | E64: 0.27163955
C65: Oxygen | D65: $/NM3 | E65: 0.17166475
C66: Nitrogen | D66: $/NM3 | E66: 0.17166475
C67: Aragon | D67: $/NM3 | E67: 1.9283673
C69: Handling Machine over max. Qty. | D69: $/ton | E69: 0
C70: Cutting LTS | D70: $/ton | E70: 0
C72: Cost Per Ton
C73: Imported Scrap | D73: $/ton | E73: =E24*E49/E$19 -> 56.435888 | G73: =(E73+E74)*E19/E104 -> 71.005405 | H73: =(E73+E74)*E19/E156 -> 112.21626
C74: Local Scrap | D74: $/ton | E74: =E25*E50/E$19 -> 14.129283
C75: DRI | D75: $/ton | E75: =E26*E51/E$19 -> 247.18831 | G75: =E75*E19/E104 -> 248.73044
C76: Home scrap | D76: $/ton | E76: =E27*E52/E$19 -> 0
C77: PIG IRON | D77: $/ton | E77: =E28*E53/E$19 -> 0
C79: Byproduct | D79: $/ton | E79: =E30*E55/E$19 -> -12.882702
C81: Auxiliary Materials | D81: $/ton | E81: =E57*E32/1000 -> 25.101274
C82: Refractories | D82: $/ton | E82: =E58*E33/1000 -> 9.6649659
C83: Electrodes | D83: $/ton | E83: =E59*E34/1000 -> 15.074096
C84: Other Fillers | D84: $/ton | E84: =E60*E35/1000 -> 0.29982753
C86: Electricity (EAF & LF) | D86: $/KWH | E86: =E62*E37 -> 49.9541
C87: Electricity (Aux - Airliq - Lime ) | D87: $/KWH | E87: =E62*E38 -> 16.780077
C88: Natural Gas | D88: $/NM3 | E88: =E63*E39 -> 3.6588382
C89: Water | D89: $/M3 | E89: =E64*E40 -> 0.42073816
C90: Oxygen | D90: $/NM3 | E90: =E65*E41 -> 5.9735019
C91: Nitrogen | D91: $/NM3 | E91: =E66*E42 -> 0.70150766
C92: Aragon | D92: $/NM3 | E92: =E67*E43 -> 0.58730132
C94: Handling Machine over max. Qty. | D94: $/ton | E94: =E69*E45 -> 0 | G94: =SUM(E81:E84)+SUM(E86:E92)+SUM(E94:E95) -> 128.21623 | H94: =G94*E19 -> 20389585
C95: Cutting LTS | D95: $/ton | E95: =E70*E46 -> 0
C96: Imported Scrap Blending Yeild | D96: $/ton | E96: =((1/E20)-1)*$D$24*E49 -> 8.5048884
C97: Local Scrap Blending Yeild | D97: $/ton | E97: =((1/E20)-1)*$D$25*E50 -> 2.1292829
C98: DRI Yeild | D98: $/ton | E98: =((1/E20)-1)*$D$26*E51 -> 37.251278
C99: Conversion Cost St 1 | D99: $/ton | E99: =SUM(E79:E98) -> 163.21898
C100: MS Variable Cost/Ton | D100: $/ton | E100: =SUM(E73:E79)+SUM(E81:E84)+SUM(E86:E92)+SUM(E94:E95) -> 433.087
C102: BCCM - Stage # 2
C104: Produced Billets | D104: 1 | E104: =+E158+'EZDK Wire'!E21 -> 158039.04
C105: Yeild Rate | D105: % | E105: =+Billet!E18% -> 0.9938 | G105: =E104*94% -> 148556.7
C106: Moltten Steel | D106: Tons | E106: =E104/E105 -> 159025
C108: Consumption
C109: Byproduct (Crops) | D109: -0.0026319847 | E109: =+D109*E106 -> -418.55137
C111: Auxiliary Materials | D111: KG/ton | E111: 0.0030214386
C112: Refractories | D112: KG/ton | E112: 1.8375496
C114: Electricity | D114: Kwh/ton | E114: 5.3838798
C115: Natural Gas | D115: Nm3/ton | E115: 6.7045075
C116: Water | D116: M3/ton | E116: 0.49838629
C117: Oxygen | D117: Nm3/ton | E117: 3.4813015
C118: Nitrogen | D118: Nm3/ton | E118: 0
C119: Aragon | D119: Nm3/ton | E119: 0.00071219624
C121: Unit Purchase Price
C122: Molten Steel | D122: $/ton | E122: =+E100 -> 433.087
C124: Byproduct (Crops) | D124: $/ton | E124: 350.28906
C126: Auxiliary Materials | D126: $/KG | E126: 559.92857
C127: Refractories | D127: $/KG | E127: 678.11136
C129: Electricity | D129: $/KWH | E129: =+E62 -> 0.07
C130: Natural Gas | D130: $/NM3 | E130: 0.25072464
...

Sheet EFS Rebar
C3: Steel Making - Stage #1
C5: FX Rate | E5: =+Billet!D7 -> 16.2
C6: Inflation
C8: Rebar Production Cap | E8: 1200000
C9: Rebar Production Cap Utlization | D9: % | E9: =E10/E8 -> 0.058333333
C10: MS Rebars Produced / Sold | E10: ='Market Share'!E7*1000 -> 70000
C12: Rebar Export Sales % | D12: % | E12: 0
C13: Rebar Local Sales % | D13: % | E13: 1
C15: Rebar Export Selling Price | D15: USD | E15: 0
C16: Rebar Local Selling Price | D16: USD | E16: 0
C17: Rebar Local Selling Price | D17: LE | E17: ='Market Share'!E30 -> 9300
C19: Produced Molten Steel | D19: Tons | E19: =E106 -> 73531.926
C20: Yeild Rate | D20: % | E20: =+Billet!F17% -> 0.8417
C21: Solid Charge | D21: Tons | E21: =E19/E20 -> 87361.205
C23: Consumption
C24: Imported Scrap | D24: =+Billet!F15% -> 0.05978 | E24: =D24*$E$21 -> 5222.4528
C25: Local Scrap | D25: =+Billet!F14% -> 0.14 | E25: =D25*$E$21 -> 12230.569
C26: DRI | D26: =+Billet!F13% -> 0.8 | E26: =D26*$E$21 -> 69888.964
C27: Home scrap | D27: 0 | E27: =D27*$E$21 -> 0
C28: PIG IRON | D28: 0 | E28: =D28*$E$21 -> 0
C30: Byproduct (scrap) | D30: -0.034560194 | E30: =+D30*E21 -> -3019.2201
C32: Auxiliary Materials | D32: KG/ton | E32: 422.60159
C33: Refractories | D33: KG/ton | E33: 10.508598
C34: Electrodes | D34: KG/ton | E34: 2.5805617
C35: Other Fillers | D35: KG/ton | E35: 1.2842586
C37: Electricity (EAF & LF) | D37: KWH/Ton | E37: =+Billet!F20 -> 708.39 | G37: =+E37*E19 -> 52089281
C38: Electricity (Aux - Airliq - Lime ) | D38: KWH/Ton | E38: 239.71539 | G38: =+E38*E19 -> 17626734
C39: Natural Gas | D39: Nm3/ton | E39: 14.593054
C40: Water | D40: M3/ton | E40: 1.548884
C41: Oxygen | D41: Nm3/ton | E41: 34.797488
C42: Nitrogen | D42: Nm3/ton | E42: 4.0864981
C43: Aragon | D43: Nm3/ton | E43: 0.30455884
C45: Handling Machine over max. Qty. | D45: KG/ton | E45: 0.98684612
C46: Cutting LTS | D46: KG/ton | E46: 0
C48: Unit Purchase Price
C49: Imported Scrap | D49: $/ton | E49: =+Billet!F10 -> 267.27
C50: Local Scrap | D50: $/ton | E50: =+Billet!F9 -> 248.87
C51: DRI | D51: $/ton | E51: =+Billet!F8 -> 267.30003
C52: Home scrap | D52: $/ton | E52: 0
C53: PIG IRON | D53: $/ton | E53: 0
C55: Byproduct | D55: $/ton | E55: 352.50468
C57: Auxiliary Materials | D57: $/KG | E57: 70.364081
C58: Refractories | D58: $/KG | E58: 1089.5369
C59: Electrodes | D59: $/KG | E59: 8489.9542
C60: Other Fillers | D60: $/KG | E60: 233.46352
C62: Electricity | D62: $/KWH | E62: =+Billet!F11 -> 0.07
C63: Natural Gas | D63: $/NM3 | E63: 0.25072464
C64: Water | D64: $/M3 | E64: 0.27163955
C65: Oxygen | D65: $/NM3 | E65: 0.12203582
C66: Nitrogen | D66: $/NM3 | E66: 0.17166475
C67: Aragon | D67: $/NM3 | E67: 1.9283673
C69: Handling Machine over max. Qty. | D69: $/ton | E69: 0
C70: Cutting LTS | D70: $/ton | E70: 0
C72: Cost Per Ton
C73: Imported Scrap | D73: $/ton | E73: =E24*E49/E$19 -> 18.982298
C74: Local Scrap | D74: $/ton | E74: =E25*E50/E$19 -> 41.394559
C75: DRI | D75: $/ton | E75: =E26*E51/E$19 -> 254.05729
C76: Home scrap | D76: $/ton | E76: =E27*E52/E$19 -> 0
C77: PIG IRON | D77: $/ton | E77: =E28*E53/E$19 -> 0
C79: Byproduct | D79: $/ton | E79: =E30*E55/E$19 -> -14.473839 | G79: -6.9519287 | H79: =G79/2 -> -3.4759643 | I79: -3.4759643
G80: =G79+E79 -> -21.425767 | H80: -17.953804
C81: Auxiliary Materials | D81: $/ton | E81: =E57*E32/1000 -> 29.735972 | G81: =-3.47596434655213+E81 -> 26.260008 | H81: 25.924881
C82: Refractories | D82: $/ton | E82: =E58*E33/1000 -> 11.449505
C83: Electrodes | D83: $/ton | E83: =E59*E34/1000 -> 21.908851 | G83: =E83+H79 -> 18.432887 | H83: 21.908851
C84: Other Fillers | D84: $/ton | E84: =E60*E35/1000 -> 0.29982753
C86: Electricity (EAF & LF) | D86: $/KWH | E86: =E62*E37 -> 49.5873
C87: Electricity (Aux - Airliq - Lime ) | D87: $/KWH | E87: =E62*E38 -> 16.780077
C88: Natural Gas | D88: $/NM3 | E88: =E63*E39 -> 3.6588382
C89: Water | D89: $/M3 | E89: =E64*E40 -> 0.42073816
C90: Oxygen | D90: $/NM3 | E90: =E65*E41 -> 4.2465398
C91: Nitrogen | D91: $/NM3 | E91: =E66*E42 -> 0.70150766
C92: Aragon | D92: $/NM3 | E92: =E67*E43 -> 0.58730132
C94: Handling Machine over max. Qty. | D94: $/ton | E94: =E69*E45 -> 0 | G94: =SUM(E81:E84)+SUM(E86:E92)+SUM(E94:E95) -> 139.37646 | H94: =G94*E19 -> 10248619
C95: Cutting LTS | D95: $/ton | E95: =E70*E46 -> 0
C96: Imported Scrap Blending Yeild | D96: $/ton | E96: =((1/E20)-1)*$D$24*E49 -> 3.0048978
C97: Local Scrap Blending Yeild | D97: $/ton | E97: =((1/E20)-1)*$D$25*E50 -> 6.5527586
C98: DRI Yeild | D98: $/ton | E98: =((1/E20)-1)*$D$26*E51 -> 40.217269
C99: Conversion Cost St 1 | D99: $/ton | E99: =SUM(E79:E98) -> 174.67754
C100: MS Variable Cost/Ton | D100: $/ton | E100: =SUM(E73:E79)+SUM(E81:E84)+SUM(E86:E92)+SUM(E94:E95) -> 439.33677
C102: BCCM - Stage # 2
C104: Produced Billets | D104: =E158/E104 -> 1 | E104: =+E158 -> 72098.053
C105: Yeild Rate | D105: % | E105: =+Billet!F18% -> 0.9805
C106: Moltten Steel | D106: Tons | E106: =E104/E105 -> 73531.926
C108: Consumption
C109: Byproduct (Crops) | D109: -0.0026319847 | E109: =+D109*E106 -> -193.53491
C111: Auxiliary Materials | D111: KG/ton | E111: 0.0030214386
C112: Refractories | D112: KG/ton | E112: 1.8375496
C114: Electricity | D114: Kwh/ton | E114: 5.3838798 | G114: =E114*E104 -> 388167.25
C115: Natural Gas | D115: Nm3/ton | E115: 6.7045075 | G115: =G114+G37+G38 -> 70104182
C116: Water | D116: M3/ton | E116: 0.49838629 | G116: =G115/E104 -> 972.34501
C117: Oxygen | D117: Nm3/ton | E117: 3.4813015
C118: Nitrogen | D118: Nm3/ton | E118: 0
C119: Aragon | D119: Nm3/ton | E119: 0.00071219624
C121: Unit Purchase Price
C122: Molten Steel | D122: $/ton | E122: =+E100 -> 439.33677
C124: Byproduct (Crops) | D124: $/ton | E124: 350.28906
C126: Auxiliary Materials | D126: $/KG | E126: 559.92857
C127: Refractories | D127: $/KG | E127: 795.97151
C129: Electricity | D129: $/KWH | E129: =+E62 -> 0.07
C130: Natural Gas | D130: $/NM3 | E130: 0.25072464
...

Sheet ERM Rolling
E2: Rebar Cost / Ton
E4: Base
C6: Exchange Rate | D6: EGP/USD | E6: =+Billet!D7 -> 16.2
C7: Inflation Rate | D7: % | E7: 0
C9: Rebars
C11: Total Rebar Production Capacity | D11: Tons | E11: 500000
C12: Capacity Utilization | D12: % | E12: 0.16079018
C13: Export Sales | D13: % | E13: =1-E14 -> 0
C14: Local Sales | D14: % | E14: 1
C16: Rebar Export Selling Price | D16: USD | E16: 0
C17: Rebar Local Selling Price | D17: LE | E17: 10743.186
C19: Rebars Yield | D19: % | E19: =+Rebar!G6% -> 0.97917872
C20: Rebar Production | D20: Tons | E20: =+'Market Share'!E8*1000 -> 30000
C21: Required Billets | D21: Tons | E21: =E20/E19 -> 30637.921
C23: Consumption
C24: Imported Billets Tons | D24: 0 | E24: =+D24*E21 -> 0
C25: Produced Billets Tons | D25: 1 | E25: =+D25*E21 -> 30637.921
C26: Local Billets Tons | D26: 0 | E26: =+D26*E21 -> 0
C27: By-product | D27: -0.011671911 | E27: =+D27*(E26+E25+E24) -> -357.60309
C28: Electricity | D28: Kwh/ton | E28: 106.2063
C29: Natural Gas | D29: Nm3/ton | E29: 27.662825
C30: N.Gas | D30: MMBTU/ton | E30: =E29/28 -> 0.98795802
C31: Recycled Water | D31: Nm3/ton | E31: 0.83725281
C32: Tying | D32: Kg/ton | E32: 1.6792739
C33: Chemicals | D33: Kg/ton | E33: 0.6430821
C34: Label & Rings | D34: Kg/ton | E34: 0.6430821
C35: Sp. Parts/Oil & Grease | D35: Kg/ton | E35: 0
C36: External Services | D36: Kg/ton | E36: 1
C38: Unit Price
C39: Imported Billets Purchase Price | D39: USD/ton | E39: 0
C40: Extra Cost | D40: LE/ton | E40: 0
C41: Landed Cost | D41: LE Eq/ton | E41: =(E6*E39)+E40 -> 0
C42: Good / Prod Billet Purchase Price | D42: LE/ton | E42: =+Rebar!G12*E6 -> 7110.1767
C43: Local Billet Purchase Price | D43: LE/ton | E43: 0
C44: By Product Reduction | D44: LE/ton | E44: =+E42 -> 7110.1767
C45: Electricity | D45: LE/KWH | E45: =0.07*E6 -> 1.134
C46: Natural Gas | D46: USD/MMBTU | E46: =+E47*28/E6 -> 7.3997061
C47: Natural Gas | D47: LE/NM3 | E47: 4.2812585
C48: Recycled Water | D48: LE/NM3 | E48: 13.174888
C49: Tying | D49: LE/Kg | E49: =11249.0074074074/1000 -> 11.249007
C50: Chemicals | D50: LE/ton | E50: 2.5153663
C51: Label & Rings | D51: LE/ton | E51: 7.9825608
C52: Sp. Parts/Oil & Grease | D52: LE/ton | E52: 0
C53: External Services | D53: LE/ton | E53: 0
C55: Rebar Fixed Exp
C56: Labor Exp | D56: LE | E56: 97605192
C57: Rebar Dep | E57: 1667852
C58: Other Exp (Exluding Dep) | D58: LE | E58: 17918027
C60: Rebar Cost Per Ton
C61: Imported Billets | D61: LE/ton | E61: =(E24*E41)/E$20 -> 0
C62: Produced Billets | D62: LE/ton | E62: =(E25*E42)/E$20 -> 7261.3677
C63: Local Billets | D63: LE/ton | E63: =(E26*E43)/E$20 -> 0
C64: By Product | D64: LE/ton | E64: =(E27*E44)/E$20 -> -84.75404 | G64: =E64/E6 -> -5.2317308
C66: Raw Material Cost/Ton | D66: LE/ton | E66: =SUM(E61:E64) -> 7176.6136
C68: =C45 -> Electricity | D68: LE/ton | E68: =E28*E45 -> 120.43795 | F68: =+E68/$E$77 -> 0.4370954 | G68: =+F68*$H$77 -> 0.4159207 | H68: =E68-G68 -> 120.02203 | I68: 121.18139 | J68: =E68-I68 -> -0.74344411
C69: =C47 -> Natural Gas | D69: LE/ton | E69: =E29*E47 -> 118.4317 | F69: =+E69/$E$77 -> 0.42981431 | G69: =+F69*$H$77 -> 0.40899234 | H69: =E69-G69 -> 118.02271 | I69: 118.4317 | J69: =E69-I69 -> 0
C70: =C48 -> Recycled Water | D70: LE/ton | E70: =E31*E48 -> 11.030712 | F70: =+E70/$E$77 -> 0.040032844 | G70: =+F70*$H$77 -> 0.038093488 | H70: =E70-G70 -> 10.992618 | I70: 11.030712 | J70: =E70-I70 -> 0
C71: =C49 -> Tying | D71: LE/ton | E71: =E32*E49 -> 18.890165 | F71: =+E71/$E$77 -> 0.068556501 | G71: =+F71*$H$77 -> 0.065235342 | H71: =E71-G71 -> 18.82493 | I71: 18.890165 | J71: =E71-I71 -> 0
C72: =C50 -> Chemicals | D72: LE/ton | E72: =E33*E50 -> 1.617587 | F72: =+E72/$E$77 -> 0.0058705738 | G72: =+F72*$H$77 -> 0.0055861791 | H72: =E72-G72 -> 1.6120009 | I72: 1.617587 | J72: =E72-I72 -> 0
C73: =C51 -> Label & Rings | D73: LE/ton | E73: =E34*E51 -> 5.1334419 | F73: =+E73/$E$77 -> 0.018630373 | G73: =+F73*$H$77 -> 0.017727841 | H73: =E73-G73 -> 5.1157141 | I73: 5.1334419 | J73: =E73-I73 -> 0
C74: =C52 -> Sp. Parts/Oil & Grease | D74: LE/ton | E74: =E35*E52 -> 0 | F74: =+E74/$E$77 -> 0 | G74: =+F74*$H$77 -> 0 | H74: =E74-G74 -> 0 | I74: 0 | J74: =E74-I74 -> 0
C75: =C53 -> External Services | D75: LE/ton | E75: =E36*E53 -> 0 | F75: =+E75/$E$77 -> 0 | G75: =+F75*$H$77 -> 0 | H75: =E75-G75 -> 0 | I75: 0 | J75: =E75-I75 -> 0
C77: Other Variable Cost/Ton | D77: LE/ton | E77: =SUM(E68:E75) -> 275.54156 | G77: =16.95*E6 -> 274.59 | H77: =+E77-G77 -> 0.95155589
C79: Conversion Cost / Ton Imp Billet | E79: =((1/$E$19)-1)*E41 -> 0
C80: Conversion Cost / Ton Prod Billet | E80: =((1/$E$19)-1)*E42 -> 151.19093
C81: Conversion Cost / Ton Local Billet | E81: =((1/$E$19)-1)*E43 -> 0
C82: Conversion Cost / Ton Others | E82: =E64+SUM(E68:E75) -> 190.78752
C83: Conversion Exp | E83: =SUM(E79:E82)*E20 -> 10259353
C86: Rebar Variable Cost/Ton | D86: LE/ton | E86: =E77+E66 -> 7452.1552 | G86: =+E86/E6 -> 460.00958
C87: Rebar Variable EXP | D87: LE | E87: =E86*E20 -> 2.2356466e+08
C89: Labor Exp | D89: LE | E89: =E56 -> 97605192
C90: Dep Exp | D90: LE | E90: =E57 -> 1667852
C91: Other Fixed Exp | D91: LE | E91: =E58 -> 17918027
C92: Labor | D92: LE/ton | E92: =E89/E20 -> 3253.5064
C93: Dep | D93: LE/ton | E93: =E90/E20 -> 55.595067
C94: Other Fixed | D94: LE/ton | E94: =E91/E20 -> 597.26755
C96: Rebar Fixed Cost/Ton | D96: LE/ton | E96: =E92+E93+E94 -> 3906.369
C97: Rebar Fixed EXP | D97: LE | E97: =E96*E20 -> 1.1719107e+08
C99: Rebar Manuf Cost/Ton | D99: LE/ton | E99: =E86+E96 -> 11358.524
C100: Rebars COGS | D100: LE | E100: =E99*E20 -> 3.4075573e+08
C102: COGS/Sales | D102: % | E102: =E100/'[1]Production Q. & Sales (2)'!D78 -> 0.39453046
C103: Cost/Ton | D103: LE/ton | E103: =E99 -> 11358.524
C104: Selling Price/Ton | D104: LE/ton | E104: ='[1]Production Q. & Sales (2)'!D78/'[1]Production Q. & Sales (2)'!D67 -> 10743.186
C105: Gross Margin/Ton | D105: LE/ton | E105: =E104-E103 -> -615.33811

Sheet ESR Rebar
E2: ='[1]EFS MS Flat'!N2 -> Base
C3: Steel Making - Stage #1
C5: FX Rate | E5: =+Billet!D7 -> 16.2
C6: Inflation
C8: Rebar Production Cap | E8: 1200000
C9: Rebar Production Cap Utlization | D9: % | E9: =E10/E8 -> 0.058333333
C10: MS Rebars Produced / Sold | E10: ='Market Share'!E9*1000 -> 70000
C12: Rebar Export Sales % | D12: % | E12: 0
C13: Rebar Local Sales % | D13: % | E13: 1
C15: Rebar Export Selling Price | D15: USD | E15: 565
C16: Rebar Local Selling Price | D16: USD | E16: 677.69333
C17: Rebar Local Selling Price | D17: LE | E17: =E16*E5 -> 10978.632
C19: Produced Billet | D19: Tons | E19: =+E106 -> 72297.074
C20: EAF Yield | D20: % | E20: =+Billet!G17% -> 0.8735
C21: BCCM Yield | D21: % | E21: =+Billet!G18% -> 0.985
C22: Yield Rate | D22: % | E22: =+E20*E21 -> 0.8603975
C23: Solid Charge | D23: Tons | E23: =E19/E22 -> 84027.526
C25: Consumption
C26: Imported Scrap | D26: =+Billet!G15% -> 0.639867 | E26: =+D26*$E$23 -> 53766.441
C27: Local Scrap | D27: =+Billet!G14% -> 0.160133 | E27: =+D27*$E$23 -> 13455.58
C28: DRI | D28: =+Billet!G13% -> 0.2 | E28: =+D28*$E$23 -> 16805.505
C29: Home scrap | D29: 0 | E29: =+D29*$E$23 -> 0
C30: PIG IRON | D30: 0 | E30: =+D30*$E$23 -> 0
C32: Byproduct (scrap) | D32: -0.0080112177 | E32: =D32*E23 -> -673.1628
C34: Auxiliary Materials | D34: KG/ton | E34: =0.109025912856941*1000 -> 109.02591
C35: Refractories | D35: KG/ton | E35: 7.6715424
C36: Electrodes | D36: KG/ton | E36: 1.8285669
C37: Consumables | D37: KG/ton | E37: 1
C39: Electricity | D39: Kwh/ton | E39: =+Billet!G20+15.7308917064777 -> 612.83089
C40: Natural Gas | D40: Nm3/ton | E40: 14.208495
C41: Water | D41: M3/ton | E41: 0.99468845
C42: Oxygen | D42: Nm3/ton | E42: 22.875814
C43: Nitrogen | D43: Nm3/ton | E43: 1.0835797
C44: Chem | D44: Nm3/ton | E44: 1
C46: Handling Machine over max. Qty. | D46: KG/ton | E46: 1
C47: Cutting LTS | D47: KG/ton | E47: 1
C49: Unit Purchase Price
C50: Imported Scrap | D50: $/ton | E50: =+Billet!G10 -> 300
C51: Local Scrap | D51: $/ton | E51: =+Billet!G9 -> 300
C52: DRI | D52: $/ton | E52: =+Billet!G8 -> 274.66003
C53: Home scrap | D53: $/ton | E53: 0
C54: PIG IRON | D54: $/ton | E54: 0
C56: Byproduct | D56: $/ton | E56: =6176.5/E5 -> 381.26543
C58: Auxiliary Materials | D58: $/KG | E58: =5924.76704651993/E5 -> 365.72636
C59: Refractories | D59: $/KG | E59: =16540.4227713778/E5 -> 1021.0138
C60: Electrodes | D60: $/KG | E60: =221779.653102083/E5 -> 13690.102
C61: Consumables | D61: $/KG | E61: =63205.0332834264/E5 -> 3901.5453
C63: Electricity | D63: $/KWH | E63: =+Billet!G11 -> 0.007
C64: Natural Gas | D64: $/NM3 | E64: =4.28401851215912/E5 -> 0.26444559 | F64: =E64*28 -> 7.4044764
C65: Water | D65: $/M3 | E65: =9.1962943800284/E5 -> 0.56767249
C66: Oxygen | D66: $/NM3 | E66: =3.18254566700526/E5 -> 0.19645344
C67: Nitrogen | D67: $/NM3 | E67: =8.26736178405019/E5 -> 0.51033097
C68: Chem | D68: $/NM3 | E68: =3.15551479378521/E5 -> 0.19478486
C70: Handling Machine over max. Qty. | D70: $/ton | E70: 2.3241758 | G70: 4.8137384
C71: Cutting LTS | D71: $/ton | E71: 31.416227
C73: Cost Per Ton
C74: Imported Scrap | D74: $/ton | E74: =E26*E50/E$19 -> 223.1063
C75: Local Scrap | D75: $/ton | E75: =E27*E51/E$19 -> 55.834542
C76: DRI | D76: $/ton | E76: =E28*E52/E$19 -> 63.844915
C77: Home scrap | D77: $/ton | E77: =E29*E53/E$19 -> 0
C78: PIG IRON | D78: $/ton | E78: =E30*E54/E$19 -> 0
C80: Byproduct | D80: $/ton | E80: =E32*E56/E$19 -> -3.5499875
C82: Auxiliary Materials | D82: $/ton | E82: =E58*E34/1000 -> 39.87365
C83: Refractories | D83: $/ton | E83: =E59*E35/1000 -> 7.8327503
C84: Electrodes | D84: $/ton | E84: =E60*E36/1000 -> 25.033267
C85: Consumables | D85: $/ton | E85: =E61*E37/1000 -> 3.9015453
C87: Electricity | D87: $/KWH | E87: =E63*E39 -> 4.2898162
C88: Natural Gas | D88: $/NM3 | E88: =E64*E40 -> 3.7573738
C89: Water | D89: $/M3 | E89: =E65*E41 -> 0.56465727
C90: Oxygen | D90: $/NM3 | E90: =E66*E42 -> 4.4940323
C91: Nitrogen | D91: $/NM3 | E91: =E67*E43 -> 0.5529843
C92: Chem | D92: $/NM3 | E92: =E68*E44 -> 0.19478486
C94: Handling Machine over max. Qty. | D94: $/ton | E94: =E70*E46 -> 2.3241758
C95: Cutting LTS | D95: $/ton | E95: =E71*E47 -> 31.416227
C96: Imported Scrap Blending Yeild | D96: $/ton | E96: =((1/E22)-1)*$D$26*E50 -> 31.146197
C97: Local Scrap Blending Yeild | D97: $/ton | E97: =((1/E22)-1)*$D$27*E51 -> 7.7946416
C98: DRI Yeild | D98: $/ton | E98: =((1/E22)-1)*$D$28*E52 -> 8.9129097
C99: Conversion Cost St 1 | D99: $/ton | E99: =SUM(E80:E98) -> 168.53902
C100: Billet Variable Cost/Ton | D100: $/ton | E100: =SUM(E74:E80)+SUM(E82:E85)+SUM(E87:E92)+SUM(E94:E95) -> 463.47103
C102: Rebars - Stage # 3
C104: Produced Rebars | D104: Tons | E104: =+E10 -> 70000
C105: Yeild Rate | D105: % | E105: =+Rebar!H6% -> 0.96822729
C106: Produced Billets | D106: 1 | E106: =E104/E105*D106 -> 72297.074
C107: Local Billet | D107: 0 | E107: =E104/E105*D107 -> 0
C108: Imported Billets | D108: 0 | E108: =E104/E105*D108 -> 0
C110: Consumption
C111: Byproduct (Rejected Slabs) | D111: -0.021355601 | E111: =+D111*SUM(E106:E108) -> -1543.9475
C112: Byproduct (Crops) | D112: 0 | E112: 0
C114: Refractories | D114: KG/ton | E114: 0
C116: Electricity | D116: Kwh/ton | E116: 104.11271
C117: Natural Gas | D117: Nm3/ton | E117: 29.333686
C118: Water | D118: M3/ton | E118: 0.52882891
C120: Lables & Rings | D120: ton/ton | E120: 1
C121: Chem | D121: ton/ton | E121: 1
C122: Tying | D122: ton/ton | E122: 1.4443874
C124: Unit Purchase Price
C125: Produced Billet | D125: $/ton | E125: =+Rebar!H12 -> 463.47103
C126: Local Billet
C127: Imported Billet | D127: $/ton | E127: 0
C129: Byproduct (Rejected Slabs) | D129: $/ton | E129: 358.62619
...

Sheet EZDK Wire
E2: Rebar Cost / Ton
E4: Base
C6: Exchange Rate | D6: EGP/USD | E6: =+Billet!D7 -> 16.2
C7: Inflation Rate | D7: % | E7: 0
C9: Rebars
C11: Total Rebar Production Capacity | D11: Tons | E11: 500000
C12: Capacity Utilization | D12: % | E12: 0.16079018
C13: Export Sales | D13: % | E13: =1-E14 -> 0
C14: Local Sales | D14: % | E14: 1
C16: Rebar Export Selling Price | D16: USD | E16: 0
C17: Rebar Local Selling Price | D17: LE | E17: 10743.186
C19: Rebars Yield | D19: % | E19: =+Wire!E6% -> 0.9761
C20: Rebar Production | D20: Tons | E20: =('Market Share'!F19+'Market Share'!F6)*1000 -> 50000
C21: Required Billets | D21: Tons | E21: =E20/E19 -> 51224.26
C23: Consumption
C24: Imported Billets Tons | D24: 0 | E24: =+D24*E21 -> 0
C25: Produced Billets Tons | D25: 1 | E25: =+D25*E21 -> 51224.26
C26: Local Billets Tons | D26: 0 | E26: =+D26*E21 -> 0
C27: By-product | D27: -0.018443095 | E27: =+D27*(E26+E25+E24) -> -944.73391
C28: Electricity | D28: Kwh/ton | E28: 117.84816
C29: Natural Gas | D29: Nm3/ton | E29: 30.6951
C30: N.Gas | D30: MMBTU/ton | E30: =E29/28 -> 1.0962536
C31: Recycled Water | D31: Nm3/ton | E31: 0.92902872
C32: Tying | D32: Kg/ton | E32: 1.8633484
C33: Chemicals | D33: Kg/ton | E33: 0.71357388
C34: Label & Rings | D34: Kg/ton | E34: 0.71357388
C35: Sp. Parts/Oil & Grease | D35: Kg/ton | E35: 0
C36: External Services | D36: Kg/ton | E36: 0
C38: Unit Price
C39: Imported Billets Purchase Price | D39: USD/ton | E39: 0
C40: Extra Cost | D40: LE/ton | E40: 0
C41: Landed Cost | D41: LE Eq/ton | E41: =(E6*E39)+E40 -> 0
C42: Good / Prod Billet Purchase Price | D42: LE/ton | E42: =+Wire!E12*E6 -> 7110.1767
C43: Local Billet Purchase Price | D43: LE/ton | E43: 0
C44: By Product Reduction | D44: LE/ton | E44: 5132.9268
C45: Electricity | D45: LE/KWH | E45: =0.07*E6 -> 1.134
C46: Natural Gas | D46: USD/MMBTU | E46: =+E47*28/E6 -> 7.3997061
C47: Natural Gas | D47: LE/NM3 | E47: 4.2812585
C48: Recycled Water | D48: LE/NM3 | E48: 13.174888
C49: Tying | D49: LE/Kg | E49: =11249.0074074074/1000 -> 11.249007
C50: Chemicals | D50: LE/ton | E50: 2.5153663
C51: Label & Rings | D51: LE/ton | E51: 7.9825608
C52: Sp. Parts/Oil & Grease | D52: LE/ton | E52: 0
C53: External Services | D53: LE/ton | E53: 0
C55: Rebar Fixed Exp
C56: Labor Exp | D56: LE | E56: 97605192
C57: Rebar Dep | E57: 1667852
C58: Other Exp (Exluding Dep) | D58: LE | E58: 17918027
C60: Rebar Cost Per Ton
C61: Imported Billets | D61: LE/ton | E61: =(E24*E41)/E$20 -> 0
C62: Produced Billets | D62: LE/ton | E62: =(E25*E42)/E$20 -> 7284.2708 | F62: =E62/E6 -> 449.64635
C63: Local Billets | D63: LE/ton | E63: =(E26*E43)/E$20 -> 0
C64: By Product | D64: LE/ton | E64: =(E27*E44)/E$20 -> -96.985 | F64: =E64/E6 -> -5.9867284 | G64: =-6.03*E6 -> -97.686 | H64: -99.495
C66: Raw Material Cost/Ton | D66: LE/ton | E66: =SUM(E61:E64) -> 7187.2858
C68: =C45 -> Electricity | D68: LE/ton | E68: =E28*E45 -> 133.63982 | F68: =+E68/$E$77 -> 0.4370954 | G68: =+F68*$H$77 -> 1.3677539 | H68: =E68-G68 -> 132.27206 | I68: 136.11463
C69: =C47 -> Natural Gas | D69: LE/ton | E69: =E29*E47 -> 131.41366 | F69: =+E69/$E$77 -> 0.42981431 | G69: =+F69*$H$77 -> 1.34497 | H69: =E69-G69 -> 130.06869 | I69: 131.41366
C70: =C48 -> Recycled Water | D70: LE/ton | E70: =E31*E48 -> 12.239849 | F70: =+E70/$E$77 -> 0.040032844 | G70: =+F70*$H$77 -> 0.12527032 | H70: =E70-G70 -> 12.114579 | I70: 12.239849
C71: =C49 -> Tying | D71: LE/ton | E71: =E32*E49 -> 20.96082 | F71: =+E71/$E$77 -> 0.068556501 | G71: =+F71*$H$77 -> 0.21452622 | H71: =E71-G71 -> 20.746294 | I71: 20.96082
C72: =C50 -> Chemicals | D72: LE/ton | E72: =E33*E50 -> 1.7948997 | F72: =+E72/$E$77 -> 0.0058705738 | G72: =+F72*$H$77 -> 0.018370133 | H72: =E72-G72 -> 1.7765296 | I72: 1.7948997
C73: =C51 -> Label & Rings | D73: LE/ton | E73: =E34*E51 -> 5.6961469 | F73: =+E73/$E$77 -> 0.018630373 | G73: =+F73*$H$77 -> 0.058297951 | H73: =E73-G73 -> 5.6378489 | I73: 5.6961469
C74: =C52 -> Sp. Parts/Oil & Grease | D74: LE/ton | E74: =E35*E52 -> 0 | F74: =+E74/$E$77 -> 0 | G74: =+F74*$H$77 -> 0 | H74: =E74-G74 -> 0 | I74: 0
C75: =C53 -> External Services | D75: LE/ton | E75: =E36*E53 -> 0 | F75: =+E75/$E$77 -> 0 | G75: =+F75*$H$77 -> 0 | H75: =E75-G75 -> 0 | I75: 0
C77: Other Variable Cost/Ton | D77: LE/ton | E77: =SUM(E68:E75) -> 305.74519 | G77: =18.68*E6 -> 302.616 | H77: =+E77-G77 -> 3.1291886
C79: Conversion Cost / Ton Imp Billet | E79: =((1/$E$19)-1)*E41 -> 0
C80: Conversion Cost / Ton Prod Billet | E80: =((1/$E$19)-1)*E42 -> 174.09407
C81: Conversion Cost / Ton Local Billet | E81: =((1/$E$19)-1)*E43 -> 0
C82: Conversion Cost / Ton Others | E82: =E64+SUM(E68:E75) -> 208.76019
C83: Conversion Exp | E83: =SUM(E79:E82)*E20 -> 19142713
C86: Rebar Variable Cost/Ton | D86: LE/ton | E86: =E77+E66 -> 7493.031 | F86: =E86/E6 -> 462.53278
C87: Rebar Variable EXP | D87: LE | E87: =E86*E20 -> 3.7465155e+08
C89: Labor Exp | D89: LE | E89: =E56 -> 97605192
C90: Dep Exp | D90: LE | E90: =E57 -> 1667852
C91: Other Fixed Exp | D91: LE | E91: =E58 -> 17918027
C92: Labor | D92: LE/ton | E92: =E89/E20 -> 1952.1038
C93: Dep | D93: LE/ton | E93: =E90/E20 -> 33.35704
C94: Other Fixed | D94: LE/ton | E94: =E91/E20 -> 358.36053
C96: Rebar Fixed Cost/Ton | D96: LE/ton | E96: =E92+E93+E94 -> 2343.8214
C97: Rebar Fixed EXP | D97: LE | E97: =E96*E20 -> 1.1719107e+08
C99: Rebar Manuf Cost/Ton | D99: LE/ton | E99: =E86+E96 -> 9836.8524
C100: Rebars COGS | D100: LE | E100: =E99*E20 -> 4.9184262e+08
C102: COGS/Sales | D102: % | E102: =E100/'[1]Production Q. & Sales (2)'!D78 -> 0.56946041
C103: Cost/Ton | D103: LE/ton | E103: =E99 -> 9836.8524
C104: Selling Price/Ton | D104: LE/ton | E104: ='[1]Production Q. & Sales (2)'!D78/'[1]Production Q. & Sales (2)'!D67 -> 10743.186
C105: Gross Margin/Ton | D105: LE/ton | E105: =E104-E103 -> 906.33369

Sheet EZDK Flat
E2: ='[1]EFS MS Flat'!N2 -> Base
C3: Steel Making - Stage #1
C5: FX Rate | E5: =+Billet!D7 -> 16.2
C6: Inflation
C8: Rebar Production Cap | E8: 1200000
C9: Rebar Production Cap Utlization | D9: % | E9: 1
C10: HRC Produced / Sold | E10: =('Market Share'!G6+'Market Share'!G19)*1000 -> 85000
C12: Rebar Export Sales % | D12: % | E12: 0
C13: Rebar Local Sales % | D13: % | E13: 1
C15: Rebar Export Selling Price | D15: USD | E15: 565
C16: Rebar Local Selling Price | D16: USD | E16: 677.69333
C17: Rebar Local Selling Price | D17: LE | E17: =E16*E5 -> 10978.632
C19: Produced Molten Steel | D19: Tons | E19: =E106 -> 88138.192
C20: Yeild Rate | D20: % | E20: =+Flat!E17% -> 0.8522
C21: Solid Charge | D21: Tons | E21: =E19/E20 -> 103424.3
C23: Consumption
C24: Imported Scrap | D24: =+Flat!E15% -> 0.03 | E24: =D24*$E$21 -> 3102.7291
C25: Local Scrap | D25: =+Flat!E14% -> 0.16998 | E25: =D25*$E$21 -> 17580.063
C26: DRI | D26: =+Flat!E13% -> 0.8 | E26: =D26*$E$21 -> 82739.443
C27: Home scrap | D27: 0 | E27: =D27*$E$21 -> 0
C28: PIG IRON | D28: 0 | E28: =D28*$E$21 -> 0
C30: Byproduct (scrap) | D30: -0.032673411 | E30: =+D30*E21 -> -3379.2248
C32: Auxiliary Materials | D32: KG/ton | E32: 422.60159
C33: Refractories | D33: KG/ton | E33: 10.508598
C34: Electrodes | D34: KG/ton | E34: 2.5805617
C35: Other Fillers | D35: KG/ton | E35: 1.2842586
C37: Electricity (EAF & LF) | D37: KWH/Ton | E37: =+Flat!E20 -> 693.12
C38: Electricity (Aux - Airliq - Lime ) | D38: KWH/Ton | E38: 239.71539
C39: Natural Gas | D39: Nm3/ton | E39: 14.593054
C40: Water | D40: M3/ton | E40: 1.548884
C41: Oxygen | D41: Nm3/ton | E41: 34.797488
C42: Nitrogen | D42: Nm3/ton | E42: 4.0864981
C43: Aragon | D43: Nm3/ton | E43: 0.30455884
C45: Handling Machine over max. Qty. | D45: KG/ton | E45: 0.98684612
C46: Cutting LTS | D46: KG/ton | E46: 0
C48: Unit Purchase Price
C49: Imported Scrap | D49: $/ton | E49: =+Flat!E10 -> 275.51
C50: Local Scrap | D50: $/ton | E50: =+Flat!E9 -> 248.87
C51: DRI | D51: $/ton | E51: =+Flat!E8 -> 262.42129
C52: Home scrap | D52: $/ton | E52: 0
C53: PIG IRON | D53: $/ton | E53: 0
C55: Byproduct | D55: $/ton | E55: 352.50468
C57: Auxiliary Materials | D57: $/KG | E57: 66.357842
C58: Refractories | D58: $/KG | E58: 916.67199
C59: Electrodes | D59: $/KG | E59: 6438.55
C60: Other Fillers | D60: $/KG | E60: 257.32978
C62: Electricity | D62: $/KWH | E62: =+Billet!E11 -> 0.07
C63: Natural Gas | D63: $/NM3 | E63: 0.25072464
C64: Water | D64: $/M3 | E64: 0.27163955
C65: Oxygen | D65: $/NM3 | E65: 0.1579975
C66: Nitrogen | D66: $/NM3 | E66: 0.17166475
C67: Aragon | D67: $/NM3 | E67: 1.9283673
C69: Handling Machine over max. Qty. | D69: $/ton | E69: 0
C70: Cutting LTS | D70: $/ton | E70: 0
C72: Cost Per Ton
C73: Imported Scrap | D73: $/ton | E73: =E24*E49/E$19 -> 9.6987796
C74: Local Scrap | D74: $/ton | E74: =E25*E50/E$19 -> 49.639665
C75: DRI | D75: $/ton | E75: =E26*E51/E$19 -> 246.34714
C76: Home scrap | D76: $/ton | E76: =E27*E52/E$19 -> 0
C77: PIG IRON | D77: $/ton | E77: =E28*E53/E$19 -> 0
C79: Byproduct | D79: $/ton | E79: =E30*E55/E$19 -> -13.515055
C81: Auxiliary Materials | D81: $/ton | E81: =E57*E32/1000 -> 28.042929
C82: Refractories | D82: $/ton | E82: =E58*E33/1000 -> 9.632937
C83: Electrodes | D83: $/ton | E83: =E59*E34/1000 -> 16.615076
C84: Other Fillers | D84: $/ton | E84: =E60*E35/1000 -> 0.33047799
C86: Electricity (EAF & LF) | D86: $/KWH | E86: =E62*E37 -> 48.5184
C87: Electricity (Aux - Airliq - Lime ) | D87: $/KWH | E87: =E62*E38 -> 16.780077
C88: Natural Gas | D88: $/NM3 | E88: =E63*E39 -> 3.6588382
C89: Water | D89: $/M3 | E89: =E64*E40 -> 0.42073816
C90: Oxygen | D90: $/NM3 | E90: =E65*E41 -> 5.4979162
C91: Nitrogen | D91: $/NM3 | E91: =E66*E42 -> 0.70150766
C92: Aragon | D92: $/NM3 | E92: =E67*E43 -> 0.58730132
C94: Handling Machine over max. Qty. | D94: $/ton | E94: =E69*E45 -> 0 | G94: =SUM(E81:E84)+SUM(E86:E92)+SUM(E94:E95) -> 130.7862 | H94: =G94*E19 -> 11527259
C95: Cutting LTS | D95: $/ton | E95: =E70*E46 -> 0
C96: Imported Scrap Blending Yeild | D96: $/ton | E96: =((1/E20)-1)*$D$24*E49 -> 1.4334796
C97: Local Scrap Blending Yeild | D97: $/ton | E97: =((1/E20)-1)*$D$25*E50 -> 7.3367425
C98: DRI Yeild | D98: $/ton | E98: =((1/E20)-1)*$D$26*E51 -> 36.410107
C99: Conversion Cost St 1 | D99: $/ton | E99: =SUM(E79:E98) -> 162.45147
C100: MS Variable Cost/Ton | D100: $/ton | E100: =SUM(E73:E79)+SUM(E81:E84)+SUM(E86:E92)+SUM(E94:E95) -> 422.95672
C102: TCS - Stage # 2
C104: Produced Slabs | D104: =E158/E104 -> 1 | E104: =+E158 -> 87018.837
C105: Yeild Rate | D105: % | E105: =+Flat!E18% -> 0.9873
C106: Moltten Steel | D106: Tons | E106: =E104/E105 -> 88138.192
C108: Consumption
C109: Byproduct (Crops) | D109: -0.0026319847 | E109: =+D109*E106 -> -231.97838
C111: Auxiliary Materials | D111: KG/ton | E111: 0.0030214386
C112: Refractories | D112: KG/ton | E112: 1.8375496
C114: Electricity | D114: Kwh/ton | E114: 5.3838798
C115: Natural Gas | D115: Nm3/ton | E115: 6.7045075
C116: Water | D116: M3/ton | E116: 0.49838629
C117: Oxygen | D117: Nm3/ton | E117: 3.4813015
C118: Nitrogen | D118: Nm3/ton | E118: 0
C119: Aragon | D119: Nm3/ton | E119: 0.00071219624
C121: Unit Purchase Price
C122: Molten Steel | D122: $/ton | E122: =+E100 -> 422.95672
C124: Byproduct (Crops) | D124: $/ton | E124: 350.28906
C126: Auxiliary Materials | D126: $/KG | E126: 559.92857
C127: Refractories | D127: $/KG | E127: 1013.8652
C129: Electricity | D129: $/KWH | E129: =+E62 -> 0.07
C130: Natural Gas | D130: $/NM3 | E130: 0.25072464
...

Sheet EFS Flat
E2: ='[1]EFS MS Flat'!N2 -> Base
C3: Steel Making - Stage #1
C5: FX Rate | E5: =+Billet!D7 -> 16.2
C6: Inflation
C8: Rebar Production Cap | E8: 1200000
C9: Rebar Production Cap Utlization | D9: % | E9: 1
C10: HRC Produced / Sold | E10: =('Market Share'!G20+'Market Share'!G7)*1000 -> 15000
C12: Rebar Export Sales % | D12: % | E12: 0.5
C13: Rebar Local Sales % | D13: % | E13: 0.5
C15: Rebar Export Selling Price | D15: USD | E15: 565
C16: Rebar Local Selling Price | D16: USD | E16: 677.69333
C17: Rebar Local Selling Price | D17: LE | E17: =E16*E5 -> 10978.632
C19: Produced Molten Steel | D19: Tons | E19: =E106 -> 15618.492
C20: Yeild Rate | D20: % | E20: =+Flat!F17% -> 0.8417
C21: Solid Charge | D21: Tons | E21: =E19/E20 -> 18555.89
C23: Consumption
C24: Imported Scrap | D24: =+Flat!F15% -> 0.05978 | E24: =D24*$E$21 -> 1109.2711
C25: Local Scrap | D25: =+Flat!F14% -> 0.14 | E25: =D25*$E$21 -> 2597.8245
C26: DRI | D26: =+Flat!F13% -> 0.8 | E26: =D26*$E$21 -> 14844.712
C27: Home scrap | D27: 0 | E27: =D27*$E$21 -> 0
C28: PIG IRON | D28: 0 | E28: =D28*$E$21 -> 0
C30: Byproduct (scrap) | D30: -0.032673411 | E30: =+D30*E21 -> -606.2842
C32: Auxiliary Materials | D32: KG/ton | E32: 422.60159
C33: Refractories | D33: KG/ton | E33: 10.508598
C34: Electrodes | D34: KG/ton | E34: 2.5805617
C35: Other Fillers | D35: KG/ton | E35: 1.2842586
C37: Electricity (EAF & LF) | D37: KWH/Ton | E37: =+Flat!F20 -> 708.39
C38: Electricity (Aux - Airliq - Lime ) | D38: KWH/Ton | E38: 239.71539
C39: Natural Gas | D39: Nm3/ton | E39: 14.593054
C40: Water | D40: M3/ton | E40: 1.548884
C41: Oxygen | D41: Nm3/ton | E41: 34.797488
C42: Nitrogen | D42: Nm3/ton | E42: 4.0864981
C43: Aragon | D43: Nm3/ton | E43: 0.30455884
C45: Handling Machine over max. Qty. | D45: KG/ton | E45: 0.98684612
C46: Cutting LTS | D46: KG/ton | E46: 0
C48: Unit Purchase Price
C49: Imported Scrap | D49: $/ton | E49: =+Flat!F10 -> 267.27
C50: Local Scrap | D50: $/ton | E50: =+Flat!F9 -> 248.87
C51: DRI | D51: $/ton | E51: =+Flat!F8 -> 267.30003
C52: Home scrap | D52: $/ton | E52: 0
C53: PIG IRON | D53: $/ton | E53: 0
C55: Byproduct | D55: $/ton | E55: 352.50468
C57: Auxiliary Materials | D57: $/KG | E57: 83.695531
C58: Refractories | D58: $/KG | E58: 1295.9648
C59: Electrodes | D59: $/KG | E59: 6438.55
C60: Other Fillers | D60: $/KG | E60: 257.32978
C62: Electricity | D62: $/KWH | E62: =+Billet!E11 -> 0.07
C63: Natural Gas | D63: $/NM3 | E63: 0.25072464
C64: Water | D64: $/M3 | E64: 0.27163955
C65: Oxygen | D65: $/NM3 | E65: 0.17166475
C66: Nitrogen | D66: $/NM3 | E66: 0.17166475
C67: Aragon | D67: $/NM3 | E67: 1.9283673
C69: Handling Machine over max. Qty. | D69: $/ton | E69: 11.920073
C70: Cutting LTS | D70: $/ton | E70: 0
C72: Cost Per Ton
C73: Imported Scrap | D73: $/ton | E73: =E24*E49/E$19 -> 18.982298
C74: Local Scrap | D74: $/ton | E74: =E25*E50/E$19 -> 41.394559
C75: DRI | D75: $/ton | E75: =E26*E51/E$19 -> 254.05729
C76: Home scrap | D76: $/ton | E76: =E27*E52/E$19 -> 0
C77: PIG IRON | D77: $/ton | E77: =E28*E53/E$19 -> 0
C79: Byproduct | D79: $/ton | E79: =E30*E55/E$19 -> -13.683652
C81: Auxiliary Materials | D81: $/ton | E81: =E57*E32/1000 -> 35.369864
C82: Refractories | D82: $/ton | E82: =E58*E33/1000 -> 13.618772
C83: Electrodes | D83: $/ton | E83: =E59*E34/1000 -> 16.615076
C84: Other Fillers | D84: $/ton | E84: =E60*E35/1000 -> 0.33047799
C86: Electricity (EAF & LF) | D86: $/KWH | E86: =E62*E37 -> 49.5873
C87: Electricity (Aux - Airliq - Lime ) | D87: $/KWH | E87: =E62*E38 -> 16.780077
C88: Natural Gas | D88: $/NM3 | E88: =E63*E39 -> 3.6588382
C89: Water | D89: $/M3 | E89: =E64*E40 -> 0.42073816
C90: Oxygen | D90: $/NM3 | E90: =E65*E41 -> 5.9735019
C91: Nitrogen | D91: $/NM3 | E91: =E66*E42 -> 0.70150766
C92: Aragon | D92: $/NM3 | E92: =E67*E43 -> 0.58730132
C94: Handling Machine over max. Qty. | D94: $/ton | E94: =E69*E45 -> 11.763278 | G94: =SUM(E81:E84)+SUM(E86:E92)+SUM(E94:E95) -> 155.40673 | H94: =G94*E19 -> 2427218.9
C95: Cutting LTS | D95: $/ton | E95: =E70*E46 -> 0
C96: Imported Scrap Blending Yeild | D96: $/ton | E96: =((1/E20)-1)*$D$24*E49 -> 3.0048978
C97: Local Scrap Blending Yeild | D97: $/ton | E97: =((1/E20)-1)*$D$25*E50 -> 6.5527586
C98: DRI Yeild | D98: $/ton | E98: =((1/E20)-1)*$D$26*E51 -> 40.217269
C99: Conversion Cost St 1 | D99: $/ton | E99: =SUM(E79:E98) -> 191.49801
C100: MS Variable Cost/Ton | D100: $/ton | E100: =SUM(E73:E79)+SUM(E81:E84)+SUM(E86:E92)+SUM(E94:E95) -> 456.15723
C102: TCS - Stage # 2
C104: Produced Billets | D104: =E158/E104 -> 1 | E104: =+E158 -> 15306.122
C105: Yeild Rate | D105: % | E105: =+Flat!F18% -> 0.98
C106: Moltten Steel | D106: Tons | E106: =E104/E105 -> 15618.492
C108: Consumption
C109: Byproduct (Crops) | D109: -0.0026319847 | E109: =+D109*E106 -> -41.107633
C111: Auxiliary Materials | D111: KG/ton | E111: 0.0030214386
C112: Refractories | D112: KG/ton | E112: 1.8375496
C114: Electricity | D114: Kwh/ton | E114: 5.3838798
C115: Natural Gas | D115: Nm3/ton | E115: 6.7045075
C116: Water | D116: M3/ton | E116: 0.49838629
C117: Oxygen | D117: Nm3/ton | E117: 3.4813015
C118: Nitrogen | D118: Nm3/ton | E118: 0
C119: Aragon | D119: Nm3/ton | E119: 0.00071219624
C121: Unit Purchase Price
C122: Molten Steel | D122: $/ton | E122: =+E100 -> 456.15723
C124: Byproduct (Crops) | D124: $/ton | E124: 350.28906
C126: Auxiliary Materials | D126: $/KG | E126: 559.92857
C127: Refractories | D127: $/KG | E127: 854.392
C129: Electricity | D129: $/KWH | E129: =+E62 -> 0.07
C130: Natural Gas | D130: $/NM3 | E130: 0.25072464
...

Sheet Fixed Cost
B2: Total Monthly Fixed Cost | H2: =+TODAY() -> 46303
B4: Item | C4: Unit | D4: EZDK | E4: EFS | F4: ERM | G4: ESR | H4: Total Fixed
B6: Total Fixed Cost W/O Depretiation | C6: $ M | D6: =+SUM(D7:D9) -> 20.58 | E6: =+SUM(E7:E9) -> 6.22 | F6: =+SUM(F7:F9) -> 6.53 | G6: =+SUM(G7:G9) -> 10 | H6: =SUM(D6:G6) -> 43.33
B7: Manufacturing Fixed Cost | C7: $ M | D7: 9.93 | E7: 3.54 | F7: 1.17 | G7: 2.45 | H7: =SUM(D7:G7) -> 17.09
B8: SG&A | C8: $ M | D8: 3.66 | E8: 0.26 | F8: 0.84 | G8: 2.38 | H8: =SUM(D8:G8) -> 7.14
B9: Net Finance Cost | C9: $ M | D9: 6.99 | E9: 2.42 | F9: 4.52 | G9: 5.17 | H9: =SUM(D9:G9) -> 19.1
B11: Depretiation | C11: $ M | D11: 2.39 | E11: 2.52 | F11: 1.24 | G11: 0.13 | H11: =SUM(D11:G11) -> 6.28
B13: Total Monthly Fixed Cost including Depretiation | C13: $ M | D13: =D11+D6 -> 22.97 | E13: =E11+E6 -> 8.74 | F13: =F11+F6 -> 7.77 | G13: =G11+G6 -> 10.13 | H13: =H11+H6 -> 49.61
B15: USD Exchange rate | D15: 16.2
B17: Item | D17: EZDK | E17: EFS | F17: ERM | G17: ESR | H17: Total Fixed
B19: Total Fixed Cost W/O Depretiation | C19: LE M | D19: =D6*$D$15 -> 333.396 | E19: =E6*$D$15 -> 100.764 | F19: =F6*$D$15 -> 105.786 | G19: =G6*$D$15 -> 162 | H19: =SUM(D19:G19) -> 701.946
B20: Manufacturing Fixed Cost | C20: LE M | D20: =D7*$D$15 -> 160.866 | E20: =E7*$D$15 -> 57.348 | F20: =F7*$D$15 -> 18.954 | G20: =G7*$D$15 -> 39.69 | H20: =SUM(D20:G20) -> 276.858
B21: SG&A | C21: LE M | D21: =D8*$D$15 -> 59.292 | E21: =E8*$D$15 -> 4.212 | F21: =F8*$D$15 -> 13.608 | G21: =G8*$D$15 -> 38.556 | H21: =SUM(D21:G21) -> 115.668
B22: Net Finance Cost | C22: LE M | D22: =D9*$D$15 -> 113.238 | E22: =E9*$D$15 -> 39.204 | F22: =F9*$D$15 -> 73.224 | G22: =G9*$D$15 -> 83.754 | H22: =SUM(D22:G22) -> 309.42
B24: Depretiation | C24: LE M | D24: =D11*$D$15 -> 38.718 | E24: =E11*$D$15 -> 40.824 | F24: =F11*$D$15 -> 20.088 | G24: =G11*$D$15 -> 2.106 | H24: =SUM(D24:G24) -> 101.736
D26: 1 | E26: / 12
B28: Item | D28: EZDK | E28: EFS | F28: ERM | G28: ESR
B29: Fixed Cost Distribution
B30: DRI | C30: % | F30: 70
B31: Rebar | C31: % | D31: 25 | E31: 50 | F31: 30 | G31: 100
B32: Wire Rod | C32: % | D32: 25
B33: Flat | C33: % | D33: 50 | E33: 50
B34: Total | C34: % | D34: =SUM(D30:D33) -> 100 | E34: =SUM(E30:E33) -> 100 | F34: =SUM(F30:F33) -> 100 | G34: =SUM(G30:G33) -> 100
B36: DRI | D36: EZDK | E36: EFS | F36: ERM | G36: ESR | H36: Total
B38: Manufacturing Fixed Cost | C38: $ M | F38: =$F$30%*F7 -> 0.819 | H38: =SUM(D38:G38) -> 0.819
B39: SG&A | C39: $ M | F39: =$F$30%*F8 -> 0.588 | H39: =SUM(D39:G39) -> 0.588
B40: Net Finance Cost | C40: $ M | F40: =$F$30%*F9 -> 3.164 | H40: =SUM(D40:G40) -> 3.164
B41: Depretiation | C41: $ M | F41: =$F$30%*F11 -> 0.868 | H41: =SUM(D41:G41) -> 0.868
H42: =SUM(H38:H41) -> 5.439
B44: Rebar | D44: EZDK | E44: EFS | F44: ERM | G44: ESR | H44: Total
B46: Manufacturing Fixed Cost | C46: $ M | D46: =D$31%*D7 -> 2.4825 | E46: =E$31%*E7 -> 1.77 | F46: =F$31%*F7 -> 0.351 | G46: =G$31%*G7 -> 2.45 | H46: =SUM(D46:G46) -> 7.0535
B47: SG&A | C47: $ M | D47: =D$31%*D8 -> 0.915 | E47: =E$31%*E8 -> 0.13 | F47: =F$31%*F8 -> 0.252 | G47: =G$31%*G8 -> 2.38 | H47: =SUM(D47:G47) -> 3.677
B48: Net Finance Cost | C48: $ M | D48: =D$31%*D9 -> 1.7475 | E48: =E$31%*E9 -> 1.21 | F48: =F$31%*F9 -> 1.356 | G48: =G$31%*G9 -> 5.17 | H48: =SUM(D48:G48) -> 9.4835
B49: Depretiation | C49: $ M | D49: =D$31%*D11 -> 0.5975 | E49: =E$31%*E11 -> 1.26 | F49: =F$31%*F11 -> 0.372 | G49: =G$31%*G11 -> 0.13 | H49: =SUM(D49:G49) -> 2.3595
H50: =SUM(H46:H49) -> 22.5735
B52: Wire Rod | D52: EZDK | E52: EFS | F52: ERM | G52: ESR | H52: Total
B54: Manufacturing Fixed Cost | C54: $ M | D54: =D$32%*D7 -> 2.4825 | H54: =SUM(D54:G54) -> 2.4825
B55: SG&A | C55: $ M | D55: =D$32%*D8 -> 0.915 | H55: =SUM(D55:G55) -> 0.915
B56: Net Finance Cost | C56: $ M | D56: =D$32%*D9 -> 1.7475 | H56: =SUM(D56:G56) -> 1.7475
B57: Depretiation | C57: $ M | D57: =D$32%*D11 -> 0.5975 | H57: =SUM(D57:G57) -> 0.5975
H58: =SUM(H54:H57) -> 5.7425
B60: Flat | D60: EZDK | E60: EFS | F60: ERM | G60: ESR | H60: Total
B62: Manufacturing Fixed Cost | C62: $ M | D62: =D$33%*D7 -> 4.965 | E62: =E$33%*E7 -> 1.77 | H62: =SUM(D62:G62) -> 6.735
B63: SG&A | C63: $ M | D63: =D$33%*D8 -> 1.83 | E63: =E$33%*E8 -> 0.13 | H63: =SUM(D63:G63) -> 1.96
B64: Net Finance Cost | C64: $ M | D64: =D$33%*D9 -> 3.495 | E64: =E$33%*E9 -> 1.21 | H64: =SUM(D64:G64) -> 4.705
B65: Depretiation | C65: $ M | D65: =D$33%*D11 -> 1.195 | E65: =E$33%*E11 -> 1.26 | H65: =SUM(D65:G65) -> 2.455
H66: =SUM(H62:H65) -> 15.855

Sheet DRI
B2: DRI Production Cost | F2: =+'Fixed Cost'!H2 -> 46303
B4: Item | C4: Unit | E4: EZDK | F4: ERM
B6: FX | C6: $/LE | E6: =+'Fixed Cost'!D15 -> 16.2
B8: IOP Landed Cost | C8: $/t | E8: 130 | F8: 136.62
B9: NG Price | C9: $/MMBTU | E9: 5.5 | F9: 5.5
B11: MRMR | C11: t/t | E11: 1.5 | F11: 1.43
B12: NG Consumption | C12: Nm3 | E12: 292.58 | F12: 333
B14: Variable Manufacturing Cost
B16: Material Prices | C16: $/t | E16: =+E8 -> 130 | F16: =+F8 -> 136.62
B18: MRMR Effect | C18: $/t | E18: =+(E11-1)*E16 -> 65 | F18: =+(F11-1)*F16 -> 58.7466
B19: Other Conversion Cost | C19: $/t | E19: =+SUM('DRI Cost'!E53:E61)/'DRI Cost'!E6 -> 67.421286 | F19: =+SUM('DRI Cost'!G53:G61)/'DRI Cost'!G6 -> 70.304901
B20: Total Conversion Cost | C20: $/t | E20: =+SUM(E18:E19) -> 132.42129 | F20: =+SUM(F18:F19) -> 129.0515
B22: Total Variable Manufacturing Cost | C22: $/t | E22: =+E20+E16 -> 262.42129 | F22: =+F20+F16 -> 265.6715
G24: =1+'Fixed Cost'!D26 -> 2 | H24: / 12

Sheet Billet
B2: Billet Production Cost | G2: =+DRI!F2 -> 46303
B4: Item | C4: Unit | E4: EZDK | F4: EFS | G4: ESR
B6: DRI Margin From ERM | C6: $/t | F6: 1.6285249 | G6: 8.9885249
B7: FX | C7: $/LE | D7: =+'Fixed Cost'!D15 -> 16.2
B8: DRI Price | C8: $/t | E8: =+DRI!E22 -> 262.42129 | F8: =+DRI!F22+(F6) -> 267.30003 | G8: =+DRI!F22+(G6) -> 274.66003
B9: Local Scrap Price | C9: $/t | E9: 300 | F9: 248.87 | G9: =+E9 -> 300
B10: Imported Scrap Landed Cost | C10: $/t | E10: 300 | F10: 267.27 | G10: =+E10 -> 300
B11: Elictricity Price | C11: $/KWH | E11: 0.07 | F11: 0.07 | G11: 0.007
B13: DRI Blending Ratio | C13: % | E13: 80 | F13: 80 | G13: 20
B14: Local Scrap | C14: % | E14: 4 | F14: 14 | G14: 16.0133
B15: Imported Scrap | C15: % | E15: 15.977 | F15: 5.978 | G15: 63.9867
B17: EAF Yield | C17: % | E17: 84.93 | F17: 84.17 | G17: 87.35
B18: CCP Yield | C18: % | E18: 99.38 | F18: 98.05 | G18: 98.5
B19: Billet yield from Solid Charge | C19: % | E19: =+E18*E17/100 -> 84.403434 | F19: =+F18*F17/100 -> 82.528685 | G19: =+G18*G17/100 -> 86.03975
B20: EAF & LF Electricity Consumption | C20: KWH/tms | E20: 713.63 | F20: 708.39 | G20: 597.1
B22: Variable Manufacturing Cost
B24: Material Price | C24: $/t | E24: =E8*E13%+E9*E14%+E10*E15% -> 269.86803 | F24: =F8*F13%+F9*F14%+F10*F15% -> 264.65922 | G24: =G8*G13%+G9*G14%+G10*G15% -> 294.93201
B26: Yield Effect | C26: $/t | E26: =+((1/(E17%*E18%)-1)*E8*E13%+((1/(E17%*E18%)-1))*E9*E14%+((1/(E17%*E18%))-1)*E10*E15%) -> 49.867811 | F26: =+((1/(F17%*F18%)-1)*F8*F13%+((1/(F17%*F18%)-1))*F9*F14%+((1/(F17%*F18%))-1)*F10*F15%) -> 56.028333 | G26: =+((1/(G17%*G18%)-1)*G8*G13%+((1/(G17%*G18%)-1))*G9*G14%+((1/(G17%*G18%))-1)*G10*G15%) -> 47.853748
B27: Other Conversion Cost | C27: $/t | E27: =+'EZDK Rebar'!J270 -> 119.16396 | F27: =+'EFS Rebar'!J270 -> 130.70155 | G27: =+SUM('ESR Rebar'!E80:E95) -> 120.68528
B28: Total Conversion Cost | C28: $/t | E28: =+E26+E27 -> 169.03177 | F28: =+F26+F27 -> 186.72988 | G28: =+G26+G27 -> 168.53902
B30: Total Variable Manufacturing Cost | C30: $/t | E30: =+E28+E24 -> 438.8998 | F30: =+F28+F24 -> 451.38911 | G30: =+G28+G24 -> 463.47103
B33: Items | C33: Units | E33: EZDK | F33: EFS | G33: ERM | H33: ESR | K33: =G24*16.3 -> 4807.3917
K34: =(G28+21)*16.3 -> 3089.4861
B35: Billet Trade off | E35: 1.0410868 | F35: 1.0384615 | H35: 1.0404568
B36: Landed Cost | E36: 1.0174193
B38: Source
B39: EZDK | C39: $/t | E39: =+E30 -> 438.8998 | F39: =+E30*E35 -> 456.93279 | G39: 429.88 | H39: =+E30*E35 -> 456.93279
B40: EFS | C40: $/t | E40: =+F30*F35 -> 468.75023 | F40: =+F30 -> 451.38911 | G40: =+F30*F35 -> 468.75023 | H40: =+F30*F35 -> 468.75023
B41: ESR | C41: $/t | E41: =+G30*H35 -> 482.22157 | F41: =+G30*H35 -> 482.22157 | G41: =+G30*(H35) -> 482.22157 | H41: =+G30 -> 463.47103
B42: Market | C42: $/t | E42: =+E52 -> 514.36 | F42: =E52 -> 514.36 | G42: =E52 -> 514.36 | H42: =E52 -> 514.36
B44: Minimum Billet Cost | C44: $/t | E44: =MIN(E39:E42) -> 438.8998 | F44: =MIN(F39:F42) -> 451.38911 | G44: =MIN(G39:G42) -> 429.88 | H44: =MIN(H39:H42) -> 456.93279
B46: Market Billet
B48: Base | C48: $/t | E48: 428
B49: Safe Guardes | C49: $/t | E49: 74
B50: Other Costs | C50: $/t | E50: 12.36
B52: Market Price for Billet | C52: $/t | E52: =+SUM(E48:E50) -> 514.36
H54: =1+DRI!G24 -> 3 | I54: / 12

Sheet Rebar
B2: Rebar Productiom | H2: =+Billet!G2 -> 46303
B4: Items | C4: Units | E4: EZDK | F4: EFS | G4: ERM | H4: ESR
B6: Rebar Yield | C6: % | E6: 93.62 | F6: 97.09 | G6: 97.917872 | H6: 96.822729
B8: Sc1 In-house billet
B10: Variable Manufacturing Cost
B12: Material Price | C12: $/t | E12: =+Billet!E30 -> 438.8998 | F12: =+Billet!F30 -> 451.38911 | G12: =+Billet!E30 -> 438.8998 | H12: =+Billet!G30 -> 463.47103
B14: Yeild Effect | C14: $/t | E14: =+E12*((1/E6%)-1) -> 29.91007 | F14: =+F12*((1/F6%)-1) -> 13.52912 | G14: =+G12*((1/G6%)-1) -> 9.3327737 | H14: =+H12*((1/H6%)-1) -> 15.208958
B15: Home Scrap Deduction | C15: $/t | E15: =+'EZDK Rebar'!E193 -> -15.88 | F15: =+'EFS Rebar'!E193 -> -7.24 | G15: =+'ERM Rolling'!E64/'ERM Rolling'!E6 -> -5.2317308 | H15: =+'ESR Rebar'!E146 -> -7.91
B16: Other Conversion Cost | C16: $/t | E16: =+SUM('EZDK Rebar'!E195:E201) -> 16.15312 | F16: =+SUM('EFS Rebar'!E195:E199) -> 12.116607 | G16: =+'ERM Rolling'!E77/'ERM Rolling'!E6 -> 17.008738 | H16: =SUM('ESR Rebar'!E149:E157) -> 14.946021
B17: Total Conversion Cost | C17: $/t | E17: =+E16+E15+E14 -> 30.183189 | F17: =+F16+F15+F14 -> 18.405727 | G17: =+G16+G15+G14 -> 21.109781 | H17: =+H16+H15+H14 -> 22.244979
B19: Total Variable Manufacturing Cost | C19: $/t | E19: =+E17+E12 -> 469.08299 | F19: =+F17+F12 -> 469.79483 | G19: =+G17+G12 -> 460.00958 | H19: =+H17+H12 -> 485.71601
B21: Sc2 In-house billet
B23: Variable Manufacturing Cost
B25: Material Price | C25: $/t | E25: =+Billet!$E$52 -> 514.36 | F25: =+Billet!$E$52 -> 514.36 | G25: =+Billet!$E$52 -> 514.36 | H25: =+Billet!$E$52 -> 514.36
B27: Yeild Effect | C27: $/t | E27: =+E25*((1/E6%)-1) -> 35.052519 | F27: =+F25*((1/F6%)-1) -> 15.416496 | G27: =+G25*((1/G6%)-1) -> 10.937361 | H27: =+H25*((1/H6%)-1) -> 16.878897
B28: Home Scrap Deduction | C28: $/t | E28: =+E15 -> -15.88 | F28: =+F15 -> -7.24 | G28: =+G15 -> -5.2317308 | H28: =+H15 -> -7.91
B29: Other Conversion Cost | C29: $/t | E29: =+E16 -> 16.15312 | F29: =+F16 -> 12.116607 | G29: =+G16 -> 17.008738 | H29: =+H16 -> 14.946021
B30: Total Conversion Cost | C30: $/t | E30: =+E29+E28+E27 -> 35.325638 | F30: =+F29+F28+F27 -> 20.293103 | G30: =+G29+G28+G27 -> 22.714368 | H30: =+H29+H28+H27 -> 23.914918
B32: Total Variable Manufacturing Cost | C32: $/t | E32: =+E30+E25 -> 549.68564 | F32: =+F30+F25 -> 534.6531 | G32: =+G30+G25 -> 537.07437 | H32: =+H30+H25 -> 538.27492
B34: Difference | C34: $/t | E34: =+E19-E32 -> -80.60265 | F34: =+F19-F32 -> -64.85827 | G34: =+G19-G32 -> -77.064788 | H34: =+H19-H32 -> -52.558909
H36: =1+Billet!H54 -> 4 | I36: / 12

Sheet Wire
B2: Wire Rod Productiom | E2: =+Billet!G2 -> 46303
B4: Items | C4: Units | E4: EZDK
B6: Rebar Yield | C6: % | E6: 97.61
B8: Sc1 In-house billet
B10: Variable Manufacturing Cost
B12: Material Price | C12: $/t | E12: =+Billet!E30 -> 438.8998
B14: Yeild Effect | C14: $/t | E14: =+E12*((1/E6%)-1) -> 10.746548
B15: Home Scrap Deduction | C15: $/t | E15: =+'EZDK Wire'!E64/'EZDK Wire'!E6 -> -5.9867284
B16: Other Conversion Cost | C16: $/t | E16: =+'EZDK Wire'!E77/'EZDK Wire'!E6 -> 18.87316
B17: Total Conversion Cost | C17: $/t | E17: =+E16+E15+E14 -> 23.632979
B19: Total Variable Manufacturing Cost | C19: $/t | E19: =+E17+E12 -> 462.53278
B21: Sc2 In-house billet
B23: Variable Manufacturing Cost
B25: Material Price | C25: $/t | E25: =+Billet!$E$52 -> 514.36
B27: Yeild Effect | C27: $/t | E27: =+E25*((1/E6%)-1) -> 12.594206
B28: Home Scrap Deduction | C28: $/t | E28: =+E15 -> -5.9867284
B29: Other Conversion Cost | C29: $/t | E29: =+E16 -> 18.87316
B30: Total Conversion Cost | C30: $/t | E30: =+E29+E28+E27 -> 25.480637
B32: Total Variable Manufacturing Cost | C32: $/t | E32: =+E30+E25 -> 539.84064
B34: Difference | C34: $/t | E34: =+E19-E32 -> -77.307859
E36: =1+Rebar!H36 -> 5 | F36: / 12

Sheet Flat
B2: HRC Production Cost | F2: =+DRI!F2 -> 46303
B4: Item | C4: Unit | E4: EZDK | F4: EFS
B6: DRI Margin From ERM | C6: $/t | F6: 1.6285249
B7: FX | C7: $/LE | D7: =+DRI!E6 -> 16.2
B8: DRI Price | C8: $/t | E8: =+DRI!E22 -> 262.42129 | F8: =+DRI!F22+F6 -> 267.30003
B9: Local Scrap Price | C9: $/t | E9: 248.87 | F9: 248.87
B10: Imported Scrap Landed Cost | C10: $/t | E10: 275.51 | F10: 267.27
B11: Elictricity Price | C11: $/KWH | E11: 0.07 | F11: 0.07
B13: DRI Blending Ratio | C13: % | E13: 80 | F13: 80
B14: Local Scrap | C14: % | E14: 16.998 | F14: 14
B15: Imported Scrap | C15: % | E15: 3 | F15: 5.978
B17: EAF Yield | C17: % | E17: 85.22 | F17: 84.17
B18: TSC Yield | C18: % | E18: 98.73 | F18: 98
B19: HSM Yield | C19: % | E19: 97.68 | F19: 98
B20: EAF & LF Electricity Consumption | C20: KWH/tms | E20: 693.12 | F20: 708.39
B22: Variable Manufacturing Cost
B24: Material Price | C24: $/t | E24: =E8*E13%+E9*E14%+E10*E15% -> 260.50525 | F24: =F8*F13%+F9*F14%+F10*F15% -> 264.65922
B26: Yield Effect | C26: $/t | E26: =+((1/(E17%*E18%*E19%)-1)*E8*E13%+((1/(E17%*E18%*E19%)-1))*E9*E14%+((1/(E17%*E18%*E19%))-1)*E10*E15%) -> 56.466212 | F26: =+((1/(F17%*F18%*F19%)-1)*F8*F13%+((1/(F17%*F18%*F19%)-1))*F9*F14%+((1/(F17%*F18%*F19%))-1)*F10*F15%) -> 62.739932
B27: Other Conversion Cost | C27: $/t | E27: =+'EZDK Flat'!J269 -> 125.9086 | F27: =+'EFS Flat'!J269 -> 151.84056
B28: Total Conversion Cost | C28: $/t | E28: =+E26+E27 -> 182.37482 | F28: =+F26+F27 -> 214.58049
B30: Total Variable Manufacturing Cost | C30: $/t | E30: =+E28+E24 -> 442.88007 | F30: =+F28+F24 -> 479.23971
F32: =1+Wire!E36 -> 6 | G32: / 12

Sheet Market Share
B2: Monthly Market Share | G2: =+Flat!F2 -> 46303
B4: Item | C4: Units | E4: Rebar | F4: Wire Rod | G4: HRC
B6: EZDK | C6: Ktons | E6: 100 | F6: 40 | G6: 45
B7: EFS | C7: Ktons | E7: 70 | G7: 7.5
B8: ERM | C8: Ktons | E8: 30
B9: ESR | C9: Ktons | E9: 70
B11: Group Local Sales Quantity | C11: Ktons | E11: =SUM(E6:E9) -> 270 | F11: =+F6 -> 40 | G11: =SUM(G22:G23) -> 0
B12: Ezz Steel market Share | C12: % | E12: =+E11/E22*100 -> 51.428571 | F12: =+F11/F22*100 -> 53.333333 | H12: Ezz Steel
E13: =100-E12 -> 48.571429 | F13: =100-F12 -> 46.666667 | H13: Other
B14: EZDK % from Group sales | C14: % | E14: =+E6/E11*100 -> 37.037037 | F14: =+F6/F11*100 -> 100 | G14: =+G6/G11*100 -> #DIV/0!
B15: EFS % from Group sales | C15: % | E15: =E7/E11*100 -> 25.925926 | G15: =+G7/G11*100 -> #DIV/0!
B16: ERM % from Group sales | C16: % | E16: =+E8/E11*100 -> 11.111111
B17: ESR % from Group sales | C17: % | E17: =+E9/E11*100 -> 25.925926
B19: EZDK Export | C19: Ktons | F19: 10 | G19: 40
B20: EFS Export | C20: Ktons | G20: 7.5
B22: Total Local Market | C22: Ktons | E22: 525 | F22: 75 | G22: N/A
B25: Selling Prices | C25: Units | E25: Rebar | F25: Wire Rod | G25: HRC
B27: FX | D27: =+'Fixed Cost'!D15 -> 16.2
B29: EZDK | C29: LE/ton | E29: 9300 | F29: 9075 | G29: 8900
B30: EFS | C30: LE/ton | E30: 9300 | G30: 8900
B31: ERM | C31: LE/ton | E31: 9300
B32: ESR | C32: LE/ton | E32: 9300
B34: EZDK | C34: $/ton | E34: 490 | F34: 480 | G34: 510
B35: EFS | C35: $/ton | E35: 490 | G35: 510
B36: ERM | C36: $/ton | E36: 490
B37: ESR | C37: $/ton | E37: 490
E39: =1+Flat!F32 -> 7 | F39: / 12

Sheet Production Requirments
B2: Monthly Production requirment | I2: ='Market Share'!G2 -> 46303
B4: Item | C4: Unit | E4: EZDK | F4: EFS | G4: ERM | H4: ESR | I4: Total
B6: 1 - Long Production Line
B7: Rebars | C7: Ktons | E7: ='Market Share'!E6 -> 100 | F7: ='Market Share'!E7 -> 70 | G7: ='Market Share'!E8 -> 30 | H7: ='Market Share'!E9 -> 70 | I7: =SUM(E7:H7) -> 270
B8: Wire Rod | C8: Ktons | E8: ='Market Share'!F6+'Market Share'!F19 -> 50 | I8: =SUM(E8:H8) -> 50
B10: Billet | C10: Ktons | E10: =+'EZDK Rebar'!E104/1000 -> 158.03904 | F10: ='EFS Rebar'!E104/1000 -> 72.098053 | G10: =+'ERM Rolling'!E21/1000 -> 30.637921 | H10: ='ESR Rebar'!E19/1000 -> 72.297074 | I10: =SUM(E10:H10) -> 333.07209
B11: Molten Steel | C11: Ktons | E11: ='EZDK Rebar'!E19/1000 -> 159.025 | F11: ='EFS Rebar'!E106/1000 -> 73.531926 | H11: =H10/'ESR Rebar'!E21 -> 73.398044 | I11: =SUM(E11:H11) -> 305.95497
B12: EAF Solid Charge (W/O Aux & Alloys) | C12: Ktons | E12: ='EZDK Rebar'!E21/1000 -> 187.24243 | F12: ='EFS Rebar'!E21/1000 -> 87.361205 | H12: ='ESR Rebar'!E23/1000 -> 84.027526 | I12: =SUM(E12:H12) -> 358.63116
B13: DRI Blending Ratio | C13: % | E13: ='EZDK Rebar'!D26 -> 0.8 | F13: ='EFS Rebar'!D26 -> 0.8 | H13: ='ESR Rebar'!D28 -> 0.2
B14: DRI | C14: Ktons | E14: ='EZDK Rebar'!E26/1000 -> 149.79395 | F14: ='EFS Rebar'!E26/1000 -> 69.888964 | H14: ='ESR Rebar'!E28/1000 -> 16.805505 | I14: =SUM(E14:H14) -> 236.48841
B15: Imported Scrap Blending Ratio | C15: % | E15: ='EZDK Rebar'!D24 -> 0.15977 | F15: ='EFS Rebar'!D24 -> 0.05978 | H15: ='ESR Rebar'!D26 -> 0.639867
B16: Imported Scrap | C16: Ktons | E16: ='EZDK Rebar'!E24/1000 -> 29.915723 | F16: ='EFS Rebar'!E24/1000 -> 5.2224528 | H16: ='ESR Rebar'!E26/1000 -> 53.766441 | I16: =SUM(E16:H16) -> 88.904617
B17: Local Scrap Blending Ratio | C17: % | E17: ='EZDK Rebar'!D25 -> 0.04 | F17: ='EFS Rebar'!D25 -> 0.14 | H17: ='ESR Rebar'!D27 -> 0.160133
B18: local Scrap | C18: Ktons | E18: ='EZDK Rebar'!E25/1000 -> 7.4896973 | F18: ='EFS Rebar'!E25/1000 -> 12.230569 | H18: ='ESR Rebar'!E27/1000 -> 13.45558 | I18: =SUM(E18:H18) -> 33.175846
B20: MRMR | C20: ton/ton | E20: ='DRI Cost'!E15 -> 1.5 | G20: ='DRI Cost'!G15 -> 1.43
B21: IOP | C21: Ktons | E21: =E14*E20 -> 224.69092 | G21: =(F14+H14)*G20 -> 123.97309 | I21: =SUM(E21:H21) -> 348.66401
B23: 2 - Flat Production Line
B24: HRC | C24: Ktons | E24: =('EZDK Flat'!E10)/1000 -> 85 | F24: ='EFS Flat'!E10/1000 -> 15 | I24: =SUM(E24:H24) -> 100
B26: Molten steel | C26: Ktons | E26: ='EZDK Flat'!E19/1000 -> 88.138192 | F26: ='EFS Flat'!E19/1000 -> 15.618492 | I26: =SUM(E26:H26) -> 103.75668
B27: EAF Solid Charge (W/O Aux & Alloys) | C27: Ktons | E27: ='EZDK Flat'!E21/1000 -> 103.4243 | F27: ='EFS Flat'!E21/1000 -> 18.55589 | I27: =SUM(E27:H27) -> 121.98019
B28: DRI Blending Ratio | C28: % | E28: ='EZDK Flat'!D26 -> 0.8 | F28: ='EFS Flat'!D26 -> 0.8
B29: DRI | C29: Ktons | E29: ='EZDK Flat'!E26/1000 -> 82.739443 | F29: ='EFS Flat'!E26/1000 -> 14.844712 | I29: =SUM(E29:H29) -> 97.584155
B30: Imported Scrap Blending Ratio | C30: % | E30: ='EZDK Flat'!D24 -> 0.03 | F30: ='EFS Flat'!D24 -> 0.05978
B31: Imported Scrap | C31: Ktons | E31: ='EZDK Flat'!E24/1000 -> 3.1027291 | F31: ='EFS Flat'!E24/1000 -> 1.1092711 | I31: =SUM(E31:H31) -> 4.2120002
B32: Local Scrap Blending Ratio | C32: % | E32: ='EZDK Flat'!D25 -> 0.16998 | F32: ='EFS Flat'!D25 -> 0.14
B33: local Scrap | C33: Ktons | E33: ='EZDK Flat'!E25/1000 -> 17.580063 | F33: ='EFS Flat'!E25/1000 -> 2.5978245 | I33: =SUM(E33:H33) -> 20.177888
B35: MRMR | C35: ton/ton | E35: ='DRI Cost'!E15 -> 1.5 | G35: ='DRI Cost'!G15 -> 1.43
B36: IOP | C36: Ktons | E36: =E29*E35 -> 124.10917 | G36: =F29*G35 -> 21.227938 | I36: =SUM(E36:H36) -> 145.3371
B38: Monthly Production Summary
B39: Rebar | C39: Ktons | E39: =E7 -> 100 | F39: =F7 -> 70 | G39: =+G7 -> 30 | H39: =H7 -> 70 | I39: =SUM(E39:H39) -> 270
B40: Wire Rod | C40: Ktons | E40: =E8 -> 50 | I40: =SUM(E40:H40) -> 50
B41: HRC | C41: Ktons | E41: =E24 -> 85 | F41: =F24 -> 15 | I41: =SUM(E41:H41) -> 100
B42: Billet | C42: Ktons | E42: =E10 -> 158.03904 | F42: =F10 -> 72.098053 | G42: =+G10 -> 30.637921 | H42: =H10 -> 72.297074 | I42: =SUM(E42:H42) -> 333.07209
B43: DRI | C43: Ktons | E43: =E29+E14 -> 232.53339 | F43: =F29+F14 -> 84.733675 | H43: =H29+H14 -> 16.805505 | I43: =SUM(E43:H43) -> 334.07257
B44: IOP | C44: Ktons | E44: =E21+E36 -> 348.80008 | G44: =G21+G36 -> 145.20103 | I44: =SUM(E44:H44) -> 494.00111
B45: Scrap | C45: Ktons | E45: =E16+E18+E31+E33 -> 58.088213 | F45: =F16+F18+F31+F33 -> 21.160117 | H45: =H16+H18+H31+H33 -> 67.222021 | I45: =SUM(E45:H45) -> 146.47035
H47: =1+'Market Share'!E39 -> 8 | I47: / 12

Sheet P&L $ Monthly
B2: P & L Statement per month USD
E4: EZDK | J4: EFS | N4: ERM | P4: ESR | R4: Total
B5: Items | C5: Unit | E5: Rebar | F5: Wire Rod | G5: HRC | H5: Sub-Total | J5: Rebar | K5: HRC | L5: Sub-Total | N5: Rebar | P5: Rebar
B7: Local Sales | C7: Ktons | E7: =+'Market Share'!E6 -> 100 | F7: =+'Market Share'!F6 -> 40 | G7: =+'Market Share'!G6 -> 45 | H7: =SUM(E7:G7) -> 185 | J7: =+'Market Share'!E7 -> 70 | K7: =+'Market Share'!G7 -> 7.5 | L7: =SUM(J7:K7) -> 77.5 | N7: =+'Market Share'!E8 -> 30 | P7: =+'Market Share'!E9 -> 70 | R7: =+P7+L7+H7+N7 -> 362.5
B8: Export Sales | C8: Ktons | E8: =+'Market Share'!E19 -> 0 | F8: =+'Market Share'!F19 -> 10 | G8: =+'Market Share'!G19 -> 40 | H8: =SUM(E8:G8) -> 50 | J8: =+'Market Share'!E20 -> 0 | K8: =+'Market Share'!G20 -> 7.5 | L8: =SUM(J8:K8) -> 7.5 | N8: 0 | P8: 0 | R8: =+P8+L8+H8+N8 -> 57.5
B9: Total Sales Quantity | C9: Ktons | E9: =SUM(E7:E8) -> 100 | F9: =SUM(F7:F8) -> 50 | G9: =SUM(G7:G8) -> 85 | H9: =SUM(H7:H8) -> 235 | J9: =SUM(J7:J8) -> 70 | K9: =SUM(K7:K8) -> 15 | L9: =SUM(L7:L8) -> 85 | N9: =SUM(N7:N8) -> 30 | P9: =SUM(P7:P8) -> 70 | R9: =+P9+L9+H9+N9 -> 420
B11: Local Sales Value | C11: M $ | E11: =+E12*E7/1000 -> 57.407407 | F11: =F12*F7/1000 -> 22.407407 | G11: =G12*G7/1000 -> 24.722222 | H11: =SUM(E11:G11) -> 104.53704 | J11: =J12*J7/1000 -> 40.185185 | K11: =+K12*K7/1000 -> 4.1203704 | L11: =SUM(J11:K11) -> 44.305556 | N11: =N12*N7/1000 -> 17.222222 | P11: =+P12*P9/1000 -> 40.185185 | R11: =+P11+L11+H11+N11 -> 206.25
B12: Price per unit | C12: $/t | E12: =+'Market Share'!E29/'Market Share'!D27 -> 574.07407 | F12: =+'Market Share'!F29/'Market Share'!D27 -> 560.18519 | G12: =+'Market Share'!G29/'Market Share'!D27 -> 549.38272 | H12: =+H11/H7*1000 -> 565.06507 | J12: =+'Market Share'!E30/'Market Share'!D27 -> 574.07407 | K12: =+'Market Share'!G30/'Market Share'!D27 -> 549.38272 | L12: =+L11/L7*1000 -> 571.68459 | N12: =+'Market Share'!E31/'Market Share'!D27 -> 574.07407 | P12: =+'Market Share'!E32/'Market Share'!D27 -> 574.07407 | R12: =+R11/R7*1000 -> 568.96552
B13: Export Sales Value | C13: M $ | E13: =E14*E8/1000 -> 0 | F13: =F14*F8/1000 -> 4.8 | G13: =+G14*G8/1000 -> 20.4 | H13: =SUM(E13:G13) -> 25.2 | J13: 0 | K13: =+K14*K8/1000 -> 3.825 | L13: =+SUM(J13:K13) -> 3.825 | N13: 0 | P13: 0 | R13: =+P13+L13+H13+N13 -> 29.025
B14: Price per unit | C14: $/t | E14: =+'Market Share'!E34 -> 490 | F14: =+'Market Share'!F34 -> 480 | G14: =+'Market Share'!G34 -> 510 | H14: =+H13/H8*1000 -> 504 | J14: 0 | K14: =+'Market Share'!G35 -> 510 | L14: 0 | N14: 0 | P14: 0 | R14: =+R13/R8*1000 -> 504.78261
B15: Total Sales Value | C15: M $ | E15: =+E13+E11 -> 57.407407 | F15: =+F13+F11 -> 27.207407 | G15: =+G13+G11 -> 45.122222 | H15: =SUM(E15:G15) -> 129.73704 | J15: =+J13+J11 -> 40.185185 | K15: =+K13+K11 -> 7.9453704 | L15: =SUM(J15:K15) -> 48.130556 | N15: =+N13+N11 -> 17.222222 | P15: =+P13+P11 -> 40.185185 | R15: =+P15+L15+H15+N15 -> 235.275
B16: Average price per unit | C16: $/t | E16: =+E15*1000/(E9) -> 574.07407 | F16: =F15/F9*1000 -> 544.14815 | G16: =+G15/G9*1000 -> 530.84967 | H16: =+H15/H9*1000 -> 552.0725 | J16: =+J15*1000/(J9) -> 574.07407 | K16: =+K15*1000/(K9) -> 529.69136 | L16: =+L15/L9*1000 -> 566.24183 | N16: =+N15*1000/(N9) -> 574.07407 | P16: =P15/P9*1000 -> 574.07407 | R16: =+R15/R9*1000 -> 560.17857
B18: Varible COGS | C18: M $ | E18: =(+E19*E9)/1000 -> 46.908445 | F18: =+F19*F9/1000 -> 23.126639 | G18: =+G19*G9/1000 -> 37.644925 | H18: =SUM(E18:G18) -> 107.68001 | J18: =J19*J9/1000 -> 32.885737 | K18: =K19*K9/1000 -> 7.1886167 | L18: =SUM(J18:K18) -> 40.074354 | N18: =N19*N9/1000 -> 13.800287 | P18: =P19*P9/1000 -> 34.000121 | R18: =+P18+L18+H18+N18 -> 195.55477
B19: Cost per unit | C19: $/t | E19: =+'EZDK Rebar'!E205 -> 469.08445 | F19: =+'EZDK Wire'!E86/'EZDK Wire'!E6 -> 462.53278 | G19: =+'EZDK Flat'!E205 -> 442.88147 | H19: =+H18/H9*1000 -> 458.21281 | J19: =+'EFS Rebar'!E205 -> 469.79625 | K19: ='EFS Flat'!E205 -> 479.24112 | L19: =+L18/L9*1000 -> 471.46299 | N19: =+'ERM Rolling'!E86/'ERM Rolling'!E6 -> 460.00958 | P19: ='ESR Rebar'!E161 -> 485.71601 | R19: =+R18/R9*1000 -> 465.6066
B21: Exporting expences | C21: $/t | E21: 0 | F21: 0.2 | G21: 0.8 | H21: =SUM(E21:G21) -> 1 | J21: 0 | K21: 0.15 | L21: =+K21 -> 0.15 | N21: 0 | P21: 0 | R21: =+P21+L21+H21+N21 -> 1.15
B23: Contribution Margin value | C23: M $ | E23: =E15-E18-E21 -> 10.498962 | F23: =F15-F18-F21 -> 3.8807685 | G23: =G15-G18-G21 -> 6.677297 | H23: =SUM(E23:G23) -> 21.057027 | J23: =J15-J18-J21 -> 7.2994479 | K23: =K15-K18-K21 -> 0.60675363 | L23: =SUM(I23:K23) -> 7.9062015 | N23: =N15-N18-N21 -> 3.4219348 | P23: =P15-P18-P21 -> 6.1850645 | R23: =+P23+L23+H23+N23 -> 38.570228
B24: CM per unit | C24: $/t | E24: =E23*1000/E9 -> 104.98962 | F24: =F23*1000/F9 -> 77.61537 | G24: =G23*1000/G9 -> 78.556435 | H24: =+H23/H9*1000 -> 89.604372 | J24: =J23*1000/J9 -> 104.27783 | K24: =K23*1000/K9 -> 40.450242 | L24: =+L23/L9*1000 -> 93.014135 | N24: =N23*1000/N9 -> 114.06449 | P24: =P23*1000/P9 -> 88.358065 | R24: =+R23/R9*1000 -> 91.833877
B25: Margin | C25: % | E25: =E24/E16*100 -> 18.288514 | F25: =F24/F16*100 -> 14.263647 | G25: =G24/G16*100 -> 14.798245 | H25: =H24/H16*100 -> 16.230544 | J25: =J24/J16*100 -> 18.164525 | K25: =K24/K16*100 -> 7.6365682 | L25: =L24/L16*100 -> 16.426574 | N25: =N24/N16*100 -> 19.869299 | P25: =P24/P16*100 -> 15.391405 | R25: =R24/R16*100 -> 16.393679
B27: Intercompany Gains
B28: DRI | C28: M $ | N28: 0.17 | R28: =+N28 -> 0.17
B29: Billet | C29: M $
B31: Manufacturing Fixed Cost | C31: M $ | E31: =+'Fixed Cost'!D46 -> 2.4825 | F31: =+'Fixed Cost'!D54 -> 2.4825 | G31: =+'Fixed Cost'!D62 -> 4.965 | H31: =SUM(E31:G31) -> 9.93 | J31: =+'Fixed Cost'!E46 -> 1.77 | K31: =+'Fixed Cost'!E62 -> 1.77 | L31: =SUM(I31:K31) -> 3.54 | N31: =+'Fixed Cost'!F7 -> 1.17 | P31: =+'Fixed Cost'!G46 -> 2.45 | R31: =+P31+L31+H31+N31 -> 17.09
B32: SG&A | C32: M $ | E32: =+'Fixed Cost'!D47 -> 0.915 | F32: =+'Fixed Cost'!D55 -> 0.915 | G32: =+'Fixed Cost'!D63 -> 1.83 | H32: =SUM(E32:G32) -> 3.66 | J32: =+'Fixed Cost'!E47 -> 0.13 | K32: =+'Fixed Cost'!E63 -> 0.13 | L32: =SUM(I32:K32) -> 0.26 | N32: =+'Fixed Cost'!F8 -> 0.84 | P32: =+'Fixed Cost'!G47 -> 2.38 | R32: =+P32+L32+H32+N32 -> 7.14
B33: Net Financing Cost | C33: M $ | E33: =+'Fixed Cost'!D48 -> 1.7475 | F33: =+'Fixed Cost'!D56 -> 1.7475 | G33: =+'Fixed Cost'!D64 -> 3.495 | H33: =SUM(E33:G33) -> 6.99 | J33: =+'Fixed Cost'!E48 -> 1.21 | K33: =+'Fixed Cost'!E64 -> 1.21 | L33: =SUM(I33:K33) -> 2.42 | N33: =+'Fixed Cost'!F9 -> 4.52 | P33: =+'Fixed Cost'!G48 -> 5.17 | R33: =+P33+L33+H33+N33 -> 19.1
B34: Total Fixed Exp | C34: M $ | E34: =SUM(E31:E33) -> 5.145 | F34: =SUM(F31:F33) -> 5.145 | G34: =SUM(G31:G33) -> 10.29 | H34: =SUM(E34:G34) -> 20.58 | J34: =SUM(J31:J33) -> 3.11 | K34: =SUM(K31:K33) -> 3.11 | L34: =SUM(I34:K34) -> 6.22 | N34: =SUM(N31:N33) -> 6.53 | P34: =SUM(P31:P33) -> 10 | R34: =+P34+L34+H34+N34 -> 43.33
B36: Cash Earning before Tax & Dep | C36: M $ | E36: =E23-E34 -> 5.3539619 | F36: =F23-F34 -> -1.2642315 | G36: =G23-G34 -> -3.612703 | H36: =SUM(E36:G36) -> 0.47702738 | J36: =J23-J34 -> 4.1894479 | K36: =K23-K34 -> -2.5032464 | L36: =SUM(I36:K36) -> 1.6862015 | N36: =N23+N28-N34 -> -2.9380652 | P36: =P23-P34 -> -3.8149355 | R36: =+P36+L36+H36+N36 -> -4.5897718
B37: EBTD per unit | C37: $/t | E37: =+E36/E9*1000 -> 53.539619 | F37: =+F36/F9*1000 -> -25.28463 | G37: =+G36/G9*1000 -> -42.502389 | H37: =+H36/H9*1000 -> 2.0299038 | J37: =+J36/J9*1000 -> 59.849255 | K37: =+K36/K9*1000 -> -166.88309 | L37: =+L36/L9*1000 -> 19.837665 | N37: =+N36/N9*1000 -> -97.935506 | P37: =+P36/P9*1000 -> -54.499078 | R37: =+R36/R9*1000 -> -10.928028
B38: Margin | C38: % | E38: =E37/E16*100 -> 9.3262562 | F38: =F37/F16*100 -> -4.6466444 | G38: =G37/G16*100 -> -8.006483 | H38: =H37/H16*100 -> 0.3676879 | J38: =J37/J16*100 -> 10.425354 | K38: =K37/K16*100 -> -31.505723 | L38: =L37/L16*100 -> 3.5033909 | N38: =N37/N16*100 -> -17.059733 | P38: =P37/P16*100 -> -9.4933878 | R38: =R37/R16*100 -> -1.9508115
B40: Depretiation | C40: M $ | E40: ='Fixed Cost'!D49 -> 0.5975 | F40: =+'Fixed Cost'!D57 -> 0.5975 | G40: =+'Fixed Cost'!D65 -> 1.195 | H40: =SUM(E40:G40) -> 2.39 | J40: =+'Fixed Cost'!E49 -> 1.26 | K40: =+'Fixed Cost'!E65 -> 1.26 | L40: =SUM(J40:K40) -> 2.52 | N40: =+'Fixed Cost'!F11 -> 1.24 | P40: =+'Fixed Cost'!G11 -> 0.13 | R40: =+P40+L40+H40+N40 -> 6.28
B41: FC per unit | C41: $/t | E41: =(+E40+E34)/E9*1000 -> 57.425 | F41: =(+F40+F34)/F9*1000 -> 114.85 | G41: =(+G40+G34)/G9*1000 -> 135.11765 | H41: =(H34+H40)*1000/H9 -> 97.744681 | J41: =(+J40+J34)/J9*1000 -> 62.428571 | K41: =(+K40+K34)/K9*1000 -> 291.33333 | L41: =(L34+L40)*1000/L9 -> 102.82353 | N41: =(+N40+N34)/N9*1000 -> 259 | P41: =(+P40+P34)/P9*1000 -> 144.71429 | R41: =(R34+R40)*1000/R9 -> 118.11905
B43: EBT | C43: M $ | E43: =+E36-E40 -> 4.7564619 | F43: =+F36-F40 -> -1.8617315 | G43: =+G36-G40 -> -4.807703 | H43: =SUM(E43:G43) -> -1.9129726 | J43: =+J36-J40 -> 2.9294479 | K43: =+K36-K40 -> -3.7632464 | L43: =SUM(I43:K43) -> -0.83379851 | N43: =+N36-N40 -> -4.1780652 | P43: =+P36-P40 -> -3.9449355 | R43: =+P43+L43+H43+N43 -> -10.869772
B44: EBT per unit | C44: $/t | E44: =+E43/E9*1000 -> 47.564619 | F44: =+F43/F9*1000 -> -37.23463 | G44: =+G43/G9*1000 -> -56.561212 | H44: =+H43/H9*1000 -> -8.140309 | J44: =+J43/J9*1000 -> 41.849255 | K44: =+K43/K9*1000 -> -250.88309 | L44: =+L43/L9*1000 -> -9.8093943 | N44: =+N43/N9*1000 -> -139.26884 | P44: =+P43/P9*1000 -> -56.356221 | R44: =+R43/R9*1000 -> -25.880409
B45: Margin | C45: % | E45: =+E44/E16*100 -> 8.2854498 | F45: =+F44/F16*100 -> -6.8427375 | G45: =+G44/G16*100 -> -10.654845 | H45: =+H44/H16*100 -> -1.4745 | J45: =+J44/J16*100 -> 7.2898703 | K45: =+K44/K16*100 -> -47.364014 | L45: =+L44/L16*100 -> -1.7323684 | N45: =+N44/N16*100 -> -24.259733 | P45: =+P44/P16*100 -> -9.8168901 | R45: =+R44/R16*100 -> -4.6200284
B47: VC + FC | C47: $/t | E47: =E19+E41 -> 526.50945 | F47: =F19+F41 -> 577.38278 | G47: =G19+G41 -> 577.99912 | H47: =H19+H41 -> 555.95749 | J47: =J19+J41 -> 532.22482 | K47: =K19+K41 -> 770.57445 | L47: =L19+L41 -> 574.28652 | N47: =N19+N41 -> 719.00958 | P47: =P19+P41 -> 630.43029 | R47: =R19+R41 -> 583.72565
B48: BE Quantity | C48: K-ton | E48: =(E34+E40)/(E16-E19)*1000 -> 54.695884 | F48: =(F34+F40)/(F16-F19)*1000 -> 70.360521 | G48: =(G34+G40)/(G16-G19)*1000 -> 130.55854 | H48: =(H34+H40)/(H16-H19)*1000 -> 244.72699 | J48: =(J34+J40)/(J16-J19)*1000 -> 41.907279 | K48: =(K34+K40)/(K16-K19)*1000 -> 86.620001 | L48: =(L34+L40)/(L16-L19)*1000 -> 92.214675 | N48: =(N34+N40)/(N16-N19)*1000 -> 68.119357 | P48: =(P34+P40)/(P16-P19)*1000 -> 114.64715 | R48: =(R34+R40)/(R16-R19)*1000 -> 524.57402
H50: =1+'Production Requirments'!H47 -> 9 | I50: / 12

Sheet P&L LE Monthly
B2: P & L Statement per month LE
B4: FX | C4: =+'Fixed Cost'!D15 -> 16.2 | E4: EZDK | J4: EFS | N4: ERM | P4: ESR | R4: Total
B5: Items | C5: Unit | E5: Rebar | F5: Wire Rod | G5: HRC | H5: Sub-Total | J5: Rebar | K5: HRC | L5: Sub-Total | N5: Rebar | P5: Rebar
B7: Local Sales | C7: Ktons | E7: =+'Market Share'!E6 -> 100 | F7: =+'Market Share'!F6 -> 40 | G7: =+'Market Share'!G6 -> 45 | H7: =SUM(E7:G7) -> 185 | J7: =+'Market Share'!E7 -> 70 | K7: =+'Market Share'!G7 -> 7.5 | L7: =SUM(J7:K7) -> 77.5 | N7: =+'Market Share'!E8 -> 30 | P7: =+'Market Share'!E9 -> 70 | R7: =+P7+L7+H7+N7 -> 362.5
B8: Export Sales | C8: Ktons | E8: =+'Market Share'!E19 -> 0 | F8: =+'Market Share'!F19 -> 10 | G8: =+'Market Share'!G19 -> 40 | H8: =SUM(E8:G8) -> 50 | J8: =+'Market Share'!E20 -> 0 | K8: =+'Market Share'!G20 -> 7.5 | L8: =SUM(J8:K8) -> 7.5 | N8: 0 | P8: 0 | R8: =+P8+L8+H8+N8 -> 57.5
B9: Total Sales Quantity | C9: Ktons | E9: =SUM(E7:E8) -> 100 | F9: =SUM(F7:F8) -> 50 | G9: =SUM(G7:G8) -> 85 | H9: =SUM(H7:H8) -> 235 | J9: =SUM(J7:J8) -> 70 | K9: =SUM(K7:K8) -> 15 | L9: =SUM(L7:L8) -> 85 | N9: =SUM(N7:N8) -> 30 | P9: =SUM(P7:P8) -> 70 | R9: =+P9+L9+H9+N9 -> 420
B11: Local Sales Value | C11: M LE | E11: =+E12*E7/1000 -> 930 | F11: =F12*F7/1000 -> 363 | G11: =G12*G7/1000 -> 400.5 | H11: =SUM(E11:G11) -> 1693.5 | J11: =J12*J7/1000 -> 651 | K11: =+K12*K7/1000 -> 66.75 | L11: =SUM(J11:K11) -> 717.75 | N11: =N12*N7/1000 -> 279 | P11: =+P12*P9/1000 -> 651 | R11: =+P11+L11+H11+N11 -> 3341.25
B12: Price per unit | C12: LE/t | E12: =+'Market Share'!E29 -> 9300 | F12: =+'Market Share'!F29 -> 9075 | G12: =+'Market Share'!G29 -> 8900 | H12: =+H11/H7*1000 -> 9154.0541 | J12: =+'Market Share'!E30 -> 9300 | K12: =+'Market Share'!G30 -> 8900 | L12: =+L11/L7*1000 -> 9261.2903 | N12: =+'Market Share'!E31 -> 9300 | P12: =+'Market Share'!E32 -> 9300 | R12: =+R11/R7*1000 -> 9217.2414
B13: Export Sales Value | C13: M LE | E13: =E14*E8/1000 -> 0 | F13: =F14*F8/1000 -> 77.76 | G13: =+G14*G8/1000 -> 330.48 | H13: =SUM(E13:G13) -> 408.24 | J13: 0 | K13: =+K14*K8/1000 -> 61.965 | L13: =SUM(J13:K13) -> 61.965 | N13: 0 | P13: 0 | R13: =+P13+L13+H13+N13 -> 470.205
B14: Price per unit | C14: LE/t | E14: =+'Market Share'!E34*C4 -> 7938 | F14: =+'Market Share'!F34*C4 -> 7776 | G14: =+'Market Share'!G34*C4 -> 8262 | H14: =+H13/H8*1000 -> 8164.8 | J14: 0 | K14: =+'Market Share'!G35*C4 -> 8262 | L14: 0 | N14: 0 | P14: 0 | R14: =+R13/R8*1000 -> 8177.4783
B15: Total Sales Value | C15: M LE | E15: =+E13+E11 -> 930 | F15: =+F13+F11 -> 440.76 | G15: =+G13+G11 -> 730.98 | H15: =SUM(E15:G15) -> 2101.74 | J15: =+J13+J11 -> 651 | K15: =+K13+K11 -> 128.715 | L15: =SUM(J15:K15) -> 779.715 | N15: =+N13+N11 -> 279 | P15: =+P13+P11 -> 651 | R15: =+P15+L15+H15+N15 -> 3811.455
B16: Average price per unit | C16: LE/t | E16: =+E15*1000/(E9) -> 9300 | F16: =F15/F9*1000 -> 8815.2 | G16: =+G15/G9*1000 -> 8599.7647 | H16: =+H15/H9*1000 -> 8943.5745 | J16: =+J15*1000/(J9) -> 9300 | K16: =+K15*1000/(K9) -> 8581 | L16: =+L15/L9*1000 -> 9173.1176 | N16: =+N15*1000/(N9) -> 9300 | P16: =P15/P9*1000 -> 9300 | R16: =+R15/R9*1000 -> 9074.8929
B18: Varible COGS | C18: M LE | E18: =(+E19*E9)/1000 -> 759.91682 | F18: =+F19*F9/1000 -> 374.65155 | G18: =+G19*G9/1000 -> 609.84779 | H18: =SUM(E18:G18) -> 1744.4162 | J18: =J19*J9/1000 -> 532.74894 | K18: =K19*K9/1000 -> 116.45559 | L18: =SUM(J18:K18) -> 649.20454 | N18: =N19*N9/1000 -> 223.56466 | P18: =P19*P9/1000 -> 550.80195 | R18: =+P18+L18+H18+N18 -> 3167.9873
B19: Cost per unit | C19: LE/t | E19: =+'EZDK Rebar'!E205*C4 -> 7599.1682 | F19: =+'EZDK Wire'!E86 -> 7493.031 | G19: =+'EZDK Flat'!E205*C4 -> 7174.6799 | H19: =+H18/H9*1000 -> 7423.0475 | J19: =+'EFS Rebar'!E205*C4 -> 7610.6992 | K19: ='EFS Flat'!E205*C4 -> 7763.7061 | L19: =+L18/L9*1000 -> 7637.7004 | N19: =+'ERM Rolling'!E86 -> 7452.1552 | P19: ='ESR Rebar'!E161*C4 -> 7868.5993 | R19: =+R18/R9*1000 -> 7542.8269
B21: Exporting expences | C21: LE/t | E21: 0 | F21: =+C4*0.2 -> 3.24 | G21: =+C4*0.8 -> 12.96 | H21: =SUM(E21:G21) -> 16.2 | J21: 0 | K21: =+C4*0.15 -> 2.43 | L21: =+K21 -> 2.43 | N21: 0 | P21: 0 | R21: =+P21+L21+H21+N21 -> 18.63
B23: Contribution Margin value | C23: M LE | E23: =E15-E18-E21 -> 170.08318 | F23: =F15-F18-F21 -> 62.86845 | G23: =G15-G18-G21 -> 108.17221 | H23: =SUM(E23:G23) -> 341.12384 | J23: =J15-J18-J21 -> 118.25106 | K23: =K15-K18-K21 -> 9.8294088 | L23: =SUM(I23:K23) -> 128.08046 | N23: =N15-N18-N21 -> 55.435344 | P23: =P15-P18-P21 -> 100.19805 | R23: =+P23+L23+H23+N23 -> 624.8377
B24: CM per unit | C24: LE/t | E24: =E23*1000/E9 -> 1700.8318 | F24: =F23*1000/F9 -> 1257.369 | G24: =G23*1000/G9 -> 1272.6142 | H24: =+H23/H9*1000 -> 1451.5908 | J24: =J23*1000/J9 -> 1689.3008 | K24: =K23*1000/K9 -> 655.29392 | L24: =+L23/L9*1000 -> 1506.829 | N24: =N23*1000/N9 -> 1847.8448 | P24: =P23*1000/P9 -> 1431.4007 | R24: =+R23/R9*1000 -> 1487.7088
B25: Margin | C25: % | E25: =E24/E16*100 -> 18.288514 | F25: =F24/F16*100 -> 14.263647 | G25: =G24/G16*100 -> 14.798245 | H25: =H24/H16*100 -> 16.230544 | J25: =J24/J16*100 -> 18.164525 | K25: =K24/K16*100 -> 7.6365682 | L25: =L24/L16*100 -> 16.426574 | N25: =N24/N16*100 -> 19.869299 | P25: =P24/P16*100 -> 15.391405 | R25: =R24/R16*100 -> 16.393679
B27: Intercompany Gains
B28: DRI | C28: M LE | N28: =0.17*C4 -> 2.754 | R28: =+N28 -> 2.754
B29: Billet | C29: M LE
B31: Manufacturing Fixed Cost | C31: M LE | E31: =+'Fixed Cost'!D46*C4 -> 40.2165 | F31: =+'Fixed Cost'!D54*C4 -> 40.2165 | G31: =+'Fixed Cost'!D62*C4 -> 80.433 | H31: =SUM(E31:G31) -> 160.866 | J31: =+'Fixed Cost'!E46*C4 -> 28.674 | K31: =+'Fixed Cost'!E62*C4 -> 28.674 | L31: =SUM(I31:K31) -> 57.348 | N31: =+'Fixed Cost'!F7*C4 -> 18.954 | P31: =+'Fixed Cost'!G46*C4 -> 39.69 | R31: =+P31+L31+H31+N31 -> 276.858
B32: SG&A | C32: M LE | E32: =+'Fixed Cost'!D47*C4 -> 14.823 | F32: =+'Fixed Cost'!D55*C4 -> 14.823 | G32: =+'Fixed Cost'!D63*C4 -> 29.646 | H32: =SUM(E32:G32) -> 59.292 | J32: =+'Fixed Cost'!E47*C4 -> 2.106 | K32: =+'Fixed Cost'!E63*C4 -> 2.106 | L32: =SUM(I32:K32) -> 4.212 | N32: =+'Fixed Cost'!F8*C4 -> 13.608 | P32: =+'Fixed Cost'!G47*C4 -> 38.556 | R32: =+P32+L32+H32+N32 -> 115.668
B33: Net Financing Cost | C33: M LE | E33: =+'Fixed Cost'!D48*C4 -> 28.3095 | F33: =+'Fixed Cost'!D56*C4 -> 28.3095 | G33: =+'Fixed Cost'!D64*C4 -> 56.619 | H33: =SUM(E33:G33) -> 113.238 | J33: =+'Fixed Cost'!E48*C4 -> 19.602 | K33: =+'Fixed Cost'!E64*C4 -> 19.602 | L33: =SUM(I33:K33) -> 39.204 | N33: =+'Fixed Cost'!F9*C4 -> 73.224 | P33: =+'Fixed Cost'!G48*C4 -> 83.754 | R33: =+P33+L33+H33+N33 -> 309.42
B34: Total Fixed Exp | C34: M LE | E34: =SUM(E31:E33) -> 83.349 | F34: =SUM(F31:F33) -> 83.349 | G34: =SUM(G31:G33) -> 166.698 | H34: =SUM(E34:G34) -> 333.396 | J34: =SUM(J31:J33) -> 50.382 | K34: =SUM(K31:K33) -> 50.382 | L34: =SUM(I34:K34) -> 100.764 | N34: =SUM(N31:N33) -> 105.786 | P34: =SUM(P31:P33) -> 162 | R34: =+P34+L34+H34+N34 -> 701.946
B36: Cash Earning before Tax & Dep | C36: M LE | E36: =E23-E34 -> 86.734183 | F36: =F23-F34 -> -20.48055 | G36: =G23-G34 -> -58.525789 | H36: =SUM(E36:G36) -> 7.7278436 | J36: =J23-J34 -> 67.869055 | K36: =K23-K34 -> -40.552591 | L36: =SUM(I36:K36) -> 27.316464 | N36: =N23+N28-N34 -> -47.596656 | P36: =P23-P34 -> -61.801954 | R36: =+P36+L36+H36+N36 -> -74.354302
B37: EBTD per unit | C37: LE/t | E37: =+E36/E9*1000 -> 867.34183 | F37: =+F36/F9*1000 -> -409.611 | G37: =+G36/G9*1000 -> -688.5387 | H37: =+H36/H9*1000 -> 32.884441 | J37: =+J36/J9*1000 -> 969.55793 | K37: =+K36/K9*1000 -> -2703.5061 | L37: =+L36/L9*1000 -> 321.37017 | N37: =+N36/N9*1000 -> -1586.5552 | P37: =+P36/P9*1000 -> -882.88506 | R37: =+R36/R9*1000 -> -177.03405
B38: Margin | C38: % | E38: =E37/E16*100 -> 9.3262562 | F38: =F37/F16*100 -> -4.6466444 | G38: =G37/G16*100 -> -8.006483 | H38: =H37/H16*100 -> 0.3676879 | J38: =J37/J16*100 -> 10.425354 | K38: =K37/K16*100 -> -31.505723 | L38: =L37/L16*100 -> 3.5033909 | N38: =N37/N16*100 -> -17.059733 | P38: =P37/P16*100 -> -9.4933878 | R38: =R37/R16*100 -> -1.9508115
B40: Depretiation | C40: M LE | E40: ='Fixed Cost'!D49*C4 -> 9.6795 | F40: =+'Fixed Cost'!D57*C4 -> 9.6795 | G40: =+'Fixed Cost'!D65*C4 -> 19.359 | H40: =SUM(E40:G40) -> 38.718 | J40: =+'Fixed Cost'!E49*C4 -> 20.412 | K40: =+'Fixed Cost'!E65*C4 -> 20.412 | L40: =SUM(J40:K40) -> 40.824 | N40: =+'Fixed Cost'!F11*C4 -> 20.088 | P40: =+'Fixed Cost'!G11*C4 -> 2.106 | R40: =+P40+L40+H40+N40 -> 101.736
B41: FC per unit | C41: LE/t | E41: =(+E40+E34)/E9*1000 -> 930.285 | F41: =(+F40+F34)/F9*1000 -> 1860.57 | G41: =(+G40+G34)/G9*1000 -> 2188.9059 | H41: =(H34+H40)*1000/H9 -> 1583.4638 | J41: =(+J40+J34)/J9*1000 -> 1011.3429 | K41: =(+K40+K34)/K9*1000 -> 4719.6 | L41: =(L34+L40)*1000/L9 -> 1665.7412 | N41: =(+N40+N34)/N9*1000 -> 4195.8 | P41: =(+P40+P34)/P9*1000 -> 2344.3714 | R41: =(R34+R40)*1000/R9 -> 1913.5286
B43: EBT | C43: M LE | E43: =+E36-E40 -> 77.054683 | F43: =+F36-F40 -> -30.16005 | G43: =+G36-G40 -> -77.884789 | H43: =SUM(E43:G43) -> -30.990156 | J43: =+J36-J40 -> 47.457055 | K43: =+K36-K40 -> -60.964591 | L43: =SUM(I43:K43) -> -13.507536 | N43: =+N36-N40 -> -67.684656 | P43: =+P36-P40 -> -63.907954 | R43: =+P43+L43+H43+N43 -> -176.0903
B44: EBT per unit | C44: LE/t | E44: =+E43/E9*1000 -> 770.54683 | F44: =+F43/F9*1000 -> -603.201 | G44: =+G43/G9*1000 -> -916.29164 | H44: =+H43/H9*1000 -> -131.87301 | J44: =+J43/J9*1000 -> 677.95793 | K44: =+K43/K9*1000 -> -4064.3061 | L44: =+L43/L9*1000 -> -158.91219 | N44: =+N43/N9*1000 -> -2256.1552 | P44: =+P43/P9*1000 -> -912.97078 | R44: =+R43/R9*1000 -> -419.26262
B45: Margin | C45: % | E45: =+E44/E16*100 -> 8.2854498 | F45: =+F44/F16*100 -> -6.8427375 | G45: =+G44/G16*100 -> -10.654845 | H45: =+H44/H16*100 -> -1.4745 | J45: =+J44/J16*100 -> 7.2898703 | K45: =+K44/K16*100 -> -47.364014 | L45: =+L44/L16*100 -> -1.7323684 | N45: =+N44/N16*100 -> -24.259733 | P45: =+P44/P16*100 -> -9.8168901 | R45: =+R44/R16*100 -> -4.6200284
B47: VC + FC | C47: LE/t | E47: =E19+E41 -> 8529.4532 | F47: =F19+F41 -> 9353.601 | G47: =G19+G41 -> 9363.5858 | H47: =H19+H41 -> 9006.5113 | J47: =J19+J41 -> 8622.0421 | K47: =K19+K41 -> 12483.306 | L47: =L19+L41 -> 9303.4416 | N47: =N19+N41 -> 11647.955 | P47: =P19+P41 -> 10212.971 | R47: =R19+R41 -> 9456.3555
B48: BE Quantity | C48: K-ton | E48: =(E34+E40)/(E16-E19)*1000 -> 54.695884 | F48: =(F34+F40)/(F16-F19)*1000 -> 70.360521 | G48: =(G34+G40)/(G16-G19)*1000 -> 130.55854 | H48: =(H34+H40)/(H16-H19)*1000 -> 244.72699 | J48: =(J34+J40)/(J16-J19)*1000 -> 41.907279 | K48: =(K34+K40)/(K16-K19)*1000 -> 86.620001 | L48: =(L34+L40)/(L16-L19)*1000 -> 92.214675 | N48: =(N34+N40)/(N16-N19)*1000 -> 68.119357 | P48: =(P34+P40)/(P16-P19)*1000 -> 114.64715 | R48: =(R34+R40)/(R16-R19)*1000 -> 524.57402
P49: =P47*840000 -> 8.5788955e+09
H50: =+'P&L $ Monthly'!H50+1 -> 10 | I50: / 12 | P50: =P49/3 -> 2.8596318e+09

Sheet P&L $ Annual
B2: P & L Statement per Annual USD
E4: EZDK | J4: EFS | N4: ERM | P4: ESR | R4: Total
B5: Items | C5: Unit | E5: Rebar | F5: Wire Rod | G5: HRC | H5: Sub-Total | J5: Rebar | K5: HRC | L5: Sub-Total | N5: Rebar | P5: Rebar
B7: Local Sales | C7: Ktons | E7: =+'Market Share'!E6*12 -> 1200 | F7: =+'Market Share'!F6*12 -> 480 | G7: =+'Market Share'!G6*12 -> 540 | H7: =SUM(E7:G7) -> 2220 | J7: =+'Market Share'!E7*12 -> 840 | K7: =+'Market Share'!G7*12 -> 90 | L7: =SUM(J7:K7) -> 930 | N7: =+'Market Share'!E8*12 -> 360 | P7: =+'Market Share'!E9*12 -> 840 | R7: =+P7+L7+H7+N7 -> 4350
B8: Export Sales | C8: Ktons | E8: =+'Market Share'!E19*12 -> 0 | F8: =+'Market Share'!F19*12 -> 120 | G8: =+'Market Share'!G19*12 -> 480 | H8: =SUM(E8:G8) -> 600 | J8: =+'Market Share'!E20 -> 0 | K8: =+'Market Share'!G20*12 -> 90 | L8: =SUM(J8:K8) -> 90 | N8: 0 | P8: 0 | R8: =+P8+L8+H8+N8 -> 690
B9: Total Sales Quantity | C9: Ktons | E9: =SUM(E7:E8) -> 1200 | F9: =SUM(F7:F8) -> 600 | G9: =SUM(G7:G8) -> 1020 | H9: =SUM(H7:H8) -> 2820 | J9: =SUM(J7:J8) -> 840 | K9: =SUM(K7:K8) -> 180 | L9: =SUM(L7:L8) -> 1020 | N9: =SUM(N7:N8) -> 360 | P9: =SUM(P7:P8) -> 840 | R9: =+P9+L9+H9+N9 -> 5040
B11: Local Sales Value | C11: M $ | E11: =+E12*E7/1000 -> 688.88889 | F11: =F12*F7/1000 -> 268.88889 | G11: =G12*G7/1000 -> 296.66667 | H11: =SUM(E11:G11) -> 1254.4444 | J11: =J12*J7/1000 -> 482.22222 | K11: =+K12*K7/1000 -> 49.444444 | L11: =SUM(J11:K11) -> 531.66667 | N11: =N12*N7/1000 -> 206.66667 | P11: =+P12*P9/1000 -> 482.22222 | R11: =+P11+L11+H11+N11 -> 2475
B12: Price per unit | C12: $/t | E12: =+'Market Share'!E29/'Market Share'!D27 -> 574.07407 | F12: =+'Market Share'!F29/'Market Share'!D27 -> 560.18519 | G12: =+'Market Share'!G29/'Market Share'!D27 -> 549.38272 | H12: =+H11/H7*1000 -> 565.06507 | J12: =+'Market Share'!E30/'Market Share'!D27 -> 574.07407 | K12: =+'Market Share'!G30/'Market Share'!D27 -> 549.38272 | L12: =+L11/L7*1000 -> 571.68459 | N12: =+'Market Share'!E31/'Market Share'!D27 -> 574.07407 | P12: =+'Market Share'!E32/'Market Share'!D27 -> 574.07407 | R12: =+R11/R7*1000 -> 568.96552
B13: Export Sales Value | C13: M $ | E13: =E14*E8/1000 -> 0 | F13: =F14*F8/1000 -> 57.6 | G13: =+G14*G8/1000 -> 244.8 | H13: =SUM(E13:G13) -> 302.4 | J13: 0 | K13: =+K14*K8/1000 -> 45.9 | L13: =+SUM(J13:K13) -> 45.9 | N13: 0 | P13: 0 | R13: =+P13+L13+H13+N13 -> 348.3
B14: Price per unit | C14: $/t | E14: =+'Market Share'!E34 -> 490 | F14: =+'Market Share'!F34 -> 480 | G14: =+'Market Share'!G34 -> 510 | H14: =+H13/H8*1000 -> 504 | J14: 0 | K14: =+'Market Share'!G35 -> 510 | L14: 0 | N14: 0 | P14: 0 | R14: =+R13/R8*1000 -> 504.78261
B15: Total Sales Value | C15: M $ | E15: =+E13+E11 -> 688.88889 | F15: =+F13+F11 -> 326.48889 | G15: =+G13+G11 -> 541.46667 | H15: =SUM(E15:G15) -> 1556.8444 | J15: =+J13+J11 -> 482.22222 | K15: =+K13+K11 -> 95.344444 | L15: =SUM(J15:K15) -> 577.56667 | N15: =+N13+N11 -> 206.66667 | P15: =+P13+P11 -> 482.22222 | R15: =+P15+L15+H15+N15 -> 2823.3
B16: Average price per unit | C16: $/t | E16: =+E15*1000/(E9) -> 574.07407 | F16: =F15/F9*1000 -> 544.14815 | G16: =+G15/G9*1000 -> 530.84967 | H16: =+H15/H9*1000 -> 552.0725 | J16: =+J15*1000/(J9) -> 574.07407 | K16: =+K15*1000/(K9) -> 529.69136 | L16: =+L15/L9*1000 -> 566.24183 | N16: =+N15*1000/(N9) -> 574.07407 | P16: =P15/P9*1000 -> 574.07407 | R16: =+R15/R9*1000 -> 560.17857
B18: Varible COGS | C18: M $ | E18: =(+E19*E9)/1000 -> 562.90135 | F18: =+F19*F9/1000 -> 277.51967 | G18: =+G19*G9/1000 -> 451.7391 | H18: =SUM(E18:G18) -> 1292.1601 | J18: =J19*J9/1000 -> 394.62885 | K18: =K19*K9/1000 -> 86.263401 | L18: =SUM(J18:K18) -> 480.89225 | N18: =N19*N9/1000 -> 165.60345 | P18: =P19*P9/1000 -> 408.00145 | R18: =+P18+L18+H18+N18 -> 2346.6573
B19: Cost per unit | C19: $/t | E19: =+'EZDK Rebar'!E205 -> 469.08445 | F19: =+'EZDK Wire'!E86/'EZDK Wire'!E6 -> 462.53278 | G19: =+'EZDK Flat'!E205 -> 442.88147 | H19: =+H18/H9*1000 -> 458.21281 | J19: =+'EFS Rebar'!E205 -> 469.79625 | K19: ='EFS Flat'!E205 -> 479.24112 | L19: =+L18/L9*1000 -> 471.46299 | N19: =+'ERM Rolling'!E86/'ERM Rolling'!E6 -> 460.00958 | P19: ='ESR Rebar'!E161 -> 485.71601 | R19: =+R18/R9*1000 -> 465.6066
B21: Exporting expences | C21: $/t | E21: 0 | F21: =12*0.2 -> 2.4 | G21: =12*0.8 -> 9.6 | H21: =SUM(E21:G21) -> 12 | J21: 0 | K21: =12*0.15 -> 1.8 | L21: =+K21 -> 1.8 | N21: 0 | P21: 0 | R21: =+P21+L21+H21+N21 -> 13.8
B23: Contribution Margin value | C23: M $ | E23: =E15-E18-E21 -> 125.98754 | F23: =F15-F18-F21 -> 46.569222 | G23: =G15-G18-G21 -> 80.127563 | H23: =SUM(E23:G23) -> 252.68433 | J23: =J15-J18-J21 -> 87.593374 | K23: =K15-K18-K21 -> 7.2810435 | L23: =SUM(I23:K23) -> 94.874418 | N23: =N15-N18-N21 -> 41.063218 | P23: =P15-P18-P21 -> 74.220774 | R23: =+P23+L23+H23+N23 -> 462.84274
B24: CM per unit | C24: $/t | E24: =E23*1000/E9 -> 104.98962 | F24: =F23*1000/F9 -> 77.61537 | G24: =G23*1000/G9 -> 78.556435 | H24: =+H23/H9*1000 -> 89.604372 | J24: =J23*1000/J9 -> 104.27783 | K24: =K23*1000/K9 -> 40.450242 | L24: =+L23/L9*1000 -> 93.014135 | N24: =N23*1000/N9 -> 114.06449 | P24: =P23*1000/P9 -> 88.358065 | R24: =+R23/R9*1000 -> 91.833877
B25: Margin | C25: % | E25: =E24/E16*100 -> 18.288514 | F25: =F24/F16*100 -> 14.263647 | G25: =G24/G16*100 -> 14.798245 | H25: =H24/H16*100 -> 16.230544 | J25: =J24/J16*100 -> 18.164525 | K25: =K24/K16*100 -> 7.6365682 | L25: =L24/L16*100 -> 16.426574 | N25: =N24/N16*100 -> 19.869299 | P25: =P24/P16*100 -> 15.391405 | R25: =R24/R16*100 -> 16.393679
B27: Intercompany Gains
B28: DRI | C28: M $ | N28: =12*0.17 -> 2.04 | R28: =+N28 -> 2.04
B29: Billet | C29: M $
B31: Manufacturing Fixed Cost | C31: M $ | E31: =+'Fixed Cost'!D46*12 -> 29.79 | F31: =+'Fixed Cost'!D54*12 -> 29.79 | G31: =+'Fixed Cost'!D62*12 -> 59.58 | H31: =SUM(E31:G31) -> 119.16 | J31: =+'Fixed Cost'!E46*12 -> 21.24 | K31: =+'Fixed Cost'!E62*12 -> 21.24 | L31: =SUM(I31:K31) -> 42.48 | N31: =+'Fixed Cost'!F7*12 -> 14.04 | P31: =+'Fixed Cost'!G46*12 -> 29.4 | R31: =+P31+L31+H31+N31 -> 205.08
B32: SG&A | C32: M $ | E32: =+'Fixed Cost'!D47*12 -> 10.98 | F32: =+'Fixed Cost'!D55*12 -> 10.98 | G32: =+'Fixed Cost'!D63*12 -> 21.96 | H32: =SUM(E32:G32) -> 43.92 | J32: =+'Fixed Cost'!E47*12 -> 1.56 | K32: =+'Fixed Cost'!E63*12 -> 1.56 | L32: =SUM(I32:K32) -> 3.12 | N32: =+'Fixed Cost'!F8*12 -> 10.08 | P32: =+'Fixed Cost'!G47*12 -> 28.56 | R32: =+P32+L32+H32+N32 -> 85.68
B33: Net Financing Cost | C33: M $ | E33: =+'Fixed Cost'!D48*12 -> 20.97 | F33: =+'Fixed Cost'!D56*12 -> 20.97 | G33: =+'Fixed Cost'!D64*12 -> 41.94 | H33: =SUM(E33:G33) -> 83.88 | J33: =+'Fixed Cost'!E48*12 -> 14.52 | K33: =+'Fixed Cost'!E64*12 -> 14.52 | L33: =SUM(I33:K33) -> 29.04 | N33: =+'Fixed Cost'!F9*12 -> 54.24 | P33: =+'Fixed Cost'!G48*12 -> 62.04 | R33: =+P33+L33+H33+N33 -> 229.2
B34: Total Fixed Exp | C34: M $ | E34: =SUM(E31:E33) -> 61.74 | F34: =SUM(F31:F33) -> 61.74 | G34: =SUM(G31:G33) -> 123.48 | H34: =SUM(E34:G34) -> 246.96 | J34: =SUM(J31:J33) -> 37.32 | K34: =SUM(K31:K33) -> 37.32 | L34: =SUM(I34:K34) -> 74.64 | N34: =SUM(N31:N33) -> 78.36 | P34: =SUM(P31:P33) -> 120 | R34: =+P34+L34+H34+N34 -> 519.96
B36: Cash Earning before Tax & Dep | C36: M $ | E36: =E23-E34 -> 64.247543 | F36: =F23-F34 -> -15.170778 | G36: =G23-G34 -> -43.352437 | H36: =SUM(E36:G36) -> 5.7243286 | J36: =J23-J34 -> 50.273374 | K36: =K23-K34 -> -30.038956 | L36: =SUM(I36:K36) -> 20.234418 | N36: =N23+N28-N34 -> -35.256782 | P36: =P23-P34 -> -45.779226 | R36: =+P36+L36+H36+N36 -> -55.077261
B37: EBTD per unit | C37: $/t | E37: =+E36/E9*1000 -> 53.539619 | F37: =+F36/F9*1000 -> -25.28463 | G37: =+G36/G9*1000 -> -42.502389 | H37: =+H36/H9*1000 -> 2.0299038 | J37: =+J36/J9*1000 -> 59.849255 | K37: =+K36/K9*1000 -> -166.88309 | L37: =+L36/L9*1000 -> 19.837665 | N37: =+N36/N9*1000 -> -97.935506 | P37: =+P36/P9*1000 -> -54.499078 | R37: =+R36/R9*1000 -> -10.928028
B38: Margin | C38: % | E38: =E37/E16*100 -> 9.3262562 | F38: =F37/F16*100 -> -4.6466444 | G38: =G37/G16*100 -> -8.006483 | H38: =H37/H16*100 -> 0.3676879 | J38: =J37/J16*100 -> 10.425354 | K38: =K37/K16*100 -> -31.505723 | L38: =L37/L16*100 -> 3.5033909 | N38: =N37/N16*100 -> -17.059733 | P38: =P37/P16*100 -> -9.4933878 | R38: =R37/R16*100 -> -1.9508115
B40: Depretiation | C40: M $ | E40: ='Fixed Cost'!D49*12 -> 7.17 | F40: =+'Fixed Cost'!D57*12 -> 7.17 | G40: =+'Fixed Cost'!D65*12 -> 14.34 | H40: =SUM(E40:G40) -> 28.68 | J40: =+'Fixed Cost'!E49*12 -> 15.12 | K40: =+'Fixed Cost'!E65*12 -> 15.12 | L40: =SUM(J40:K40) -> 30.24 | N40: =+'Fixed Cost'!F11*12 -> 14.88 | P40: =+'Fixed Cost'!G11*12 -> 1.56 | R40: =+P40+L40+H40+N40 -> 75.36
B41: FC per unit | C41: $/t | E41: =(+E40+E34)/E9*1000 -> 57.425 | F41: =(+F40+F34)/F9*1000 -> 114.85 | G41: =(+G40+G34)/G9*1000 -> 135.11765 | H41: =(H34+H40)*1000/H9 -> 97.744681 | J41: =(+J40+J34)/J9*1000 -> 62.428571 | K41: =(+K40+K34)/K9*1000 -> 291.33333 | L41: =(L34+L40)*1000/L9 -> 102.82353 | N41: =(+N40+N34)/N9*1000 -> 259 | P41: =(+P40+P34)/P9*1000 -> 144.71429 | R41: =(R34+R40)*1000/R9 -> 118.11905
E42: =+E40/E9*1000 -> 5.975 | F42: =+F40/F9*1000 -> 11.95 | G42: =+G40/G9*1000 -> 14.058824 | H42: =+H40/H9*1000 -> 10.170213 | J42: =+J40/J9*1000 -> 18 | K42: =+K40/K9*1000 -> 84 | L42: =+L40/L9*1000 -> 29.647059 | N42: =+N40/N9*1000 -> 41.333333 | P42: =+P40/P9*1000 -> 1.8571429 | R42: =+R40/R9*1000 -> 14.952381
B43: EBT | C43: M $ | E43: =+E36-E40 -> 57.077543 | F43: =+F36-F40 -> -22.340778 | G43: =+G36-G40 -> -57.692437 | H43: =SUM(E43:G43) -> -22.955671 | J43: =+J36-J40 -> 35.153374 | K43: =+K36-K40 -> -45.158956 | L43: =SUM(I43:K43) -> -10.005582 | N43: =+N36-N40 -> -50.136782 | P43: =+P36-P40 -> -47.339226 | R43: =+P43+L43+H43+N43 -> -130.43726
B44: EBT per unit | C44: $/t | E44: =+E43/E9*1000 -> 47.564619 | F44: =+F43/F9*1000 -> -37.23463 | G44: =+G43/G9*1000 -> -56.561212 | H44: =+H43/H9*1000 -> -8.140309 | J44: =+J43/J9*1000 -> 41.849255 | K44: =+K43/K9*1000 -> -250.88309 | L44: =+L43/L9*1000 -> -9.8093943 | N44: =+N43/N9*1000 -> -139.26884 | P44: =+P43/P9*1000 -> -56.356221 | R44: =+R43/R9*1000 -> -25.880409
B45: Margin | C45: % | E45: =+E44/E16*100 -> 8.2854498 | F45: =+F44/F16*100 -> -6.8427375 | G45: =+G44/G16*100 -> -10.654845 | H45: =+H44/H16*100 -> -1.4745 | J45: =+J44/J16*100 -> 7.2898703 | K45: =+K44/K16*100 -> -47.364014 | L45: =+L44/L16*100 -> -1.7323684 | N45: =+N44/N16*100 -> -24.259733 | P45: =+P44/P16*100 -> -9.8168901 | R45: =+R44/R16*100 -> -4.6200284
B47: VC + FC | C47: $/t | E47: =E19+E41 -> 526.50945 | F47: =F19+F41 -> 577.38278 | G47: =G19+G41 -> 577.99912 | H47: =H19+H41 -> 555.95749 | J47: =J19+J41 -> 532.22482 | K47: =K19+K41 -> 770.57445 | L47: =L19+L41 -> 574.28652 | N47: =N19+N41 -> 719.00958 | P47: =P19+P41 -> 630.43029 | R47: =R19+R41 -> 583.72565
B48: BE Quantity | C48: K-ton | E48: =(E34+E40)/(E16-E19)*1000 -> 656.3506 | F48: =(F34+F40)/(F16-F19)*1000 -> 844.32626 | G48: =(G34+G40)/(G16-G19)*1000 -> 1566.7025 | H48: =(H34+H40)/(H16-H19)*1000 -> 2936.7239 | J48: =(J34+J40)/(J16-J19)*1000 -> 502.88735 | K48: =(K34+K40)/(K16-K19)*1000 -> 1039.44 | L48: =(L34+L40)/(L16-L19)*1000 -> 1106.5761 | N48: =(N34+N40)/(N16-N19)*1000 -> 817.43228 | P48: =(P34+P40)/(P16-P19)*1000 -> 1375.7658 | R48: =(R34+R40)/(R16-R19)*1000 -> 6294.8883
H50: =+'P&L LE Monthly'!H50+1 -> 11 | I50: / 12

Sheet P&L LE Annual
B2: P & L Statement per month LE
B4: FX | C4: =+'Fixed Cost'!D15 -> 16.2 | E4: EZDK | J4: EFS | N4: ERM | P4: ESR | R4: Total
B5: Items | C5: Unit | E5: Rebar | F5: Wire Rod | G5: HRC | H5: Sub-Total | J5: Rebar | K5: HRC | L5: Sub-Total | N5: Rebar | P5: Rebar
B7: Local Sales | C7: Ktons | E7: =+'Market Share'!E6*12 -> 1200 | F7: =+'Market Share'!F6*12 -> 480 | G7: =+'Market Share'!G6*12 -> 540 | H7: =SUM(E7:G7) -> 2220 | J7: =+'Market Share'!E7*12 -> 840 | K7: =+'Market Share'!G7*12 -> 90 | L7: =SUM(J7:K7) -> 930 | N7: =+'Market Share'!E8*12 -> 360 | P7: =+'Market Share'!E9*12 -> 840 | R7: =+P7+L7+H7+N7 -> 4350
B8: Export Sales | C8: Ktons | E8: =+'Market Share'!E19 -> 0 | F8: =+'Market Share'!F19*12 -> 120 | G8: =+'Market Share'!G19*12 -> 480 | H8: =SUM(E8:G8) -> 600 | J8: =+'Market Share'!E20 -> 0 | K8: =+'Market Share'!G20*12 -> 90 | L8: =SUM(J8:K8) -> 90 | N8: 0 | P8: 0 | R8: =+P8+L8+H8+N8 -> 690
B9: Total Sales Quantity | C9: Ktons | E9: =SUM(E7:E8) -> 1200 | F9: =SUM(F7:F8) -> 600 | G9: =SUM(G7:G8) -> 1020 | H9: =SUM(H7:H8) -> 2820 | J9: =SUM(J7:J8) -> 840 | K9: =SUM(K7:K8) -> 180 | L9: =SUM(L7:L8) -> 1020 | N9: =SUM(N7:N8) -> 360 | P9: =SUM(P7:P8) -> 840 | R9: =+P9+L9+H9+N9 -> 5040
B11: Local Sales Value | C11: M LE | E11: =+E12*E7/1000 -> 11160 | F11: =F12*F7/1000 -> 4356 | G11: =G12*G7/1000 -> 4806 | H11: =SUM(E11:G11) -> 20322 | J11: =J12*J7/1000 -> 7812 | K11: =+K12*K7/1000 -> 801 | L11: =SUM(J11:K11) -> 8613 | N11: =N12*N7/1000 -> 3348 | P11: =+P12*P9/1000 -> 7812 | R11: =+P11+L11+H11+N11 -> 40095
B12: Price per unit | C12: LE/t | E12: =+'Market Share'!E29 -> 9300 | F12: =+'Market Share'!F29 -> 9075 | G12: =+'Market Share'!G29 -> 8900 | H12: =+H11/H7*1000 -> 9154.0541 | J12: =+'Market Share'!E30 -> 9300 | K12: =+'Market Share'!G30 -> 8900 | L12: =+L11/L7*1000 -> 9261.2903 | N12: =+'Market Share'!E31 -> 9300 | P12: =+'Market Share'!E32 -> 9300 | R12: =+R11/R7*1000 -> 9217.2414
B13: Export Sales Value | C13: M LE | E13: =E14*E8/1000 -> 0 | F13: =F14*F8/1000 -> 933.12 | G13: =+G14*G8/1000 -> 3965.76 | H13: =SUM(E13:G13) -> 4898.88 | J13: 0 | K13: =+K14*K8/1000 -> 743.58 | L13: =SUM(J13:K13) -> 743.58 | N13: 0 | P13: 0 | R13: =+P13+L13+H13+N13 -> 5642.46
B14: Price per unit | C14: LE/t | E14: =+'Market Share'!E34*C4 -> 7938 | F14: =+'Market Share'!F34*C4 -> 7776 | G14: =+'Market Share'!G34*C4 -> 8262 | H14: =+H13/H8*1000 -> 8164.8 | J14: 0 | K14: =+'Market Share'!G35*C4 -> 8262 | L14: 0 | N14: 0 | P14: 0 | R14: =+R13/R8*1000 -> 8177.4783
B15: Total Sales Value | C15: M LE | E15: =+E13+E11 -> 11160 | F15: =+F13+F11 -> 5289.12 | G15: =+G13+G11 -> 8771.76 | H15: =SUM(E15:G15) -> 25220.88 | J15: =+J13+J11 -> 7812 | K15: =+K13+K11 -> 1544.58 | L15: =SUM(J15:K15) -> 9356.58 | N15: =+N13+N11 -> 3348 | P15: =+P13+P11 -> 7812 | R15: =+P15+L15+H15+N15 -> 45737.46 | S15: =R15 -> 45737.46
B16: Average price per unit | C16: LE/t | E16: =+E15*1000/(E9) -> 9300 | F16: =F15/F9*1000 -> 8815.2 | G16: =+G15/G9*1000 -> 8599.7647 | H16: =+H15/H9*1000 -> 8943.5745 | J16: =+J15*1000/(J9) -> 9300 | K16: =+K15*1000/(K9) -> 8581 | L16: =+L15/L9*1000 -> 9173.1176 | N16: =+N15*1000/(N9) -> 9300 | P16: =P15/P9*1000 -> 9300 | R16: =+R15/R9*1000 -> 9074.8929
B18: Varible COGS | C18: M LE | E18: =(+E19*E9)/1000 -> 9119.0018 | F18: =+F19*F9/1000 -> 4495.8186 | G18: =+G19*G9/1000 -> 7318.1735 | H18: =SUM(E18:G18) -> 20932.994 | J18: =J19*J9/1000 -> 6392.9873 | K18: =K19*K9/1000 -> 1397.4671 | L18: =SUM(J18:K18) -> 7790.4544 | N18: =N19*N9/1000 -> 2682.7759 | P18: =P19*P9/1000 -> 6609.6235 | R18: =+P18+L18+H18+N18 -> 38015.848
B19: Cost per unit | C19: LE/t | E19: =+'EZDK Rebar'!E205*C4 -> 7599.1682 | F19: =+'EZDK Wire'!E86 -> 7493.031 | G19: =+'EZDK Flat'!E205*C4 -> 7174.6799 | H19: =+H18/H9*1000 -> 7423.0475 | J19: =+'EFS Rebar'!E205*C4 -> 7610.6992 | K19: ='EFS Flat'!E205*C4 -> 7763.7061 | L19: =+L18/L9*1000 -> 7637.7004 | N19: =+'ERM Rolling'!E86 -> 7452.1552 | P19: ='ESR Rebar'!E161*C4 -> 7868.5993 | R19: =+R18/R9*1000 -> 7542.8269
B21: Exporting expences | C21: LE/t | E21: 0 | F21: =+C4*0.2*12 -> 38.88 | G21: =+C4*0.8*12 -> 155.52 | H21: =SUM(E21:G21) -> 194.4 | J21: 0 | K21: =+C4*0.15*12 -> 29.16 | L21: =+K21 -> 29.16 | N21: 0 | P21: 0 | R21: =+P21+L21+H21+N21 -> 223.56
B23: Contribution Margin value | C23: M LE | E23: =E15-E18-E21 -> 2040.9982 | F23: =F15-F18-F21 -> 754.4214 | G23: =G15-G18-G21 -> 1298.0665 | H23: =SUM(E23:G23) -> 4093.4861 | J23: =J15-J18-J21 -> 1419.0127 | K23: =K15-K18-K21 -> 117.95291 | L23: =SUM(I23:K23) -> 1536.9656 | N23: =N15-N18-N21 -> 665.22413 | P23: =P15-P18-P21 -> 1202.3765 | R23: =+P23+L23+H23+N23 -> 7498.0524
B24: CM per unit | C24: LE/t | E24: =E23*1000/E9 -> 1700.8318 | F24: =F23*1000/F9 -> 1257.369 | G24: =G23*1000/G9 -> 1272.6142 | H24: =+H23/H9*1000 -> 1451.5908 | J24: =J23*1000/J9 -> 1689.3008 | K24: =K23*1000/K9 -> 655.29392 | L24: =+L23/L9*1000 -> 1506.829 | N24: =N23*1000/N9 -> 1847.8448 | P24: =P23*1000/P9 -> 1431.4007 | R24: =+R23/R9*1000 -> 1487.7088
B25: Margin | C25: % | E25: =E24/E16*100 -> 18.288514 | F25: =F24/F16*100 -> 14.263647 | G25: =G24/G16*100 -> 14.798245 | H25: =H24/H16*100 -> 16.230544 | J25: =J24/J16*100 -> 18.164525 | K25: =K24/K16*100 -> 7.6365682 | L25: =L24/L16*100 -> 16.426574 | N25: =N24/N16*100 -> 19.869299 | P25: =P24/P16*100 -> 15.391405 | R25: =R24/R16*100 -> 16.393679
B27: Intercompany Gains
B28: DRI | C28: M LE | N28: =0.17*C4*12 -> 33.048 | R28: =+N28 -> 33.048
B29: Billet | C29: M LE
B31: Manufacturing Fixed Cost | C31: M LE | E31: =+'Fixed Cost'!D46*C4*12 -> 482.598 | F31: =+'Fixed Cost'!D54*C4*12 -> 482.598 | G31: =+'Fixed Cost'!D62*C4*12 -> 965.196 | H31: =SUM(E31:G31) -> 1930.392 | J31: =+'Fixed Cost'!E46*C4*12 -> 344.088 | K31: =+'Fixed Cost'!E62*C4*12 -> 344.088 | L31: =SUM(I31:K31) -> 688.176 | N31: =+'Fixed Cost'!F7*C4*12 -> 227.448 | P31: =+'Fixed Cost'!G46*C4*12 -> 476.28 | R31: =+P31+L31+H31+N31 -> 3322.296
B32: SG&A | C32: M LE | E32: =+'Fixed Cost'!D47*C4*12 -> 177.876 | F32: =+'Fixed Cost'!D55*C4*12 -> 177.876 | G32: =+'Fixed Cost'!D63*C4*12 -> 355.752 | H32: =SUM(E32:G32) -> 711.504 | J32: =+'Fixed Cost'!E47*C4*12 -> 25.272 | K32: =+'Fixed Cost'!E63*C4*12 -> 25.272 | L32: =SUM(I32:K32) -> 50.544 | N32: =+'Fixed Cost'!F8*C4*12 -> 163.296 | P32: =+'Fixed Cost'!G47*C4*12 -> 462.672 | R32: =+P32+L32+H32+N32 -> 1388.016
B33: Net Financing Cost | C33: M LE | E33: =+'Fixed Cost'!D48*C4*12 -> 339.714 | F33: =+'Fixed Cost'!D56*C4*12 -> 339.714 | G33: =+'Fixed Cost'!D64*C4*12 -> 679.428 | H33: =SUM(E33:G33) -> 1358.856 | J33: =+'Fixed Cost'!E48*C4*12 -> 235.224 | K33: =+'Fixed Cost'!E64*C4*12 -> 235.224 | L33: =SUM(I33:K33) -> 470.448 | N33: =+'Fixed Cost'!F9*C4*12 -> 878.688 | P33: =+'Fixed Cost'!G48*C4*12 -> 1005.048 | R33: =+P33+L33+H33+N33 -> 3713.04 | S33: =R33/R9 -> 0.73671429
B34: Total Fixed Exp | C34: M LE | E34: =SUM(E31:E33) -> 1000.188 | F34: =SUM(F31:F33) -> 1000.188 | G34: =SUM(G31:G33) -> 2000.376 | H34: =SUM(E34:G34) -> 4000.752 | J34: =SUM(J31:J33) -> 604.584 | K34: =SUM(K31:K33) -> 604.584 | L34: =SUM(I34:K34) -> 1209.168 | N34: =SUM(N31:N33) -> 1269.432 | P34: =SUM(P31:P33) -> 1944 | R34: =+P34+L34+H34+N34 -> 8423.352
B36: Cash Earning before Tax & Dep | C36: M LE | E36: =E23-E34 -> 1040.8102 | F36: =F23-F34 -> -245.7666 | G36: =G23-G34 -> -702.30947 | H36: =SUM(E36:G36) -> 92.734123 | J36: =J23-J34 -> 814.42866 | K36: =K23-K34 -> -486.63109 | L36: =SUM(I36:K36) -> 327.79757 | N36: =N23+N28-N34 -> -571.15987 | P36: =P23-P34 -> -741.62345 | R36: =+P36+L36+H36+N36 -> -892.25163
B37: EBTD per unit | C37: LE/t | E37: =+E36/E9*1000 -> 867.34183 | F37: =+F36/F9*1000 -> -409.611 | G37: =+G36/G9*1000 -> -688.5387 | H37: =+H36/H9*1000 -> 32.884441 | J37: =+J36/J9*1000 -> 969.55793 | K37: =+K36/K9*1000 -> -2703.5061 | L37: =+L36/L9*1000 -> 321.37017 | N37: =+N36/N9*1000 -> -1586.5552 | P37: =+P36/P9*1000 -> -882.88506 | R37: =+R36/R9*1000 -> -177.03405
B38: Margin | C38: % | E38: =E37/E16*100 -> 9.3262562 | F38: =F37/F16*100 -> -4.6466444 | G38: =G37/G16*100 -> -8.006483 | H38: =H37/H16*100 -> 0.3676879 | J38: =J37/J16*100 -> 10.425354 | K38: =K37/K16*100 -> -31.505723 | L38: =L37/L16*100 -> 3.5033909 | N38: =N37/N16*100 -> -17.059733 | P38: =P37/P16*100 -> -9.4933878 | R38: =R37/R16*100 -> -1.9508115
B40: Depretiation | C40: M LE | E40: ='Fixed Cost'!D49*C4*12 -> 116.154 | F40: =+'Fixed Cost'!D57*C4*12 -> 116.154 | G40: =+'Fixed Cost'!D65*C4*12 -> 232.308 | H40: =SUM(E40:G40) -> 464.616 | J40: =+'Fixed Cost'!E49*C4*12 -> 244.944 | K40: =+'Fixed Cost'!E65*C4*12 -> 244.944 | L40: =SUM(J40:K40) -> 489.888 | N40: =+'Fixed Cost'!F11*C4*12 -> 241.056 | P40: =+'Fixed Cost'!G11*C4*12 -> 25.272 | R40: =+P40+L40+H40+N40 -> 1220.832
B41: FC per unit | C41: $/t | E41: =(+E40+E34)/E9*1000 -> 930.285 | F41: =(+F40+F34)/F9*1000 -> 1860.57 | G41: =(+G40+G34)/G9*1000 -> 2188.9059 | H41: =(H34+H40)*1000/H9 -> 1583.4638 | J41: =(+J40+J34)/J9*1000 -> 1011.3429 | K41: =(+K40+K34)/K9*1000 -> 4719.6 | L41: =(L34+L40)*1000/L9 -> 1665.7412 | N41: =(+N40+N34)/N9*1000 -> 4195.8 | P41: =(+P40+P34)/P9*1000 -> 2344.3714 | R41: =(R34+R40)*1000/R9 -> 1913.5286
B43: EBT | C43: M LE | E43: =+E36-E40 -> 924.6562 | F43: =+F36-F40 -> -361.9206 | G43: =+G36-G40 -> -934.61747 | H43: =SUM(E43:G43) -> -371.88188 | J43: =+J36-J40 -> 569.48466 | K43: =+K36-K40 -> -731.57509 | L43: =SUM(I43:K43) -> -162.09043 | N43: =+N36-N40 -> -812.21587 | P43: =+P36-P40 -> -766.89545 | R43: =+P43+L43+H43+N43 -> -2113.0836
B44: EBT per unit | C44: LE/t | E44: =+E43/E9*1000 -> 770.54683 | F44: =+F43/F9*1000 -> -603.201 | G44: =+G43/G9*1000 -> -916.29164 | H44: =+H43/H9*1000 -> -131.87301 | J44: =+J43/J9*1000 -> 677.95793 | K44: =+K43/K9*1000 -> -4064.3061 | L44: =+L43/L9*1000 -> -158.91219 | N44: =+N43/N9*1000 -> -2256.1552 | P44: =+P43/P9*1000 -> -912.97078 | R44: =+R43/R9*1000 -> -419.26262
B45: Margin | C45: % | E45: =+E44/E16*100 -> 8.2854498 | F45: =+F44/F16*100 -> -6.8427375 | G45: =+G44/G16*100 -> -10.654845 | H45: =+H44/H16*100 -> -1.4745 | J45: =+J44/J16*100 -> 7.2898703 | K45: =+K44/K16*100 -> -47.364014 | L45: =+L44/L16*100 -> -1.7323684 | N45: =+N44/N16*100 -> -24.259733 | P45: =+P44/P16*100 -> -9.8168901 | R45: =+R44/R16*100 -> -4.6200284
B47: VC + FC | C47: $/t | E47: =E19+E41 -> 8529.4532 | F47: =F19+F41 -> 9353.601 | G47: =G19+G41 -> 9363.5858 | H47: =H19+H41 -> 9006.5113 | J47: =J19+J41 -> 8622.0421 | K47: =K19+K41 -> 12483.306 | L47: =L19+L41 -> 9303.4416 | N47: =N19+N41 -> 11647.955 | P47: =P19+P41 -> 10212.971 | R47: =R19+R41 -> 9456.3555
B48: BE Quantity | C48: K-ton | E48: =(E34+E40)/(E16-E19)*1000 -> 656.3506 | F48: =(F34+F40)/(F16-F19)*1000 -> 844.32626 | G48: =(G34+G40)/(G16-G19)*1000 -> 1566.7025 | H48: =(H34+H40)/(H16-H19)*1000 -> 2936.7239 | J48: =(J34+J40)/(J16-J19)*1000 -> 502.88735 | K48: =(K34+K40)/(K16-K19)*1000 -> 1039.44 | L48: =(L34+L40)/(L16-L19)*1000 -> 1106.5761 | N48: =(N34+N40)/(N16-N19)*1000 -> 817.43228 | P48: =(P34+P40)/(P16-P19)*1000 -> 1375.7658 | R48: =(R34+R40)/(R16-R19)*1000 -> 6294.8883
H50: =+'P&L $ Annual'!H50+1 -> 12 | I50: / 12

Sheet P&L Sc2
B2: P & L Statement per month Sc. 2
E4: EZDK | J4: EFS | N4: ERM | P4: ESR | R4: Total
B5: Items | C5: Unit | E5: Rebar | F5: Wire Rod | G5: HRC | H5: Sub-Total | J5: Rebar | K5: HRC | L5: Sub-Total | N5: Rebar | P5: Rebar
B7: Local Sales | C7: Ktons | E7: =+'Market Share'!E6 -> 100 | F7: =+'Market Share'!F6 -> 40 | G7: 40 | H7: =SUM(E7:G7) -> 180 | J7: =+'Market Share'!E7 -> 70 | K7: =+'Market Share'!G7 -> 7.5 | L7: =SUM(J7:K7) -> 77.5 | N7: =+'Market Share'!F8 -> 0 | P7: =+'Market Share'!E9 -> 70 | R7: =+P7+L7+H7+N7 -> 327.5
B8: Export Sales | C8: Ktons | E8: =+'Market Share'!E19 -> 0 | F8: =+'Market Share'!F19 -> 10 | G8: 40 | H8: =SUM(E8:G8) -> 50 | J8: =+'Market Share'!E20 -> 0 | K8: =+'Market Share'!G20 -> 7.5 | L8: =SUM(J8:K8) -> 7.5 | N8: 0 | P8: 0 | R8: =+P8+L8+H8+N8 -> 57.5
B9: Total Sales Quantity | C9: Ktons | E9: =SUM(E7:E8) -> 100 | F9: =SUM(F7:F8) -> 50 | G9: =SUM(G7:G8) -> 80 | H9: =SUM(H7:H8) -> 230 | J9: =SUM(J7:J8) -> 70 | K9: =SUM(K7:K8) -> 15 | L9: =SUM(L7:L8) -> 85 | N9: =SUM(N7:N8) -> 0 | P9: =SUM(P7:P8) -> 70 | R9: =+P9+L9+H9+N9 -> 385
B11: Local Sales Value | C11: M $ | E11: =+E12*E7/1000 -> 57.407407 | F11: =F12*F7/1000 -> 22.407407 | G11: =G12*G7/1000 -> 21.975309 | H11: =SUM(E11:G11) -> 101.79012 | J11: =J12*J7/1000 -> 40.185185 | K11: =+K12*K7/1000 -> 4.1203704 | L11: =SUM(J11:K11) -> 44.305556 | N11: 0 | P11: =+P12*P9/1000 -> 40.185185 | R11: =+P11+L11+H11+N11 -> 186.28086
B12: Price per unit | C12: $/t | E12: =+'Market Share'!E29/'Market Share'!D27 -> 574.07407 | F12: =+'Market Share'!F29/'Market Share'!D27 -> 560.18519 | G12: =+'Market Share'!G29/'Market Share'!D27 -> 549.38272 | H12: =+H11/H7*1000 -> 565.50069 | J12: =+'Market Share'!E30/'Market Share'!D27 -> 574.07407 | K12: =+'Market Share'!G30/'Market Share'!D27 -> 549.38272 | L12: =+L11/L7*1000 -> 571.68459 | N12: 0 | P12: =+'Market Share'!E32/'Market Share'!D27 -> 574.07407
B13: Export Sales Value | C13: M $ | E13: 0 | F13: =F14*F8/1000 -> 4.8 | G13: =+G14*G8/1000 -> 20.4 | H13: =SUM(E13:G13) -> 25.2 | J13: 0 | K13: 0 | L13: 0 | N13: 0 | P13: 0 | R13: =+P13+L13+H13+N13 -> 25.2
B14: Price per unit | C14: $/t | E14: =+'Market Share'!E34 -> 490 | F14: =+'Market Share'!F34 -> 480 | G14: =+'Market Share'!G34 -> 510 | H14: =+H13/H8*1000 -> 504 | J14: 0 | K14: 0 | L14: 0 | N14: 0 | P14: 0 | R14: =+R13/R8*1000 -> 438.26087
B15: Total Sales Value | C15: M $ | E15: =+E13+E11 -> 57.407407 | F15: =+F13+F11 -> 27.207407 | G15: =+G13+G11 -> 42.375309 | H15: =SUM(E15:G15) -> 126.99012 | J15: =+J13+J11 -> 40.185185 | K15: =+K13+K11 -> 4.1203704 | L15: =SUM(J15:K15) -> 44.305556 | N15: =+N13+N11 -> 0 | P15: =+P13+P11 -> 40.185185 | R15: =+P15+L15+H15+N15 -> 211.48086
B16: Average price per unit | C16: $/t | E16: =+E15*1000/(E9) -> 574.07407 | F16: =F15/F9*1000 -> 544.14815 | G16: =+G15/G9*1000 -> 529.69136 | H16: =+H15/H9*1000 -> 552.13097 | J16: =+J15*1000/(J9) -> 574.07407 | K16: =+K15*1000/(K9) -> 274.69136 | L16: =+L15/L9*1000 -> 521.24183 | N16: 0 | P16: =P15/P9*1000 -> 574.07407 | R16: =+R15/R9*1000 -> 549.30095
B18: Varible COGS | C18: M $ | E18: =(+E19*E9)/1000 -> 54.968564 | F18: =+F19*F9/1000 -> 26.992032 | G18: =+G19*G9/1000 -> 35.430518 | H18: =SUM(E18:G18) -> 117.39111 | J18: =J19*J9/1000 -> 37.425717 | K18: =K19*K9/1000 -> 7.1886167 | L18: =SUM(J18:K18) -> 44.614334 | N18: 0 | P18: =P19*P9/1000 -> 37.679244 | R18: =+P18+L18+H18+N18 -> 199.68469
B19: Cost per unit | C19: $/t | E19: =+Rebar!E32 -> 549.68564 | F19: =+Wire!E32 -> 539.84064 | G19: =+'EZDK Flat'!E205 -> 442.88147 | H19: =+H18/H9*1000 -> 510.39615 | J19: =+Rebar!F32 -> 534.6531 | K19: ='EFS Flat'!E205 -> 479.24112 | L19: =+L18/L9*1000 -> 524.87452 | N19: 0 | P19: =+Rebar!H32 -> 538.27492 | R19: =+R18/R9*1000 -> 518.66154
B21: Exporting expences | C21: $/t | E21: 0 | F21: 0.06 | G21: 0.8 | H21: =SUM(E21:G21) -> 0.86 | J21: 0 | K21: 0 | L21: 0 | N21: 0 | P21: 0 | R21: =+P21+L21+H21+N21 -> 0.86
B23: Contribution Margin value | C23: M $ | E23: =E15-E18-E21 -> 2.4388436 | F23: =F15-F18-F21 -> 0.15537556 | G23: =G15-G18-G21 -> 6.1447907 | H23: =SUM(E23:G23) -> 8.7390099 | J23: =J15-J18-J21 -> 2.759468 | K23: =K15-K18-K21 -> -3.0682464 | L23: =SUM(I23:K23) -> -0.30877839 | N23: 0 | P23: =P15-P18-P21 -> 2.5059409 | R23: =+P23+L23+H23+N23 -> 10.936172
B24: CM per unit | C24: $/t | E24: =E23*1000/E9 -> 24.388436 | F24: =F23*1000/F9 -> 3.1075112 | G24: =G23*1000/G9 -> 76.809884 | H24: =+H23/H9*1000 -> 37.995695 | J24: =J23*1000/J9 -> 39.420971 | K24: =K23*1000/K9 -> -204.54976 | L24: =+L23/L9*1000 -> -3.632687 | N24: 0 | P24: =P23*1000/P9 -> 35.799156 | R24: =+R23/R9*1000 -> 28.405643
B25: Margin | C25: % | E25: =E24/E16*100 -> 4.2483082 | F25: =F24/F16*100 -> 0.57107816 | G25: =G24/G16*100 -> 14.500875 | H25: =H24/H16*100 -> 6.8816453 | J25: =J24/J16*100 -> 6.8668788 | K25: =K24/K16*100 -> -74.465305 | L25: =L24/L16*100 -> -0.69692929 | N25: 0 | P25: =P24/P16*100 -> 6.235982 | R25: =R24/R16*100 -> 5.171235
B27: Manufacturing Fixed Cost | C27: M $ | E27: =+'Fixed Cost'!D46 -> 2.4825 | F27: =+'Fixed Cost'!D54 -> 2.4825 | G27: =+'Fixed Cost'!D62 -> 4.965 | H27: =SUM(E27:G27) -> 9.93 | J27: =+'Fixed Cost'!E46 -> 1.77 | K27: =+'Fixed Cost'!E62 -> 1.77 | L27: =SUM(I27:K27) -> 3.54 | N27: =+'Fixed Cost'!F7 -> 1.17 | P27: =+'Fixed Cost'!G46 -> 2.45 | R27: =+P27+L27+H27+N27 -> 17.09
B28: SG&A | C28: M $ | E28: =+'Fixed Cost'!D47 -> 0.915 | F28: =+'Fixed Cost'!D55 -> 0.915 | G28: =+'Fixed Cost'!D63 -> 1.83 | H28: =SUM(E28:G28) -> 3.66 | J28: =+'Fixed Cost'!E47 -> 0.13 | K28: =+'Fixed Cost'!E63 -> 0.13 | L28: =SUM(I28:K28) -> 0.26 | N28: =+'Fixed Cost'!F8 -> 0.84 | P28: =+'Fixed Cost'!G47 -> 2.38 | R28: =+P28+L28+H28+N28 -> 7.14
B29: Net Financing Cost | C29: M $ | E29: =+'Fixed Cost'!D48 -> 1.7475 | F29: =+'Fixed Cost'!D56 -> 1.7475 | G29: =+'Fixed Cost'!D64 -> 3.495 | H29: =SUM(E29:G29) -> 6.99 | J29: =+'Fixed Cost'!E48 -> 1.21 | K29: =+'Fixed Cost'!E64 -> 1.21 | L29: =SUM(I29:K29) -> 2.42 | N29: =+'Fixed Cost'!F9 -> 4.52 | P29: =+'Fixed Cost'!G48 -> 5.17 | R29: =+P29+L29+H29+N29 -> 19.1
B30: Total Fixed Exp | C30: M $ | E30: =SUM(E27:E29) -> 5.145 | F30: =SUM(F27:F29) -> 5.145 | G30: =SUM(G27:G29) -> 10.29 | H30: =SUM(E30:G30) -> 20.58 | J30: =SUM(J27:J29) -> 3.11 | K30: =SUM(K27:K29) -> 3.11 | L30: =SUM(I30:K30) -> 6.22 | N30: =SUM(N27:N29) -> 6.53 | P30: =SUM(P27:P29) -> 10 | R30: =+P30+L30+H30+N30 -> 43.33
B32: Cash Earning before Tax & Dep | C32: M $ | E32: =E23-E30 -> -2.7061564 | F32: =F23-F30 -> -4.9896244 | G32: =G23-G30 -> -4.1452093 | H32: =SUM(E32:G32) -> -11.84099 | J32: =J23-J30 -> -0.35053202 | K32: =K23-K30 -> -6.1782464 | L32: =SUM(I32:K32) -> -6.5287784 | N32: =N23-N30 -> -6.53 | P32: =P23-P30 -> -7.4940591 | R32: =+P32+L32+H32+N32 -> -32.393828
B33: EBTD per unit | C33: $/t | E33: =+E32/E9*1000 -> -27.061564 | F33: =+F32/F9*1000 -> -99.792489 | G33: =+G32/G9*1000 -> -51.815116 | H33: =+H32/H9*1000 -> -51.482566 | J33: =+J32/J9*1000 -> -5.0076003 | K33: =+K32/K9*1000 -> -411.88309 | L33: =+L32/L9*1000 -> -76.809158 | P33: =+P32/P9*1000 -> -107.05799 | R33: =+R32/R9*1000 -> -84.139812
B34: Margin | C34: % | E34: =E33/E16*100 -> -4.7139499 | F34: =F33/F16*100 -> -18.339213 | G34: =G33/G16*100 -> -9.7821335 | H34: =H33/H16*100 -> -9.3243394 | J34: =J33/J16*100 -> -0.87229166 | K34: =K33/K16*100 -> -149.94396 | L34: =L33/L16*100 -> -14.735801 | P34: =P33/P16*100 -> -18.648811 | R34: =R33/R16*100 -> -15.317616
B36: Depretiation | C36: M $ | E36: ='Fixed Cost'!D49 -> 0.5975 | F36: =+'Fixed Cost'!D57 -> 0.5975 | G36: =+'Fixed Cost'!D65 -> 1.195 | H36: =SUM(E36:G36) -> 2.39 | J36: =+'Fixed Cost'!E49 -> 1.26 | K36: =+'Fixed Cost'!E65 -> 1.26 | L36: =SUM(J36:K36) -> 2.52 | N36: =+'Fixed Cost'!F11 -> 1.24 | P36: =+'Fixed Cost'!G11 -> 0.13 | R36: =+P36+L36+H36+N36 -> 6.28
B38: EBT | C38: M $ | E38: =+E32-E36 -> -3.3036564 | F38: =+F32-F36 -> -5.5871244 | G38: =+G32-G36 -> -5.3402093 | H38: =SUM(E38:G38) -> -14.23099 | J38: =+J32-J36 -> -1.610532 | K38: =+K32-K36 -> -7.4382464 | L38: =SUM(I38:K38) -> -9.0487784 | N38: =+N32-N36 -> -7.77 | P38: =+P32-P36 -> -7.6240591 | R38: =+P38+L38+H38+N38 -> -38.673828
B39: EBTD per unit | C39: $/t | E39: =+E38/E9*1000 -> -33.036564 | F39: =+F38/F9*1000 -> -111.74249 | G39: =+G38/G9*1000 -> -66.752616 | H39: =+H38/H9*1000 -> -61.87387 | J39: =+J38/J9*1000 -> -23.0076 | K39: =+K38/K9*1000 -> -495.88309 | L39: =+L38/L9*1000 -> -106.45622 | P39: =+P38/P9*1000 -> -108.91513 | R39: =+R38/R9*1000 -> -100.4515
B40: Margin | C40: % | E40: =+E39/E16*100 -> -5.7547564 | F40: =+F39/F16*100 -> -20.535306 | G40: =+G39/G16*100 -> -12.602172 | H40: =+H39/H16*100 -> -11.206376 | J40: =+J39/J16*100 -> -4.0077755 | K40: =+K39/K16*100 -> -180.52373 | L40: =+L39/L16*100 -> -20.423575 | P40: =+P39/P16*100 -> -18.972313 | R40: =+R39/R16*100 -> -18.287152
H42: =1+'P&L $ Monthly'!H50 -> 10 | I42: / 10

Sheet Production Plan Monthly
B2: Monthly Production & Sales summary 2020 | K2: ='Fixed Cost'!H2 -> 46303
C4: EZDK Sales | E4: EFS | F4: ERM | G4: ESR | J4: EZDK | K4: EFS
C5: Rebar | D5: Rod | E5: Rebar | F5: Rebar | G5: Rebar | J5: Flat | K5: Flat
B6: Local (K-tons) | C6: =+'Market Share'!E6 -> 100 | D6: =+'Market Share'!F6 -> 40 | E6: =+'Market Share'!E7 -> 70 | F6: =+'Market Share'!E8 -> 30 | G6: =+'Market Share'!E9 -> 70 | I6: Local (K-tons) | J6: =+'Market Share'!G6 -> 45 | K6: =+'Market Share'!G20 -> 7.5
B7: Selling Price (LE) | C7: =+'Market Share'!E29 -> 9300 | D7: =+'Market Share'!F29 -> 9075 | E7: =+'Market Share'!E30 -> 9300 | F7: =+'Market Share'!E31 -> 9300 | G7: =+'Market Share'!E32 -> 9300 | I7: Selling Price (LE) | J7: =+'Market Share'!G29 -> 8900 | K7: =+'Market Share'!G30 -> 8900
B8: Export (K-tons) | C8: 0 | D8: =+'Market Share'!F19 -> 10 | I8: Export (K-tons) | J8: =+'Market Share'!G19 -> 40 | K8: =+'Market Share'!G20 -> 7.5
B9: Selling Price ($) | C9: 0 | D9: =+'Market Share'!F34 -> 480 | I9: Selling Price ($) | J9: =+'Market Share'!G34 -> 510 | K9: =+'Market Share'!G35 -> 510
B10: Total Quantity (K-tons) | C10: =+C6+C8 -> 100 | D10: =+D6+D8 -> 50 | E10: =+E6+E8 -> 70 | F10: =+F6+F8 -> 30 | G10: =+G6+G8 -> 70 | I10: Total Quantity (K-tons) | J10: =+J6+J8 -> 85 | K10: =+K6+K8 -> 15
B11: WA Selling Price (LE) | C11: =+'P&L LE Monthly'!E16 -> 9300 | D11: =+'P&L LE Monthly'!F16 -> 8815.2 | E11: ='P&L LE Monthly'!J16 -> 9300 | F11: ='P&L LE Monthly'!N12 -> 9300 | G11: ='P&L LE Monthly'!P12 -> 9300 | I11: WA Selling Price (LE) | J11: =+'P&L LE Monthly'!G16 -> 8599.7647 | K11: ='P&L LE Monthly'!K16 -> 8581
B12: Cost per unit (LE) | C12: =+'P&L LE Monthly'!E19+'P&L LE Monthly'!E41 -> 8529.4532 | D12: =+'P&L LE Monthly'!F19+'P&L LE Monthly'!F41 -> 9353.601 | E12: ='P&L LE Monthly'!J19+'P&L LE Monthly'!J41 -> 8622.0421 | F12: ='P&L LE Monthly'!N19+'P&L LE Monthly'!N41 -> 11647.955 | G12: ='P&L LE Monthly'!P19+'P&L LE Monthly'!P41 -> 10212.971 | I12: Cost per unit (LE) | J12: =+'P&L LE Monthly'!G19+'P&L LE Monthly'!G41 -> 9363.5858 | K12: ='P&L LE Monthly'!K19+'P&L LE Monthly'!K41 -> 12483.306
C16: EZDK | E16: EFS | F16: ERM | G16: ESR | J16: EZDK | K16: EFS
B17: Rebar Yield | C17: =+Rebar!E6/100 -> 0.9362 | D17: =+Wire!E6/100 -> 0.9761 | E17: =+Rebar!F6/100 -> 0.9709 | F17: =+Rebar!G6/100 -> 0.97917872 | G17: =+Rebar!H6/100 -> 0.96822729 | I17: HSM Yield | J17: =Flat!E19% -> 0.9768 | K17: =Flat!F19% -> 0.98
B18: Required Billet (K-tons) | C18: =+C10/C17 -> 106.81478 | D18: =+D10/D17 -> 51.22426 | E18: =+E10/E17 -> 72.098053 | F18: =+F10/F17 -> 30.637921 | G18: =+G10/G17 -> 72.297074 | I18: Required Slabs (K-tons) | J18: =J10/J17 -> 87.018837 | K18: =K10/K17 -> 15.306122
B19: Billet Yield (From Solid Charge) {EAF & CCP} | C19: =+Billet!E17*Billet!E18/10000 -> 0.84403434 | E19: =Billet!F17*Billet!F18/10000 -> 0.82528685 | G19: =Billet!G17*Billet!G18/10000 -> 0.8603975 | I19: Slabs Yield (From Solid Charge) {EAF & TSC} | J19: =Flat!E17*Flat!E18/10000 -> 0.84137706 | K19: =Flat!F17*Flat!F18/10000 -> 0.824866
B20: Required Solid Charge (K-tons) | C20: =+(C18+D18)/C19 -> 187.24243 | E20: =E18/E19 -> 87.361205 | G20: =G18/G19 -> 84.027526 | I20: Required Solid Charge (K-tons) | J20: =J18/J19 -> 103.4243 | K20: =K18/K19 -> 18.55589
B21: DRI Blending Ratio | C21: =+'Production Requirments'!E13 -> 0.8 | E21: =Billet!F13% -> 0.8 | G21: =Billet!G13% -> 0.2 | I21: DRI Blending Ratio | J21: =Flat!E13% -> 0.8 | K21: =Flat!F13% -> 0.8
B22: DRI Required (K-tons) | C22: =+'Production Requirments'!E14 -> 149.79395 | E22: =E21*E20 -> 69.888964 | G22: =G20*G21 -> 16.805505 | I22: DRI Required (K-tons) | J22: =J21*J20 -> 82.739443 | K22: =K21*K20 -> 14.844712
B23: MRMR | C23: =+'Production Requirments'!E20 -> 1.5 | F23: ='Production Requirments'!G20 -> 1.43 | I23: MRMR | J23: ='Production Requirments'!E35 -> 1.5 | K23: ='Production Requirments'!G35 -> 1.43
B24: IOP Required (K-tons) | C24: =+'Production Requirments'!E21 -> 224.69092 | F24: =(E22+G22)*F23 -> 123.97309 | I24: IOP Required (K-tons) | J24: =J23*J22 -> 124.10917 | K24: =K23*K22 -> 21.227938
B27: 2020 Monthly Production plan (K-tons) | W27: =K2 -> 46303
B29: DRP 1 (EZDK) | E29: DRP 2 (EZDK) | H29: DRP 3 (EZDK) | K29: DRP (ERM)
B30: IOP | C30: =C24/2 -> 112.34546 | E30: IOP | F30: =C24/2 -> 112.34546 | H30: IOP | I30: =J24 -> 124.10917 | K30: IOP | L30: =F24+K24 -> 145.20103
B31: MRMR | C31: =C23 -> 1.5 | E31: MRMR | F31: =C23 -> 1.5 | H31: MRMR | I31: =J23 -> 1.5 | K31: MRMR | L31: =F23 -> 1.43
B32: DRI | C32: =C22/2 -> 74.896973 | E32: DRI | F32: =C22/2 -> 74.896973 | H32: DRI | I32: =J22 -> 82.739443 | K32: DRI | L32: =E22+G22+K22 -> 101.53918
B39: DRI | C39: =C22 -> 149.79395 | D39: =C21 -> 0.8 | G39: DRI | H39: =J22 -> 82.739443 | I39: =J21 -> 0.8 | K39: DRI | L39: =E22 -> 69.888964 | M39: =E21 -> 0.8 | O39: DRI | P39: =K22 -> 14.844712 | Q39: =K21 -> 0.8 | S39: DRI | T39: =G22 -> 16.805505 | U39: =G21 -> 0.2
B40: Scrap | C40: =C20-C39 -> 37.448487 | D40: =1-D39 -> 0.2 | G40: Scrap | H40: =J20-H39 -> 20.684861 | I40: =1-I39 -> 0.2 | K40: Scrap | L40: =E20-L39 -> 17.472241 | M40: =1-M39 -> 0.2 | O40: Scrap | P40: =K20-P39 -> 3.7111779 | Q40: =1-Q39 -> 0.2 | S40: Scrap | T40: =G20-T39 -> 67.222021 | U40: =1-U39 -> 0.8
C42: EAF (EZDK) | H42: EAF (EZDK) | K42: EAF (EFS) | O42: EAF (EFS) | S42: EAF (ESR)
C43: Solid Charge | D43: =C20 -> 187.24243 | H43: Solid Charge | I43: =J20 -> 103.4243 | K43: Solid Charge | L43: =E20 -> 87.361205 | O43: Solid Charge | P43: =K20 -> 18.55589 | S43: Solid Charge | T43: =G20 -> 84.027526
C44: EAF Yield | D44: =Billet!E17% -> 0.8493 | H44: EAF Yield | I44: =Flat!E17% -> 0.8522 | K44: EAF Yield | L44: =Billet!F17% -> 0.8417 | O44: EAF Yield | P44: =Flat!F17% -> 0.8417 | S44: EAF Yield | T44: =Billet!G17% -> 0.8735
C45: Molten Steel | D45: =D44*D43 -> 159.025 | H45: Molten Steel | I45: =I43*I44 -> 88.138192 | K45: Molten Steel | L45: =L43*L44 -> 73.531926 | O45: Molten Steel | P45: =P43*P44 -> 15.618492 | S45: Molten Steel | T45: =T43*T44 -> 73.398044
C48: CCP | H48: TSC | K48: CCP | O48: TSC | S48: CCP
C49: Molten Steel | D49: =D45 -> 159.025 | H49: Molten Steel | I49: =I51/I50 -> 88.138192 | K49: Molten Steel | L49: =L45 -> 73.531926 | O49: Molten Steel | P49: =P45 -> 15.618492 | S49: Molten Steel | T49: =T45 -> 73.398044
C50: CCP Yield | D50: =Billet!E18% -> 0.9938 | H50: TSC Yiled | I50: =Flat!E18% -> 0.9873 | K50: CCP Yield | L50: =Billet!F18% -> 0.9805 | O50: TSC Yield | P50: =Flat!F18% -> 0.98 | S50: CCP Yield | T50: =Billet!G18% -> 0.985
C51: Billet | D51: =D49*D50 -> 158.03904 | H51: Slabs | I51: =J18 -> 87.018837 | K51: Billet | L51: =L49*L50 -> 72.098053 | O51: Slabs | P51: =P49*P50 -> 15.306122 | S51: Billet | T51: =T49*T50 -> 72.297074
B55: BMP 1 & 2 | E55: BMP 3 | H55: HSM (EZDK) | K55: BMP (EFS) | O55: HSM (EFS) | S55: BMP (ESR) | W55: BMP (ERM)
B56: Billet | C56: =C58/C57 -> 106.81478 | E56: Billet | F56: =F58/F57 -> 51.22426 | H56: Slabs | I56: =I51 -> 87.018837 | K56: Billet | L56: =L51 -> 72.098053 | O56: Billet | P56: =P51 -> 15.306122 | S56: Billet | T56: =T51 -> 72.297074 | W56: Billet (Imported) | X56: =F18 -> 30.637921
B57: Rebar Yield | C57: =Rebar!E6% -> 0.9362 | E57: Rod Yield | F57: =Wire!E6% -> 0.9761 | H57: HSM Yield | I57: =J17 -> 0.9768 | K57: Rebar Yield | L57: =E17 -> 0.9709 | O57: HSM Yield | P57: =K17 -> 0.98 | S57: Rebar Yield | T57: =Rebar!H6% -> 0.96822729 | W57: Rebar Yield | X57: =F17 -> 0.97917872
B58: Rebars | C58: =C10 -> 100 | E58: Wire Rod | F58: =D10 -> 50 | H58: HRC | I58: =I56*I57 -> 85 | K58: Rebars | L58: =L56*L57 -> 70 | O58: HRC | P58: =P56*P57 -> 15 | S58: Rebars | T58: =T56*T57 -> 70 | W58: Rebars | X58: =X56*X57 -> 30
B60: Sales | E60: Sales | H60: Sales | K60: Sales | O60: Sales | S60: Sales | W60: Sales
B61: Local Sales | C61: =C6 -> 100 | E61: Local Sales | F61: =D6 -> 40 | H61: Local Sales | I61: =J6 -> 45 | K61: Local Sales | L61: =L58 -> 70 | O61: Local Sales | P61: =K6 -> 7.5 | S61: Local Sales | T61: =T58 -> 70 | W61: Local Sales | X61: =X58 -> 30
B62: Selling Price LE | C62: =C7 -> 9300 | E62: Selling Price LE | F62: =D7 -> 9075 | H62: Selling Price LE | I62: =J7 -> 8900 | K62: Selling Price LE | L62: =E7 -> 9300 | O62: Selling Price LE | P62: =K7 -> 8900 | S62: Selling Price LE | T62: =G7 -> 9300 | W62: Selling Price LE | X62: =F11 -> 9300
E63: Eport Sales | F63: =D8 -> 10 | H63: Eport Sales | I63: =J8 -> 40 | O63: Eport Sales | P63: =K8 -> 7.5
E64: Selling Price $ | F64: =D9 -> 480 | H64: Selling Price $ | I64: =J9 -> 510 | O64: Selling Price $ | P64: =K9 -> 510

Sheet BS
C1: 2019
C2: EZDK | D2: EFS | E2: ERM | F2: ESR
B4: Cash
B5: Net Receivable
B6: Net Inventory
B7: Other Current Assets
B8: Total Current assets
B9: Net plant property and Equipment
B10: Perminant level of inventory
B11: Other Non Current Assets
B12: Total Non Current Assets
B13: Total Assets
B15: STL
B16: CPLTD
... B36: Total Liablities and Equity

Sheet Sheet1
B1: Items | C1: Units | E1: Integrated | P1: Semi-Integrated
E2: EZDK Base | J2: EZDK Adjusted (1) | L2: SUEZ Steel (2) | P2: ESR Base | R2: Others (3)
B3: FX: $@LE | E3: ='Fixed Cost'!D15 -> 16.2 | J3: =E3 -> 16.2 | L3: =J3 -> 16.2 | P3: =L3 -> 16.2 | R3: =P3 -> 16.2
B4: Finished Production Millions ton | C4: t | E4: 3000000 | J4: =E4 -> 3000000 | L4: 1200000 | P4: =70*12*1000 -> 840000 | R4: =P4 -> 840000
B5: IOP Price | C5: $/t | E5: 130 | J5: =E5 -> 130 | L5: =J5 -> 130
B6: MRMR | C6: ratio | E6: 1.5 | J6: =E6 -> 1.5 | L6: =J6 -> 1.5
B7: DRI Other Conversion cost | C7: $/t | E7: =DRI!E19 -> 67.421286 | J7: =E7 -> 67.421286 | L7: =J7 -> 67.421286
B8: DRI VC | C8: $/t | E8: =E5*E6+E7 -> 262.42129 | J8: =J5*J6+J7 -> 262.42129 | L8: =L5*L6+L7 -> 262.42129
B10: DRI Cost | C10: $/t | E10: =E8*E11/(E13*E14) -> 265.68088 | J10: =E10 -> 265.68088 | L10: =J10 -> 265.68088
B11: DRI Blending ratio | C11: % | E11: 0.8 | J11: =E11 -> 0.8 | L11: =J11 -> 0.8 | P11: 0 | R11: 0
B12: Scrap Cost | C12: $/t | E12: =300*(1-E11)/(E13*E14) -> 75.931591 | J12: =300*(1-J11)/(J13*J14) -> 75.931591 | L12: =J12 -> 75.931591 | P12: =300*(1-P11)/(P13*P14) -> 360.11797 | R12: =300*(1-R11)/(R13*R14) -> 360.11797
B13: Yield EAF & CCP | C13: % | E13: =Billet!E17*Billet!E18/10000 -> 0.84403434 | J13: =E13 -> 0.84403434 | L13: =J13 -> 0.84403434 | P13: =Billet!G17*Billet!G18/10000 -> 0.8603975 | R13: =P13 -> 0.8603975
B14: Yield rebar % | C14: % | E14: =Rebar!E6/100 -> 0.9362 | J14: =E14 -> 0.9362 | L14: =J14 -> 0.9362 | P14: =Rebar!H6/100 -> 0.96822729 | R14: =P14 -> 0.96822729
B15: Rebar Other Conversion Cost | C15: $/t | E15: =Billet!E27+Rebar!E16+Rebar!E15 -> 119.43708 | J15: =E15 -> 119.43708 | L15: =J15 -> 119.43708 | P15: =Billet!G27+Rebar!H16+Rebar!H15 -> 127.7213 | R15: =P15 -> 127.7213
A16: A | B16: Rebar total Variable Cost | C16: $/t | E16: =E15+E12+E10 -> 461.04954 | F16: =E16*E3 -> 7469.0026 | G16: 7361 | H16: =F16-G16 -> 108.00261 | J16: =J15+J12+J10 -> 461.04954 | L16: =L15+L12+L10 -> 461.04954 | N16: =L16+L18+L19 -> 506.62554 | P16: =P15+P12+P10 -> 487.83927 | R16: =R15+R12+R10 -> 487.83927 | T16: =R16+R18+R19 -> 536.43927
N17: =L4 -> 1200000 | T17: =R4 -> 840000
A18: B | B18: Fixed Mnf / ton $ | C18: $/t | E18: ='P&L $ Annual'!H31*1000000/E4 -> 39.72 | J18: =E18 -> 39.72 | L18: =J18 -> 39.72 | N18: =N17*N16 -> 6.0795065e+08 | P18: ='Fixed Cost'!G7*1000000*12/$P$4 -> 35 | R18: =P18 -> 35 | T18: =T17*T16 -> 4.5060899e+08
B19: SG&A | C19: $/t | E19: ='P&L $ Annual'!H32*1000000/E4 -> 14.64 | J19: =E19 -> 14.64 | L19: =J19*40% -> 5.856 | N19: =N18*L3 -> 9.8488006e+09 | P19: ='Fixed Cost'!G8*1000000*12/$P$4 -> 34 | R19: =P19*40% -> 13.6 | T19: =T18*R3 -> 7.2998656e+09
B20: Net Fixed Ex | C20: $/t | E20: 41 | J20: =E20*(1-(5.5/17)) -> 27.735294 | L20: =N23 -> 18.113598 | M20: =L20/J20 -> 0.65308838 | N20: =N19*90/365 -> 2.4284714e+09 | P20: ='Fixed Cost'!G9*1000000*12/$P$4 -> 73.857143 | R20: =T23 -> 19.179541 | T20: =T19*90/365 -> 1.7999668e+09
B21: Total Fixed Excl Dep /ton $ | C21: $/t | E21: =SUM(E18:E20) -> 95.36 | F21: =E21*E3 -> 1544.832 | G21: =1006000000/705000 -> 1426.9504 | H21: =F21-G21 -> 117.88165 | J21: =SUM(J18:J20) -> 82.095294 | L21: =SUM(L18:L20) -> 63.689598 | N21: =N20*14.5% -> 3.5212835e+08 | P21: =SUM(P18:P20) -> 142.85714 | R21: =SUM(R18:R20) -> 67.779541 | T21: =T20*14.5% -> 2.6099519e+08
N22: =N21/N17 -> 293.44029 | T22: =T21/T17 -> 310.70856
A23: A+B | B23: Total COGS / ton $ | C23: $/t | E23: =E18+E16 -> 500.76954 | J23: =J18+J16 -> 500.76954 | L23: =L18+L16 -> 500.76954 | N23: =N22/L3 -> 18.113598 | P23: =P18+P16 -> 522.83927 | R23: =R18+R16 -> 522.83927 | T23: =T22/R3 -> 19.179541
A24: C | B24: SG&A | C24: $/t | E24: =E19 -> 14.64 | J24: =J19 -> 14.64 | L24: =L19 -> 5.856 | P24: =P19 -> 34 | R24: =R19 -> 13.6
A25: D | B25: =B20 -> Net Fixed Ex | C25: $/t | E25: =E20 -> 41 | J25: =J20 -> 27.735294 | L25: =L20 -> 18.113598 | P25: =P20 -> 73.857143 | R25: =R20 -> 19.179541
A26: A+B+C+D | B26: Total Cost | C26: $/t | E26: =E25+E23+E24 -> 556.40954 | J26: =J25+J23+J24 -> 543.14484 | L26: =L25+L23+L24 -> 524.73914 | P26: =P25+P23+P24 -> 630.69641 | R26: =R25+R23+R24 -> 555.61881
C27: LE/t | E27: =E26*E3 -> 9013.8346 | J27: =J26*J3 -> 8798.9464 | L27: =L26*L3 -> 8500.7741 | P27: =P26*P3 -> 10217.282 | R27: =R26*R3 -> 9001.0247
B29: Main Assumptions
B30: Raw Material Prices (IOP C&F @ $130) (Scrap C&F @ $300)
B31: (1) EZDK Adjusted scenario is calculted by deducting the finance of the 2 sister companies amounting EGP 5.5 bn
B32: (2) Suez Steel Scenario assumed: (a) SG&A 40% of EZDK's (prorated to production capacity) (b) Interest Expense of 14.5% on WC of 90 days Inventory DOH
B33: (3) For level field comparison we assumed same production level of 840 K-ton as ESR assumed: (a) SG&A 2% of Total Revenues (b) Interest Expense of 14.5% on WC of 90 days Inventory DOH

Sheet Sheet2
D2: 43738
C4: DRI | E4: % | F4: % from Rebar | I4: =+C5 -> IOP | J4: =+C6 -> N Gas | K4: =+C9 -> Dep & OH | L4: Labor | M4: Total DRI
C5: IOP | D5: =+D11-SUM(D6:D10) -> 3894.6545 | E5: =+D5/$D$11 -> 0.66361655 | F5: =+D5/$D$30 -> 0.38928678 | H5: =+C5 -> IOP | I5: =+E5 -> 0.66361655 | J5: =+I5 -> 0.66361655 | K5: =J5+J6 -> 0.91230502 | L5: =+K5+K6 -> 0.96649945 | M5: =I5 -> 0.66361655
C6: N Gas | D6: 1459.511 | E6: =+D6/$D$11 -> 0.24868847 | F6: =+D6/$D$30 -> 0.14588415 | H6: =+C6 -> N Gas | J6: =+E6 -> 0.24868847 | K6: =+E9 -> 0.054194433 | L6: =+E10 -> 0.01810213 | M6: =J6 -> 0.24868847
C7: Electricity | D7: 43.991941 | E7: =+D7/$D$11 -> 0.0074958588 | F7: =+D7/$D$30 -> 0.004397176 | H7: =+C9 -> Dep & OH | M7: =K6 -> 0.054194433
C8: Other Utility | D8: =1549.88174394933-D6-D7 -> 46.378803 | E8: =+D8/$D$11 -> 0.0079025602 | F8: =+D8/$D$30 -> 0.0046357527 | H8: =+C10 -> Labor | M8: =+L6 -> 0.01810213
C9: Dep & OH | D9: =((381.572133897876-D10))+42.7242985371549 -> 318.05806 | E9: =+D9/$D$11 -> 0.054194433 | F9: =+D9/$D$30 -> 0.031791215
C10: Labor | D10: 106.23837 | E10: =+D10/$D$11 -> 0.01810213 | F10: =+D10/$D$30 -> 0.010618964
C11: Cost / t | D11: 5868.8326 | E11: =+D11/$D$11 -> 1 | F11: =+D11/$D$30 -> 0.58661404
C13: Billet
C14: Main RM | D14: 6782.124 | E14: =+D14/$D$21 -> 0.7311178 | F14: =+D14/$D$30 -> 0.67790128 | I14: =+C14 -> Main RM | J14: =+C15 -> Aux + Ref +Electrodes | K14: =+C16 -> Energy Ngas | L14: =+C17 -> Energy Electricty | M14: =+C19 -> Dep & OH | N14: Labor | O14: Total Billet
C15: Aux + Ref +Electrodes | D15: =+D21-SUM(D16:D20)-D14 -> 1291.5982 | E15: =+D15/$D$21 -> 0.13923521 | F15: =+D15/$D$30 -> 0.12910057 | H15: Short Term | I15: =+E14 -> 0.7311178 | J15: =+I15 -> 0.7311178 | K15: =+J15+J16 -> 0.87035301 | L15: =+K15+K16 -> 0.87691478 | M15: =+L15+L16 -> 0.94216202 | N15: =+M15+M16 -> 0.95338488 | O15: =J15 -> 0.7311178
B16: 60.869455 | C16: Energy Ngas | D16: 60.869455 | E16: =+D16/$D$21 -> 0.0065617707 | F16: =+D16/$D$30 -> 0.0060841532 | H16: Long Term | J16: =+E15 -> 0.13923521 | K16: =+E16 -> 0.0065617707 | L16: =+F17 -> 0.06524724 | M16: =+E19 -> 0.011222863 | N16: =+E20 -> 0.031352852 | O16: =J16 -> 0.13923521
C17: Energy Electricty | D17: 652.77185 | E17: =+D17/$D$21 -> 0.070369271 | F17: =+D17/$D$30 -> 0.06524724 | H17: Equity | O17: =+K16 -> 0.0065617707
C18: Other Utility | D18: =807.705941550315-D16-D17 -> 94.064632 | E18: =+D18/$D$21 -> 0.010140234 | F18: =+D18/$D$30 -> 0.009402148 | H18: Labor | O18: =+L16 -> 0.06524724
C19: Dep & OH | D19: =394.948367048166-D20 -> 104.10751 | E19: =+D19/$D$21 -> 0.011222863 | F19: =+D19/$D$30 -> 0.010405975 | H19: x | O19: =+M16 -> 0.011222863
C20: Labor | D20: 290.84086 | E20: =+D20/$D$21 -> 0.031352852 | F20: =+D20/$D$30 -> 0.029070744 | H20: xx | O20: =+N16 -> 0.031352852
C21: Cost / t | D21: 9276.3765 | E21: =+D21/$D$21 -> 1 | F21: =+D21/$D$30 -> 0.92721211
C23: Rebar | I23: =+C24 -> RM | J23: =+C26 -> Energy Electricty | K23: =+C28 -> Dep & OH | L23: Labor | M23: Total Rebar
C24: RM | D24: =+D30-SUM(D25:D29) -> 9344.6727 | E24: =+D24/$D$30 -> 0.93403859 | F24: =+D24/$D$30 -> 0.93403859 | H24: =+C24 -> RM | I24: =+E24 -> 0.93403859 | J24: =+I24 -> 0.93403859 | K24: =J24+J25 -> 0.94515511 | L24: =+K24+K25 -> 0.96002509 | M24: =I24 -> 0.93403859
C25: Energy Ngas | D25: 125.35943 | E25: =+D25/$D$30 -> 0.012530192 | F25: =+D25/$D$30 -> 0.012530192 | H25: =+C25 -> Energy Ngas | J25: =+E26 -> 0.011116515 | K25: =+E28 -> 0.014869989 | L25: =+E29 -> 0.026783495 | M25: =J25 -> 0.011116515
C26: Energy Electricty | D26: 111.21617 | E26: =+D26/$D$30 -> 0.011116515 | F26: =+D26/$D$30 -> 0.011116515 | H26: =+C28 -> Dep & OH | M26: =K25 -> 0.014869989
C27: Other Utility | D27: =243.190814843472-D25-D26 -> 6.6152191 | E27: =+D27/$D$30 -> 0.00066121844 | F27: =+D27/$D$30 -> 0.00066121844 | H27: =+C29 -> Labor | M27: =+L25 -> 0.026783495
C28: Dep & OH | D28: =(387.355951077897-D29)+29.3700534436173 -> 148.76813 | E28: =+D28/$D$30 -> 0.014869989 | F28: =+D28/$D$30 -> 0.014869989
C29: Labor | D29: 267.95787 | E29: =+D29/$D$30 -> 0.026783495 | F29: =+D29/$D$30 -> 0.026783495
C30: Cost / t | D30: 10004.59 | E30: =+D30/$D$30 -> 1 | F30: =+D30/$D$30 -> 1

Sheet Sheet4
B2: Estimated Rebar Production Cost for Integrated, Semi-Integrated and Re-rollers as of 30-Dec.-2019
B4: Items | C4: Units | E4: Integrated | H4: Semi Integrated | K4: Re-rollers
E5: EZDK Adj | F5: Others | H5: ESR | I5: Others | K5: ERM | L5: Others
B6: IOP Cost (Including MRMR) | C6: $/t | E6: =+E51*(E62) -> 195 | F6: =+E6 -> 195
B7: DRI Other Conversion Cost | C7: $/t | E7: =E8-E6 -> 67.421286 | F7: =+E7 -> 67.421286
B8: DRI Variable Cost | C8: $/t | E8: =+DRI!E22 -> 262.42129 | F8: =+F6+F7 -> 262.42129
B10: DRI Cost (Including Yield) | C10: $/t | E10: =+E52*E63/100*1/(E64*E65/10000) -> 265.68088 | F10: =+F52*F63/100*1/(F64*F65/10000) -> 265.68088 | H10: =+H52*H63/100*1/(H64*H65/10000) -> 65.940007 | I10: =+I52*I63/100*1/(I64*I65/10000) -> 0
B11: Scrap Cost (Including Yield) | C11: $/t | E11: =+E53*1/(E64*E65/10000)*(100-E63)/100 -> 75.931591 | F11: =+F53*1/(F64*F65/10000)*(100-F63)/100 -> 75.931591 | H11: =+H53*1/(H64*H65/10000)*(100-H63)/100 -> 288.09438 | I11: =+I53*1/(I64*I65/10000)*(100-I63)/100 -> 360.11797
B12: Billet Cost (Including Yield) | C12: $/t | K12: =K54/(K65/100) -> 448.23257 | L12: =L58/(L65/100) -> 525.29736
B13: Rebar Other Conversion Cost | C13: $/t | E13: =+E14-E10-E11 -> 127.47052 | F13: =+E13 -> 127.47052 | H13: =+H14-H10-H11 -> 131.68163 | I13: =+H13 -> 131.68163 | K13: =+K14-K12 -> 11.777007 | L13: =+K13 -> 11.777007
B14: Rebar Variable Cost | C14: $/t | E14: =+Rebar!E19 -> 469.08299 | F14: =+F13+F11+F10 -> 469.08299 | H14: =+Rebar!H19 -> 485.71601 | I14: =+I13+I10+I11 -> 491.7996 | K14: =+Rebar!G19 -> 460.00958 | L14: =+L12+L13 -> 537.07437
P15: Other | Q15: EZDK | U15: ESR
B16: Fixed Mnf Cost | C16: $/t | E16: =+'Fixed Cost'!D7*12*1000000/$E$61 -> 39.72 | F16: =+E16 -> 39.72 | H16: =+'Fixed Cost'!G7*12*1000000/$H$61 -> 35 | I16: =+H16 -> 35 | K16: =+'Fixed Cost'!F7*12*1000000/$K$61 -> 39 | O16: Sales | P16: 12310896000 | Q16: 36099112000 | T16: Se
B17: Mnf Cost | C17: $/t | E17: =+E16+E14 -> 508.80299 | F17: =+P19/F42 -> 574.557 | H17: =+H16+H14 -> 520.71601 | I17: =+I16+I14 -> 526.7996 | K17: =+K16+K14 -> 499.00958 | L17: =+L16+L14 -> 537.07437 | O17: COGS | P17: 11169388000 | Q17: 30620025000
L18: 53 | O18: Production | P18: 1200000 | Q18: 3000000
B19: SG&A | C19: $/t | E19: =+'Fixed Cost'!D8*12*1000000/$E$61 -> 14.64 | F19: =+F45*F44/F42 -> 11.481481 | H19: =+'Fixed Cost'!G8*12*1000000/$H$61 -> 34 | I19: =+I45*I44/I42 -> 11.481481 | K19: =+'Fixed Cost'!F8*12*1000000/$K$61 -> 28 | O19: COGS/t | P19: =P17/P18 -> 9307.8233 | Q19: =Q17/Q18 -> 10206.675 | R19: =+Q19/16 -> 637.91719
B20: Financial Expenses | C20: $/t | E20: =+E78 -> 27.838296 | F20: =+P23/F42 -> 0.3712963 | H20: =+H78 -> 20.108455 | I20: =+I78 -> 19.512689 | K20: =+K78 -> 19.104097 | O20: Sales/t | P20: =P16/P18 -> 10259.08 | Q20: =Q16/Q18 -> 12033.037 | R20: =+Q20/16 -> 752.06483
B21: Total Fixed Excluding Dep | C21: $/t | E21: =+SUM(E19:E20)+E16 -> 82.198296 | F21: =+SUM(F19:F20)+F16 -> 51.572778 | H21: =+SUM(H19:H20)+H16 -> 89.108455 | I21: =+SUM(I19:I20)+I16 -> 65.994171 | K21: =+SUM(K19:K20)+K16 -> 86.104097 | L21: =+SUM(L18:L20)+L16 -> 53
O22: Interest | P22: 7218000 | Q22: 1235531000
B23: Dep | C23: $/t | E23: =+'Fixed Cost'!D11*12*1000000/$E$61 -> 9.56 | F23: =+'Fixed Cost'!E11*12*1000000/$E$61 -> 10.08 | H23: =+'Fixed Cost'!G11*12*1000000/$H$61 -> 1.8571429 | I23: =+H23 -> 1.8571429 | K23: =+'Fixed Cost'!F11*12*1000000/$K$61 -> 41.333333 | L23: =+K23 -> 41.333333 | O23: Interest/t | P23: =+P22/P18 -> 6.015 | Q23: =+Q22/Q18 -> 411.84367
B25: Total Production Cost | C25: $/t | E25: =+E23+E21+E17 -> 600.56128 | F25: =+F23+F21+F17 -> 636.20977 | H25: =+H23+H21+H17 -> 611.68161 | I25: =+I23+I21+I17 -> 594.65091 | K25: =+K23+K21+K17 -> 626.44701 | L25: =+L23+L21+L17 -> 631.4077
C26: LE/t | E26: =+E25*E42 -> 9729.0928 | F26: =+F25*F42 -> 10306.598 | H26: =+H25*H42 -> 9909.242 | I26: =+I25*I42 -> 9633.3447 | K26: =+K25*K42 -> 10148.442 | L26: =+L25*L42 -> 10228.805
B28: EBT | C28: LE/t | E28: =+E44-E26 -> -429.0928 | F28: =+F44-F26 -> -1006.5983 | H28: =+H44-H26 -> -609.24204 | I28: =+I44-I26 -> -333.34473 | K28: =+K44-K26 -> -848.44156 | L28: =+L44-L26 -> -928.80476
B41: Assumptions & Calculations | C41: Units | E41: =+E4 -> Integrated | H41: =+H4 -> Semi Integrated | K41: =+K4 -> Re-rollers
B42: FX | C42: LE/$ | E42: =+'Fixed Cost'!D15 -> 16.2 | F42: =+E42 -> 16.2 | H42: =+'Fixed Cost'!D15 -> 16.2 | I42: =+H42 -> 16.2 | K42: =+'Fixed Cost'!D15 -> 16.2 | L42: =+K42 -> 16.2
B43: Sales & SG&A
B44: Rebar Selling Price | C44: LE/t | E44: 9300 | F44: =+E44 -> 9300 | H44: =+F44 -> 9300 | I44: =+H44 -> 9300 | K44: =I44 -> 9300 | L44: =+K44 -> 9300
B45: SG&A % of total Revenue | C45: % | E45: =E19/+(E44/E42) -> 0.025501935 | F45: 0.02 | H45: 0.02 | I45: 0.02 | K45: 0.02 | L45: 0.02
B47: RM Prices
B48: IOP FOB | C48: $/t
B49: Fright | C49: $/t
B50: Miniral Jetty | C50: $/t
B51: IOP Landed Cost | C51: $/t | E51: =+DRI!E8 -> 130 | F51: =+DRI!E8 -> 130
B52: DRI Price | C52: $/t | E52: =+E8 -> 262.42129 | F52: =+F8 -> 262.42129 | H52: =+Billet!G8 -> 274.66003 | I52: 0
B53: WA Scrap Price | C53: $/t | E53: =('EZDK Rebar'!E24*Billet!E10+'EZDK Rebar'!E25*Billet!E9)/('EZDK Rebar'!E24+'EZDK Rebar'!E25) -> 300 | F53: =('EZDK Rebar'!E24*Billet!E10+'EZDK Rebar'!E25*Billet!E9)/('EZDK Rebar'!E24+'EZDK Rebar'!E25) -> 300 | H53: =+(Billet!G10*'ESR Rebar'!E26+Billet!G9*'ESR Rebar'!E27)/(+'ESR Rebar'!E26+'ESR Rebar'!E27) -> 300 | I53: =+(Billet!G10*'ESR Rebar'!E26+Billet!G9*'ESR Rebar'!E27)/(+'ESR Rebar'!E26+'ESR Rebar'!E27) -> 300
B54: Good Billet Price (EZDK) | C54: $/t | K54: =+Rebar!G12 -> 438.8998
B55: Imported Billet C&F | C55: $/t | L55: =+Billet!E48 -> 428
B56: Safe Guards | C56: $/t | L56: =+Billet!E49 -> 74
B57: Other Costs | C57: $/t | L57: =+Billet!E50 -> 12.36
B58: Billet Landed Cost | C58: $/t | L58: =+SUM(L55:L57) -> 514.36
B60: Production & Yields
B61: Rebar Production Volume | C61: K-tons | E61: =(+'Market Share'!E6+'Market Share'!F6+'Market Share'!G6)*12*1000+780000 -> 3000000 | F61: =+E61-1800000 -> 1200000 | H61: =+'Market Share'!E9*12*1000 -> 840000 | I61: =+H61 -> 840000 | K61: =+'Market Share'!E8*12*1000 -> 360000 | L61: =+K61 -> 360000
B62: DRI MRMR | C62: Ratio | E62: =+DRI!E11 -> 1.5 | F62: =+DRI!E11 -> 1.5
B63: DRI Blending Ratio | C63: % | E63: =+Billet!E13 -> 80 | F63: =+Billet!F13 -> 80 | H63: =+Billet!G13 -> 20 | I63: 0
B64: EAF & CCP Yield | C64: % | E64: =+Billet!E17*Billet!E18/100 -> 84.403434 | F64: =+Billet!E17*Billet!E18/100 -> 84.403434 | H64: =+Billet!G17*Billet!G18/100 -> 86.03975 | I64: =+Billet!G17*Billet!G18/100 -> 86.03975
B65: Rebar Yield | C65: % | E65: =+Rebar!E6 -> 93.62 | F65: =+Rebar!E6 -> 93.62 | H65: =+Rebar!H6 -> 96.822729 | I65: =+Rebar!H6 -> 96.822729 | K65: =+Rebar!G6 -> 97.917872 | L65: =+K65 -> 97.917872
B67: Yield Effect Calculation
B68: MRMR Effect | C68: $/t | E68: =(E62-1)*E6 -> 97.5 | F68: =+E68 -> 97.5
B69: DRI Price | C69: $/t | E69: =+E52 -> 262.42129 | F69: =+F52 -> 262.42129 | H69: =+H52 -> 274.66003 | I69: =+I52 -> 0
B70: DRI Yield Effect | C70: $/t | E70: =(E69*E63/100)*(1/(E64*E65/10000)-1) -> 55.743846 | F70: =(F69*F63/100)*(1/(F64*F65/10000)-1) -> 55.743846 | H70: =(H69*H63/100)*(1/(H64*H65/10000)-1) -> 11.008002 | I70: =(I69*I63/100)*(1/(I64*I65/10000)-1) -> 0
B71: Scrap Price | C71: $/t | E71: =+E53 -> 300 | F71: =+F53 -> 300 | H71: =+H53 -> 300 | I71: =+I53 -> 300
B72: Scrap Yield Effect | C72: $/t | E72: =+E71*((100-E63)/100)*(1/(E64*E65/10000)-1) -> 15.931591 | F72: =+F71*((100-F63)/100)*(1/(F64*F65/10000)-1) -> 15.931591 | H72: =+H71*((100-H63)/100)*(1/(H64*H65/10000)-1) -> 48.094376 | I72: =+I71*((100-I63)/100)*(1/(I64*I65/10000)-1) -> 60.11797
B73: Total Yield Effect | C73: $/t | E73: =+E72+E70 -> 71.675437 | F73: =+F72+F70 -> 71.675437 | H73: =+H72+H70 -> 59.102378 | I73: =+I72+I70 -> 60.11797 | K73: =K54*((1/(K65/100))-1) -> 9.3327737 | L73: =L58*((1/(L65/100))-1) -> 10.937361
B75: Debt& Interest
B76: Total Interest | C76: EGP | E76: 2000000000 | F76: =+F83 -> 4.1298132e+08 | H76: =+H83 -> 2.7363586e+08 | I76: =+I83 -> 2.6552867e+08 | K76: =+K83 -> 1.114151e+08 | L76: =+L83 -> 1.1354289e+08
B77: Interest / t | C77: LE/t | E77: =+(1-5.5/17)*E76/E61 -> 450.98039 | F77: =+F76/F61 -> 344.1511 | H77: =+H76/H61 -> 325.75698 | I77: =+I76/I61 -> 316.10556 | K77: =+K76/K61 -> 309.48638 | L77: =+L76/L61 -> 315.39692
C78: $/t | E78: =+E77/E42 -> 27.838296 | F78: =+F77/F42 -> 21.243895 | H78: =+H77/H42 -> 20.108455 | I78: =+I77/I42 -> 19.512689 | K78: =+K77/K42 -> 19.104097 | L78: =+L77/L42 -> 19.468946
B80: Total COGS + SG&A | C80: $/t | F80: =F17+F19 -> 586.03848 | H80: =H17+H19 -> 554.71601 | I80: =I17+I19 -> 538.28108 | K80: =K17+K19 -> 527.00958 | L80: =L17+L19 -> 537.07437
B81: Debt Level WC 90 DOH Inventory | C81: M EGP | F81: =+F80*F61*F42*90/360 -> 2.848147e+09 | H81: =+H80*H61*H42*90/360 -> 1.8871439e+09 | I81: =+I80*I61*I42*90/360 -> 1.8312322e+09 | K81: =+K80*K61*K42*90/360 -> 7.6837997e+08 | L81: =+L80*L61*L42*90/360 -> 7.8305443e+08
B82: Average Interest Rate | C82: % | F82: 0.145 | H82: 0.145 | I82: 0.145 | K82: 0.145 | L82: 0.145
B83: Interest value | C83: EGP | F83: =+F82*F81 -> 4.1298132e+08 | H83: =+H82*H81 -> 2.7363586e+08 | I83: =+I82*I81 -> 2.6552867e+08 | K83: =+K82*K81 -> 1.114151e+08 | L83: =+L82*L81 -> 1.1354289e+08

Sheet Sheet5
B2: EAF WW | J2: ESR
C3: Unit | D3: Cons/t | E3: Price $ | F3: Fixed | G3: Varible | H3: Total $ | K3: Unit | L3: Cons/t | M3: Price $ | N3: Fixed | O3: Varible | P3: Total $
B4: Scrap | C4: ton | D4: 1.123 | E4: 295 | F4: 0 | G4: =+E4*D4-F4 -> 331.285 | H4: =+G4+F4 -> 331.285 | J4: Scrap | K4: ton | L4: =689.87627028695/1000 -> 0.68987627 | M4: =5851.53553724831/16.3 -> 358.98991 | N4: 0 | O4: =+M4*L4-N4 -> 247.65862 | P4: =+O4+N4 -> 247.65862 | Q4: =+P4*16.3 -> 4036.8355
B5: Scrap Transport | C5: ton | D5: 1.123 | E5: 5 | F5: 0 | G5: =+E5*D5-F5 -> 5.615 | H5: =+G5+F5 -> 5.615 | J5: Scrap Transport | K5: ton | L5: 0 | M5: 0 | N5: 0 | O5: =+M5*L5-N5 -> 0 | P5: =+O5+N5 -> 0 | Q5: =+P5*16.3 -> 0
B6: Pig/DRI | C6: ton | D6: 0 | E6: 333.76 | F6: 0 | G6: =+E6*D6-F6 -> 0 | H6: =+G6+F6 -> 0 | J6: Pig/DRI | K6: ton | L6: =471.359760819623/1000 -> 0.47135976 | M6: =5946.09079077181/16.3 -> 364.79085 | N6: 0 | O6: =+M6*L6-N6 -> 171.94773 | P6: =+O6+N6 -> 171.94773 | Q6: =+P6*16.3 -> 2802.7479
B7: Pig/DRI Transport | C7: ton | D7: 0 | E7: 14 | F7: 0 | G7: =+E7*D7-F7 -> 0 | H7: =+G7+F7 -> 0 | J7: Pig/DRI Transport | K7: ton | L7: 0 | M7: 0 | N7: 0 | O7: =+M7*L7-N7 -> 0 | P7: =+O7+N7 -> 0 | Q7: =+P7*16.3 -> 0
B8: Industrial Gases | C8: Cubic m | D8: 16 | E8: 0.113 | F8: 0 | G8: =+E8*D8-F8 -> 1.808 | H8: =+G8+F8 -> 1.808 | J8: Industrial Gases | K8: Cubic m | L8: 1 | M8: =142.631124321434/16.3 -> 8.7503757 | N8: 0 | O8: =+M8*L8-N8 -> 8.7503757 | P8: =+O8+N8 -> 8.7503757 | Q8: =+P8*16.3 -> 142.63112
B9: Ferroalloys | C9: ton | D9: 0.016 | E9: 1250 | F9: 0 | G9: =+E9*D9-F9 -> 20 | H9: =+G9+F9 -> 20 | J9: Ferroalloys | K9: ton | L9: =21.2015601866151/1000 -> 0.02120156 | M9: =21638.0814465974/16.3 -> 1327.4897 | N9: 0 | O9: =+M9*L9-N9 -> 28.144852 | P9: =+O9+N9 -> 28.144852 | Q9: =+P9*16.3 -> 458.76109
B10: Fluxes | C10: ton | D10: 0.036 | E10: 123 | F10: 0 | G10: =+E10*D10-F10 -> 4.428 | H10: =+G10+F10 -> 4.428 | J10: Fluxes | K10: ton | L10: 0 | M10: 0 | N10: 0 | O10: =+M10*L10-N10 -> 0 | P10: =+O10+N10 -> 0 | Q10: =+P10*16.3 -> 0
B11: Electrodes | C11: ton | D11: 0.002 | E11: 9200 | F11: 0 | G11: =+E11*D11-F11 -> 18.4 | H11: =+G11+F11 -> 18.4 | J11: Electrodes | K11: ton | L11: =1.82856685044683/1000 -> 0.0018285669 | M11: =221779.653102083/16.3 -> 13606.114 | N11: 0 | O11: =+M11*L11-N11 -> 24.879688 | P11: =+O11+N11 -> 24.879688 | Q11: =+P11*16.3 -> 405.53892
B12: Refractories | C12: ton | D12: 0.001 | E12: 1050 | F12: 0 | G12: =+E12*D12-F12 -> 1.05 | H12: =+G12+F12 -> 1.05 | J12: Refractories | K12: ton | L12: =7.67154239185428/1000 -> 0.0076715424 | M12: =16540.4227713778/16.3 -> 1014.7499 | N12: 0 | O12: =+M12*L12-N12 -> 7.7846966 | P12: =+O12+N12 -> 7.7846966 | Q12: =+P12*16.3 -> 126.89055
B13: Others | C13: Unit | D13: 1 | E13: 12 | F13: 3 | G13: =+E13*D13-F13 -> 9 | H13: =+G13+F13 -> 12 | J13: Others | K13: Unit | L13: 1 | M13: =255.251143270712/16.3 -> 15.659579 | N13: 3 | O13: =+M13*L13-N13 -> 12.659579 | P13: =+O13+N13 -> 15.659579 | Q13: =+P13*16.3 -> 255.25114
B14: Thermal Energy | C14: GJ | D14: -0.07 | E14: 9.3 | F14: 0 | G14: =+E14*D14-F14 -> -0.651 | H14: =+G14+F14 -> -0.651 | J14: Thermal Energy | K14: GJ | L14: 0 | M14: 0 | N14: 0 | O14: =+M14*L14-N14 -> 0 | P14: =+O14+N14 -> 0 | Q14: =+P14*16.3 -> 0
B15: Electricity | C15: MWH | D15: 0.44 | E15: 105 | F15: 6.93 | G15: =+E15*D15-F15 -> 39.27 | H15: =+G15+F15 -> 46.2 | J15: Electricity | K15: MWH | L15: =612.830891706478/1000 -> 0.61283089 | M15: =1.06517452608809*1000/16.3 -> 65.34813 | N15: 6.93 | O15: =+M15*L15-N15 -> 33.117353 | P15: =+O15+N15 -> 40.047353 | Q15: =+P15*16.3 -> 652.77185
B16: Labor | C16: Houra | D16: 0.294 | E16: 40.7 | F16: 2.99 | G16: =+E16*D16-F16 -> 8.9758 | H16: =+G16+F16 -> 11.9658 | J16: Labor | K16: Houra | L16: 0 | M16: 0 | N16: =290.840861515616/16.3 -> 17.842998 | O16: 0 | P16: =+O16+N16 -> 17.842998 | Q16: =+P16*16.3 -> 290.84086
B17: Capital Charges | C17: Unit | D17: 1 | E17: 17.49 | F17: 17.49 | G17: =+E17*D17-F17 -> 0 | H17: =+G17+F17 -> 17.49 | J17: Capital Charges | K17: Unit | L17: 0 | M17: 0 | N17: =104.10750553255/16.3 -> 6.3869635 | O17: 0 | P17: =+O17+N17 -> 6.3869635 | Q17: =+P17*16.3 -> 104.10751
B18: Total | F18: =SUM(F4:F17) -> 30.41 | G18: =SUM(G4:G17) -> 439.1808 | H18: =+G18+F18 -> 469.5908 | J18: Total | N18: =SUM(N4:N17) -> 34.159961 | O18: =SUM(O4:O17) -> 534.94289 | P18: =+O18+N18 -> 569.10285 | Q18: =+P18*16.3 -> 9276.3765
B20: Yield | C20: =1/D4 -> 0.89047195 | J20: Yield | K20: =1/(L4+L6) -> 0.86115137
B21: BR DRI | C21: =+D6/(D4+D6) -> 0 | J21: BR DRI | K21: =+L6/(L4+L6) -> 0.4059121

Sheet Sheet6
B4: Items | C4: Units | E4: Integrated
E5: EZDK Actual 18 | F5: Others Actual 18
B6: Mnf Cost | C6: LE/t | E6: =+E30 -> 9466.1922 | F6: =+H33 -> 9790.2423
B7: SG&A | C7: LE/t | E7: =+E31 -> 286.47687 | F7: =+(H24/H21)+230/H21 -> 247.5
B8: Financial Expenses | C8: LE/t | E8: =+E32 -> 573.39858 | F8: =+H25/H21 -> 6.015
B9: Total Fixed | C9: LE/t | E9: =E7+E8 -> 859.87544 | F9: =F7+F8 -> 253.515
B11: Total Production Cost | C11: $/t | E11: =+E12/E17 -> 645.37923 | F11: =+F12/F17 -> 627.73483
C12: LE/t | E12: =+E9+E6 -> 10326.068 | F12: =+F9+F6 -> 10043.757
B14: EBT | C14: LE/t | E14: =+E16-E12 -> 541.37011 | F14: =+F16-F12 -> 214.57607
B16: Selling Price | E16: =+E29 -> 10867.438 | F16: =+H22/H21 -> 10258.333
B17: FX | E17: 16 | F17: 16
B20: EZDK Actual 2018 | C20: LE M | D20: % of total | E20: LE/t | G20: Others Actual 2018
B21: Total sales M t | C21: 3.214 | G21: Total sales M t | H21: 1.2
B22: T.Sales | C22: 36099 | E22: =C22/C21 -> 11231.798 | G22: T.Sales Million EGP | H22: =12310 -> 12310
B23: T.COGS | C23: 30620 | E23: =C23/C21 -> 9527.0691 | G23: T.COGS Million EGP | H23: =11169 -> 11169
B24: T.SG&A | C24: =225.95+593.386 -> 819.336 | E24: =C24/C21 -> 254.92719 | G24: T.SG&A Million EGP | H24: =67 -> 67
B25: Other net operating Exp | C25: =-188.492+321.259 -> 132.767 | E25: =C25/C21 -> 41.308961 | G25: T.Interest Million EGP | H25: =7.218 -> 7.218
B26: Net Interest | C26: 1289 | E26: =C26/C21 -> 401.05787
B27: EBT | C27: =C22-C23-C24-C25-C26-23.015 -> 3214.882 | E27: =C27/C21 -> 1000.2744 | G27: Assuming full rebar production for Others
B28: Rebar Sales M t | C28: =2.02+0.228 -> 2.248 | D28: =C28/C21 -> 0.69943995 | G28: Actual Rebar Sales Million ton | H28: 0.513
B29: Rebar Sales | C29: 24430 | D29: =+C29/C22 -> 0.67675005 | E29: =C29/$C$28 -> 10867.438 | G29: Total Billet Cap Million ton | H29: =H21/0.97 -> 1.2371134
B30: Rebar COGS | C30: =+C29-3150 -> 21280 | D30: =+C30/C23 -> 0.69497061 | E30: =C30/$C$28 -> 9466.1922 | G30: Billet avalible for sale | H30: =+H29-H28 -> 0.7241134
B31: Rebar SG&A | C31: =3150-2506 -> 644 | D31: =C31/C24 -> 0.78600232 | E31: =C31/$C$28 -> 286.47687 | G31: Rolling Exp Million EGP | H31: =+H30*800 -> 579.29072
B32: Rebar Interest * | C32: =+C26 -> 1289 | D32: =+C32/C26 -> 1 | E32: =C32/$C$28 -> 573.39858 | G32: New COGS Million EGP | H32: =+H31+H23 -> 11748.291
B33: EBT | C33: 1605 | D33: =+C33/C27 -> 0.49924072 | E33: =C33/$C$28 -> 713.96797 | G33: New COGS EGP/t | H33: =+H32/H21 -> 9790.2423
B34: * As of 31/12/18 the net interest allocated for rebars where EGP 901 M | G34: New COGS $/t | H34: =H33/F17 -> 611.89014
